Workbook

Sheet Employees List
A1: Months | B1: Employee Code | C1: Date Of Joining | D1: Date Of Rejoining | E1: Name | F1: ESI Number | G1: Bank Name | H1: Account Number | I1: Total Wages 24 - 25 | J1: Total Wages 25 - 26 | K1: No of Days in a Month 2025 | L1: Status
A2: April | B2: AC 01 | E2: BHUVANESHWARAN.V | G2: CUB | H2: 500101011548924 | I2: 60000 | J2: 66000 | K2: 30
A3: May | B3: PR 01 | E3: VASANTHA.E | G3: DBS | H3: 8131010000016959 | I3: 12000 | J3: 14500 | K3: 31
A4: June | B4: PR 02 | E4: GANESH | G4: DBS | H4: 8811010012054879 | I4: 17500 | J4: 18500 | K4: 30
A5: July | B5: PR 03 | E5: ADHIKARI BALIA.A | G5: DBS | H5: 8131010000018948 | I5: 12000 | J5: 13000 | K5: 31
A6: August | B6: PR 04 | E6: RUPESH KISAN | G6: UBI | H6: 411002010024591 | I6: 12000 | J6: 13000 | K6: 31
A7: September | B7: PR 05 | E7: SANJAY BAGARTTI.K | G7: DBS | H7: 8131010000021225 | I7: 12000 | J7: 13000 | K7: 30
A8: October | B8: PR 06 | E8: ARUMUGAM.R | G8: IB | H8: 8031517887 | I8: 19000 | J8: 21500 | K8: 31
A9: November | B9: PR 07 | E9: AMMU.S | G9: IOB | H9: 65801000040238 | I9: 9500 | J9: 10500 | K9: 30
A10: December | B10: PR 08 | E10: REVATHI.S | G10: DBS | H10: 8131010000016995 | I10: 9500 | J10: 10500 | K10: 31
A11: January | B11: PR 09 | E11: ABINAYA.V | I11: 9000 | J11: 9000 | K11: 31
A12: February | B12: PR 10 | E12: ANITHA.P | G12: IB | H12: 8054094602 | I12: 9000 | J12: 10000 | K12: 28
A13: March | B13: PR 11 | I13: 8000 | J13: 8000 | K13: 31
A14: All | B14: PR 12 | E14: PINU | G14: DBS | H14: 8131010000018814 | I14: 11000 | J14: 11000
B15: PR 13 | E15: SAMSON BODRA.P | G15: UBI | H15: 411002120007276 | I15: 10500 | J15: 11000
B16: PR 14 | E16: REVATHI.V | G16: SBI | H16: 41581902830 | I16: 9000 | J16: 10000
B17: PR 15 | E17: BHAVANI.J | G17: KVB | H17: 1616194000000849 | I17: 9000 | J17: 10000
B18: PR 16 | I18: 8000 | J18: 8000
B19: AC 02 | E19: THIRIPURA SUNDARI.R | G19: DBS | H19: 8131010000016977 | I19: 18000 | J19: 21000
B20: AC 03 | E20: LEELAVATHI.M | G20: DBS | H20: 8387010000017745 | I20: 13000 | J20: 14000
B21: DR 01 | E21: ILAMATHIVANAN.S | G21: DBS | H21: 8131010000016986 | I21: 20000 | J21: 21000
B22: PR 17 | I22: 9250 | J22: 9250
B23: PR 18 | I23: 11000 | J23: 11000
B24: PR 19 | E24: SIDHESWAR PRADHAN | G24: DBS | H24: 8131010000018939 | I24: 10500 | J24: 10500
B25: PR 20 | G25: DBS | H25: 8131010000018920 | I25: 12000 | J25: 12000
B26: PR 21 | E26: LIPAN | G26: DBS | H26: 8131010000018957 | I26: 12000 | J26: 13000
B27: PR 22 | I27: 10000 | J27: 10000
B28: PR 23 | I28: 10000 | J28: 10000
B29: PR 24 | E29: NILAMANI KISAN.B | G29: SBI | H29: 38254473147 | I29: 11000 | J29: 12000
B30: PR 25 | I30: 16000 | J30: 16000
B31: PR 26 | I31: 10000 | J31: 10000
B32: PR 27 | E32: PARSHU BAGH | G32: SBI | H32: 40653547928 | I32: 12000 | J32: 13000
B33: PR 28 | E33: GANESH KISAN.B | I33: 10000 | J33: 10000
B34: PR 29 | E34: MADHAN | I34: 14000 | J34: 14000
B35: PR 30 | E35: PRAKASH | H35: 2521711617363 | I35: 10000 | J35: 11000
B36: PR 31 | E36: RANJAN BAGH.A | H36: 411002010021257 | I36: 10000 | J36: 10000 | M36: IFSC : UBIN0541109
B37: PR 32 | E37: AMARNGTH KISAN.A | G37: IPOS | H37: 39810019872 | I37: 10000 | J37: 10000
B38: PR 33 | E38: SURUBABU ANGRIA.M | I38: 10000 | J38: 10000
B39: PR 34 | E39: PANKAJ BAGH.K | G39: SBI | H39: 34210836103 | I39: 10000 | J39: 10000
B40: PR 35 | E40: PRINCE BADRA | I40: 10000 | J40: 10000
B41: PR 36 | E41: DILIP KUMAR.S | G41: OGB | H41: 56134001006549 | I41: 10000 | J41: 10000
B42: PR 37 | E42: SURESH.S | G42: CB | H42: 2915101004645 | I42: 17000 | J42: 18000
B43: PR 38 | C43: 45768 | E43: DURYODHAN | G43: SBI | H43: 37603882610 | I43: 10000 | J43: 10000
B44: PR 39 | C44: 45768 | E44: UTTAM KISAN | G44: G-Pay | H44: ADHI-8260139733 | I44: 9000 | J44: 10000
B45: PR 40 | C45: 45768 | E45: BIDYADHAR BAG | I45: 10000 | J45: 10000
B46: PR 41 | C46: 45845 | E46: ANUBHAB DEHURY.D | J46: 9500
B47: PR 42 | C47: 45854 | E47: SENTHAMILSELVI | G47: SBI | H47: 40027391096 | J47: 10000
B48: PR 43 | E48: PRABHU | G48: SBI | H48: 38629076963 | J48: 13750
B49: PR 44 | C49: 45901 | E49: ASHOK RAJAHANS | G49: UBI | H49: 411002120003687 | J49: 10000
B50: PR 45 | C50: 45901 | E50: ANUVAB SANDHA | J50: 10000
B51: PR 46 | C51: 45908 | E51: LIPUN BANICHULA | G51: HDFC | H51: 50100494695123 | J51: 10000
B52: PR 47 | C52: 45908 | E52: KISHOR SANDHA | J52: 10000
B53: PR 48 | C53: 45908 | E53: RANJIT MUNDA | G53: SBI | H53: 36792923178 | J53: 10000
B54: PR 49 | E54: KRUSHNA MUNDA | G54: IB | H54: 7970941169 | J54: 10000
B55: PR 50 | E55: MADHAN MOHAN SINGH | J55: 14000
B56: PR 51 | E56: PRATAP DAS | J56: 10000
B57: PR 52 | E57: SIPUN MIRDHA | H57: 7848907618 | J57: 10500
B58: PR 53 | E58: DIPAN MIRDHA | G58: SBI | H58: 36793508559 | J58: 10500
B59: PR 54 | E59: GAGAN MIRDHA | G59: SBI | H59: 44366251746 | J59: 10500
B60: PR 55 | E60: NABA SANDHA | H60: 8144533466 | J60: 10500
B61: PR 56 | E61: SILU | G61: SBI | H61: 4124699337 | J61: 10500
B62: PR 57 | E62: PITABAS PRADHAN | G62: G-Pay | H62: Silu - 9827962745 | J62: 10000

Sheet Daily Attendance 25-26
F1: 1 | H1: 2 | J1: 3 | L1: 4 | N1: 5 | P1: 6 | R1: 7 | T1: 8 | V1: 9 | X1: 10 | Z1: 11 | AB1: 12 | AD1: 13 | AF1: 14 | AH1: 15 | AJ1: 16 | AL1: 17 | AN1: 18 | AP1: 19 | AR1: 20 | AT1: 21 | AV1: 22 | AX1: 23 | AZ1: 24 | BB1: 25 | BD1: 26 | BF1: 27 | BH1: 28 | BJ1: 29 | BL1: 30 | BN1: 31
C2: 45748
C3: Employee Code | D3: Name | E3: Days Present / OT Hours | F3: M | G3: A | H3: M | I3: A | J3: M | K3: A | L3: M | M3: A | N3: M | O3: A | P3: M | Q3: A | R3: M | S3: A | T3: M | U3: A | V3: M | W3: A | X3: M | Y3: A | Z3: M | AA3: A | AB3: M | AC3: A | AD3: M | AE3: A | AF3: M | AG3: A | AH3: M | AI3: A | AJ3: M | AK3: A | AL3: M | AM3: A | AN3: M | AO3: A | AP3: M | AQ3: A | AR3: M | AS3: A | AT3: M | AU3: A | AV3: M | AW3: A | AX3: M | AY3: A | AZ3: M | BA3: A | BB3: M | BC3: A | BD3: M | BE3: A | BF3: M | BG3: A | BH3: M | BI3: A | BJ3: M | BK3: A | BL3: M | BM3: A | BN3: M | BO3: A
A4: =B4&D4 -> AprilBHUVANESHWARAN.V | B4: April | C4: AC 01 | D4: =IFERROR(VLOOKUP(C4,'Employees List'!$B$2:$E1424,4,0),"") -> BHUVANESHWARAN.V | E4: =COUNTIF(F4:BO4,TRUE)/2 -> 30 | F4: TRUE | G4: TRUE | H4: TRUE | I4: TRUE | J4: TRUE | K4: TRUE | L4: TRUE | M4: TRUE | N4: TRUE | O4: TRUE | P4: TRUE | Q4: TRUE | R4: TRUE | S4: TRUE | T4: TRUE | U4: TRUE | V4: TRUE | W4: TRUE | X4: TRUE | Y4: TRUE | Z4: TRUE | AA4: TRUE | AB4: TRUE | AC4: TRUE | AD4: TRUE | AE4: TRUE | AF4: TRUE | AG4: TRUE | AH4: TRUE | AI4: TRUE | AJ4: TRUE | AK4: TRUE | AL4: TRUE | AM4: TRUE | AN4: TRUE | AO4: TRUE | AP4: TRUE | AQ4: TRUE | AR4: TRUE | AS4: TRUE | AT4: TRUE | AU4: TRUE | AV4: TRUE | AW4: TRUE | AX4: TRUE | AY4: TRUE | AZ4: TRUE | BA4: TRUE | BB4: TRUE | BC4: TRUE | BD4: TRUE | BE4: TRUE | BF4: TRUE | BG4: TRUE | BH4: TRUE | BI4: TRUE | BJ4: TRUE | BK4: TRUE | BL4: TRUE | BM4: TRUE | BN4: FALSE | BO4: FALSE
A5: =A4&C5 -> AprilBHUVANESHWARAN.VOT HOURS | C5: OT HOURS | E5: =SUM($F$5:$BO$5) -> 0
A6: =B6&D6 -> AprilTHIRIPURA SUNDARI.R | B6: April | C6: AC 02 | D6: =IFERROR(VLOOKUP(C6,'Employees List'!$B$2:$E1424,4,0),"") -> THIRIPURA SUNDARI.R | E6: =COUNTIF(F6:BO6,TRUE)/2 -> 30 | F6: TRUE | G6: TRUE | H6: TRUE | I6: TRUE | J6: TRUE | K6: TRUE | L6: TRUE | M6: TRUE | N6: TRUE | O6: TRUE | P6: TRUE | Q6: TRUE | R6: TRUE | S6: TRUE | T6: TRUE | U6: TRUE | V6: TRUE | W6: TRUE | X6: TRUE | Y6: TRUE | Z6: TRUE | AA6: TRUE | AB6: TRUE | AC6: TRUE | AD6: TRUE | AE6: TRUE | AF6: TRUE | AG6: TRUE | AH6: TRUE | AI6: TRUE | AJ6: TRUE | AK6: TRUE | AL6: TRUE | AM6: TRUE | AN6: TRUE | AO6: TRUE | AP6: TRUE | AQ6: TRUE | AR6: TRUE | AS6: TRUE | AT6: TRUE | AU6: TRUE | AV6: TRUE | AW6: TRUE | AX6: TRUE | AY6: TRUE | AZ6: TRUE | BA6: TRUE | BB6: TRUE | BC6: TRUE | BD6: TRUE | BE6: TRUE | BF6: TRUE | BG6: TRUE | BH6: TRUE | BI6: TRUE | BJ6: TRUE | BK6: TRUE | BL6: TRUE | BM6: TRUE | BN6: FALSE | BO6: FALSE
A7: =A6&C7 -> AprilTHIRIPURA SUNDARI.ROT HOURS | C7: OT HOURS | E7: =SUM($F$7:$BO$7) -> 8 | J7: 1 | X7: 1 | AJ7: 1 | AL7: 1 | AP7: 1 | AZ7: 1 | BB7: 1 | BH7: 1
A8: =B8&D8 -> AprilGANESH | B8: April | C8: PR 02 | D8: =IFERROR(VLOOKUP(C8,'Employees List'!$B$2:$E1424,4,0),"") -> GANESH | E8: =COUNTIF(F8:BO8,TRUE)/2 -> 22 | F8: TRUE | G8: TRUE | H8: FALSE | I8: FALSE | J8: FALSE | K8: FALSE | L8: TRUE | M8: TRUE | N8: TRUE | O8: TRUE | P8: TRUE | Q8: TRUE | R8: TRUE | S8: TRUE | T8: TRUE | U8: TRUE | V8: TRUE | W8: TRUE | X8: FALSE | Y8: FALSE | Z8: FALSE | AA8: FALSE | AB8: FALSE | AC8: FALSE | AD8: FALSE | AE8: FALSE | AF8: FALSE | AG8: FALSE | AH8: FALSE | AI8: FALSE | AJ8: TRUE | AK8: TRUE | AL8: TRUE | AM8: TRUE | AN8: TRUE | AO8: TRUE | AP8: TRUE | AQ8: TRUE | AR8: TRUE | AS8: TRUE | AT8: TRUE | AU8: TRUE | AV8: TRUE | AW8: TRUE | AX8: TRUE | AY8: TRUE | AZ8: TRUE | BA8: TRUE | BB8: TRUE | BC8: TRUE | BD8: TRUE | BE8: TRUE | BF8: TRUE | BG8: TRUE | BH8: TRUE | BI8: TRUE | BJ8: TRUE | BK8: TRUE | BL8: TRUE | BM8: TRUE | BN8: FALSE | BO8: FALSE
A9: =A8&C9 -> AprilGANESHOT HOURS | C9: OT HOURS | E9: =SUM($F$9:$BO$9) -> 22 | N9: 2 | AJ9: 2 | AL9: 2 | AN9: 3 | AP9: 3 | AR9: 2 | AT9: 3 | AZ9: 2 | BJ9: 3
A10: =B10&D10 -> AprilILAMATHIVANAN.S | B10: April | C10: DR 01 | D10: =IFERROR(VLOOKUP(C10,'Employees List'!$B$2:$E1424,4,0),"") -> ILAMATHIVANAN.S | E10: =COUNTIF(F10:BO10,TRUE)/2 -> 23 | F10: TRUE | G10: TRUE | H10: TRUE | I10: TRUE | J10: TRUE | K10: TRUE | L10: TRUE | M10: TRUE | N10: TRUE | O10: TRUE | P10: TRUE | Q10: TRUE | R10: FALSE | S10: FALSE | T10: TRUE | U10: TRUE | V10: TRUE | W10: TRUE | X10: TRUE | Y10: TRUE | Z10: FALSE | AA10: FALSE | AB10: FALSE | AC10: FALSE | AD10: FALSE | AE10: FALSE | AF10: FALSE | AG10: FALSE | AH10: FALSE | AI10: FALSE | AJ10: TRUE | AK10: TRUE | AL10: TRUE | AM10: TRUE | AN10: TRUE | AO10: TRUE | AP10: TRUE | AQ10: TRUE | AR10: TRUE | AS10: TRUE | AT10: FALSE | AU10: FALSE | AV10: TRUE | AW10: TRUE | AX10: TRUE | AY10: TRUE | AZ10: TRUE | BA10: TRUE | BB10: TRUE | BC10: TRUE | BD10: TRUE | BE10: TRUE | BF10: TRUE | BG10: TRUE | BH10: TRUE | BI10: TRUE | BJ10: TRUE | BK10: TRUE | BL10: TRUE | BM10: TRUE | BN10: FALSE | BO10: FALSE
A11: =A10&C11 -> AprilILAMATHIVANAN.SOT HOURS | C11: OT HOURS | E11: =SUM(F11:BO11) -> 41 | F11: 1 | H11: 2 | N11: 2 | T11: 1 | V11: 3 | AJ11: 4 | AL11: 4 | AN11: 1 | AP11: 4 | AV11: 5 | AX11: 1 | AZ11: 3 | BD11: 2 | BH11: 1 | BJ11: 5 | BL11: 2
A12: =B12&D12 -> AprilAMMU.S | B12: April | C12: PR 07 | D12: =IFERROR(VLOOKUP(C12,'Employees List'!$B$2:$E1424,4,0),"") -> AMMU.S | E12: =COUNTIF(F12:BO12,TRUE)/2 -> 30 | F12: TRUE | G12: TRUE | H12: TRUE | I12: TRUE | J12: TRUE | K12: TRUE | L12: TRUE | M12: TRUE | N12: TRUE | O12: TRUE | P12: TRUE | Q12: TRUE | R12: TRUE | S12: TRUE | T12: TRUE | U12: TRUE | V12: TRUE | W12: TRUE | X12: TRUE | Y12: TRUE | Z12: TRUE | AA12: TRUE | AB12: TRUE | AC12: TRUE | AD12: TRUE | AE12: TRUE | AF12: TRUE | AG12: TRUE | AH12: TRUE | AI12: TRUE | AJ12: TRUE | AK12: TRUE | AL12: TRUE | AM12: TRUE | AN12: TRUE | AO12: TRUE | AP12: TRUE | AQ12: TRUE | AR12: TRUE | AS12: TRUE | AT12: TRUE | AU12: TRUE | AV12: TRUE | AW12: TRUE | AX12: TRUE | AY12: TRUE | AZ12: TRUE | BA12: TRUE | BB12: TRUE | BC12: TRUE | BD12: TRUE | BE12: TRUE | BF12: TRUE | BG12: TRUE | BH12: TRUE | BI12: TRUE | BJ12: TRUE | BK12: TRUE | BL12: TRUE | BM12: TRUE | BN12: FALSE | BO12: FALSE
A13: =A12&C13 -> AprilAMMU.SOT HOURS | C13: OT HOURS | E13: =SUM(F13:BO13) -> 11 | AJ13: 2 | AL13: 1 | AP13: 2 | AT13: 2 | AV13: 2 | BJ13: 2
A14: =B14&D14 -> AprilREVATHI.S | B14: April | C14: PR 08 | D14: =IFERROR(VLOOKUP(C14,'Employees List'!$B$2:$E1424,4,0),"") -> REVATHI.S | E14: =COUNTIF(F14:BO14,TRUE)/2 -> 29 | F14: FALSE | G14: FALSE | H14: TRUE | I14: TRUE | J14: TRUE | K14: TRUE | L14: TRUE | M14: TRUE | N14: TRUE | O14: TRUE | P14: TRUE | Q14: TRUE | R14: TRUE | S14: TRUE | T14: TRUE | U14: TRUE | V14: TRUE | W14: TRUE | X14: TRUE | Y14: TRUE | Z14: TRUE | AA14: TRUE | AB14: TRUE | AC14: TRUE | AD14: TRUE | AE14: TRUE | AF14: TRUE | AG14: TRUE | AH14: TRUE | AI14: TRUE | AJ14: TRUE | AK14: TRUE | AL14: TRUE | AM14: TRUE | AN14: TRUE | AO14: TRUE | AP14: TRUE | AQ14: TRUE | AR14: TRUE | AS14: TRUE | AT14: TRUE | AU14: TRUE | AV14: TRUE | AW14: TRUE | AX14: TRUE | AY14: TRUE | AZ14: TRUE | BA14: TRUE | BB14: TRUE | BC14: TRUE | BD14: TRUE | BE14: TRUE | BF14: TRUE | BG14: TRUE | BH14: TRUE | BI14: TRUE | BJ14: TRUE | BK14: TRUE | BL14: TRUE | BM14: TRUE | BN14: FALSE | BO14: FALSE
A15: =A14&C15 -> AprilREVATHI.SOT HOURS | C15: OT HOURS | E15: =SUM(F15:BO15) -> 9 | AJ15: 2 | AL15: 1 | AP15: 2 | AV15: 2 | BJ15: 2
A16: =B16&D16 -> AprilLEELAVATHI.M | B16: April | C16: AC 03 | D16: =IFERROR(VLOOKUP(C16,'Employees List'!$B$2:$E1424,4,0),"") -> LEELAVATHI.M | E16: =COUNTIF(F16:BO16,TRUE)/2 -> 30 | F16: TRUE | G16: TRUE | H16: TRUE | I16: TRUE | J16: TRUE | K16: TRUE | L16: TRUE | M16: TRUE | N16: TRUE | O16: TRUE | P16: TRUE | Q16: TRUE | R16: TRUE | S16: TRUE | T16: TRUE | U16: TRUE | V16: TRUE | W16: TRUE | X16: TRUE | Y16: TRUE | Z16: TRUE | AA16: TRUE | AB16: TRUE | AC16: TRUE | AD16: TRUE | AE16: TRUE | AF16: TRUE | AG16: TRUE | AH16: TRUE | AI16: TRUE | AJ16: TRUE | AK16: TRUE | AL16: TRUE | AM16: TRUE | AN16: TRUE | AO16: TRUE | AP16: TRUE | AQ16: TRUE | AR16: TRUE | AS16: TRUE | AT16: TRUE | AU16: TRUE | AV16: TRUE | AW16: TRUE | AX16: TRUE | AY16: TRUE | AZ16: TRUE | BA16: TRUE | BB16: TRUE | BC16: TRUE | BD16: TRUE | BE16: TRUE | BF16: TRUE | BG16: TRUE | BH16: TRUE | BI16: TRUE | BJ16: TRUE | BK16: TRUE | BL16: TRUE | BM16: TRUE | BN16: FALSE | BO16: FALSE
A17: =A16&C17 -> AprilLEELAVATHI.MOT HOURS | C17: OT HOURS | E17: =SUM(F17:BO17) -> 3 | AJ17: 1 | AL17: 1 | AT17: 1
A18: =B18&D18 -> AprilPARSHU BAGH | B18: April | C18: PR 27 | D18: =IFERROR(VLOOKUP(C18,'Employees List'!$B$2:$E1424,4,0),"") -> PARSHU BAGH | E18: =COUNTIF(F18:BO18,TRUE)/2 -> 9 | F18: TRUE | G18: TRUE | H18: TRUE | I18: TRUE | J18: TRUE | K18: TRUE | L18: TRUE | M18: TRUE | N18: TRUE | O18: TRUE | P18: TRUE | Q18: TRUE | R18: TRUE | S18: TRUE | T18: TRUE | U18: TRUE | V18: TRUE | W18: TRUE | X18: FALSE | Y18: FALSE | Z18: FALSE | AA18: FALSE | AB18: FALSE | AC18: FALSE | AD18: FALSE | AE18: FALSE | AF18: FALSE | AG18: FALSE | AH18: FALSE | AI18: FALSE | AJ18: FALSE | AK18: FALSE | AL18: FALSE | AM18: FALSE | AN18: FALSE | AO18: FALSE | AP18: FALSE | AQ18: FALSE | AR18: FALSE | AS18: FALSE | AT18: FALSE | AU18: FALSE | AV18: FALSE | AW18: FALSE | AX18: FALSE | AY18: FALSE | AZ18: FALSE | BA18: FALSE | BB18: FALSE | BC18: FALSE | BD18: FALSE | BE18: FALSE | BF18: FALSE | BG18: FALSE | BH18: FALSE | BI18: FALSE | BJ18: FALSE | BK18: FALSE | BL18: FALSE | BM18: FALSE | BN18: FALSE | BO18: FALSE
A19: =A18&C19 -> AprilPARSHU BAGHOT HOURS | C19: OT HOURS | E19: =SUM(F19:BO19) -> 2 | N19: 2
A20: =B20&D20 -> AprilPINU | B20: April | C20: PR 12 | D20: =IFERROR(VLOOKUP(C20,'Employees List'!$B$2:$E1424,4,0),"") -> PINU | E20: =COUNTIF(F20:BO20,TRUE)/2 -> 9 | F20: TRUE | G20: TRUE | H20: TRUE | I20: TRUE | J20: TRUE | K20: TRUE | L20: TRUE | M20: TRUE | N20: TRUE | O20: TRUE | P20: TRUE | Q20: TRUE | R20: TRUE | S20: TRUE | T20: TRUE | U20: TRUE | V20: TRUE | W20: TRUE | X20: FALSE | Y20: FALSE | Z20: FALSE | AA20: FALSE | AB20: FALSE | AC20: FALSE | AD20: FALSE | AE20: FALSE | AF20: FALSE | AG20: FALSE | AH20: FALSE | AI20: FALSE | AJ20: FALSE | AK20: FALSE | AL20: FALSE | AM20: FALSE | AN20: FALSE | AO20: FALSE | AP20: FALSE | AQ20: FALSE | AR20: FALSE | AS20: FALSE | AT20: FALSE | AU20: FALSE | AV20: FALSE | AW20: FALSE | AX20: FALSE | AY20: FALSE | AZ20: FALSE | BA20: FALSE | BB20: FALSE | BC20: FALSE | BD20: FALSE | BE20: FALSE | BF20: FALSE | BG20: FALSE | BH20: FALSE | BI20: FALSE | BJ20: FALSE | BK20: FALSE | BL20: FALSE | BM20: FALSE | BN20: FALSE | BO20: FALSE
A21: =A20&C21 -> AprilPINU OT HOURS | C21: OT HOURS | E21: =SUM(F21:BO21) -> 15 | F21: 2 | H21: 5 | L21: 4 | N21: 2 | R21: 2
A22: =B22&D22 -> AprilSANJAY BAGARTTI.K | B22: April | C22: PR 05 | D22: =IFERROR(VLOOKUP(C22,'Employees List'!$B$2:$E1424,4,0),"") -> SANJAY BAGARTTI.K | E22: =COUNTIF(F22:BO22,TRUE)/2 -> 30 | F22: TRUE | G22: TRUE | H22: TRUE | I22: TRUE | J22: TRUE | K22: TRUE | L22: TRUE | M22: TRUE | N22: TRUE | O22: TRUE | P22: TRUE | Q22: TRUE | R22: TRUE | S22: TRUE | T22: TRUE | U22: TRUE | V22: TRUE | W22: TRUE | X22: TRUE | Y22: TRUE | Z22: TRUE | AA22: TRUE | AB22: TRUE | AC22: TRUE | AD22: TRUE | AE22: TRUE | AF22: TRUE | AG22: TRUE | AH22: TRUE | AI22: TRUE | AJ22: TRUE | AK22: TRUE | AL22: TRUE | AM22: TRUE | AN22: TRUE | AO22: TRUE | AP22: TRUE | AQ22: TRUE | AR22: TRUE | AS22: TRUE | AT22: TRUE | AU22: TRUE | AV22: TRUE | AW22: TRUE | AX22: TRUE | AY22: TRUE | AZ22: TRUE | BA22: TRUE | BB22: TRUE | BC22: TRUE | BD22: TRUE | BE22: TRUE | BF22: TRUE | BG22: TRUE | BH22: TRUE | BI22: TRUE | BJ22: TRUE | BK22: TRUE | BL22: TRUE | BM22: TRUE | BN22: FALSE | BO22: FALSE
A23: =A22&C23 -> AprilSANJAY BAGARTTI.KOT HOURS | C23: OT HOURS | E23: =SUM(F23:BO23) -> 87 | F23: 2 | H23: 2 | L23: 2 | N23: 2 | P23: 3 | R23: 2 | T23: 3 | V23: 2 | X23: 3 | Z23: 2 | AB23: 2 | AH23: 6 | AJ23: 4 | AL23: 2 | AN23: 4 | AP23: 6 | AT23: 7 | AV23: 8 | AX23: 6 | AZ23: 4 | BB23: 2 | BD23: 6 | BJ23: 3 | BL23: 4
A24: =B24&D24 -> AprilADHIKARI BALIA.A | B24: April | C24: PR 03 | D24: =IFERROR(VLOOKUP(C24,'Employees List'!$B$2:$E1424,4,0),"") -> ADHIKARI BALIA.A | E24: =COUNTIF(F24:BO24,TRUE)/2 -> 10 | F24: FALSE | G24: FALSE | H24: FALSE | I24: FALSE | J24: FALSE | K24: FALSE | L24: FALSE | M24: FALSE | N24: FALSE | O24: FALSE | P24: FALSE | Q24: FALSE | R24: FALSE | S24: FALSE | T24: FALSE | U24: FALSE | V24: FALSE | W24: FALSE | X24: FALSE | Y24: FALSE | Z24: FALSE | AA24: FALSE | AB24: FALSE | AC24: FALSE | AD24: FALSE | AE24: FALSE | AF24: FALSE | AG24: FALSE | AH24: FALSE | AI24: FALSE | AJ24: FALSE | AK24: FALSE | AL24: FALSE | AM24: FALSE | AN24: FALSE | AO24: FALSE | AP24: FALSE | AQ24: FALSE | AR24: FALSE | AS24: FALSE | AT24: TRUE | AU24: TRUE | AV24: TRUE | AW24: TRUE | AX24: TRUE | AY24: TRUE | AZ24: TRUE | BA24: TRUE | BB24: TRUE | BC24: TRUE | BD24: TRUE | BE24: TRUE | BF24: TRUE | BG24: TRUE | BH24: TRUE | BI24: TRUE | BJ24: TRUE | BK24: TRUE | BL24: TRUE | BM24: TRUE | BN24: FALSE | BO24: FALSE
A25: =A24&C25 -> AprilADHIKARI BALIA.AOT HOURS | C25: OT HOURS | E25: =SUM(F25:BO25) -> 34 | AT25: 5 | AV25: 8 | AX25: 4 | AZ25: 4 | BD25: 6 | BJ25: 3 | BL25: 4
A26: =B26&D26 -> AprilRUPESH KISAN | B26: April | C26: PR 04 | D26: =IFERROR(VLOOKUP(C26,'Employees List'!$B$2:$E1424,4,0),"") -> RUPESH KISAN | E26: =COUNTIF(F26:BO26,TRUE)/2 -> 10 | F26: FALSE | G26: FALSE | H26: FALSE | I26: FALSE | J26: FALSE | K26: FALSE | L26: FALSE | M26: FALSE | N26: FALSE | O26: FALSE | P26: FALSE | Q26: FALSE | R26: FALSE | S26: FALSE | T26: FALSE | U26: FALSE | V26: FALSE | W26: FALSE | X26: FALSE | Y26: FALSE | Z26: FALSE | AA26: FALSE | AB26: FALSE | AC26: FALSE | AD26: FALSE | AE26: FALSE | AF26: FALSE | AG26: FALSE | AH26: FALSE | AI26: FALSE | AJ26: FALSE | AK26: FALSE | AL26: FALSE | AM26: FALSE | AN26: FALSE | AO26: FALSE | AP26: FALSE | AQ26: FALSE | AR26: FALSE | AS26: FALSE | AT26: TRUE | AU26: TRUE | AV26: TRUE | AW26: TRUE | AX26: TRUE | AY26: TRUE | AZ26: TRUE | BA26: TRUE | BB26: TRUE | BC26: TRUE | BD26: TRUE | BE26: TRUE | BF26: TRUE | BG26: TRUE | BH26: TRUE | BI26: TRUE | BJ26: TRUE | BK26: TRUE | BL26: TRUE | BM26: TRUE | BN26: FALSE | BO26: FALSE
A27: =A26&C27 -> AprilRUPESH KISANOT HOURS | C27: OT HOURS | E27: =SUM(F27:BO27) -> 24 | AT27: 3 | AV27: 2 | AX27: 6 | AZ27: 6 | BJ27: 3 | BL27: 4
A28: =B28&D28 -> AprilLIPAN | B28: April | C28: PR 21 | D28: =IFERROR(VLOOKUP(C28,'Employees List'!$B$2:$E1424,4,0),"") -> LIPAN | E28: =COUNTIF(F28:BO28,TRUE)/2 -> 10 | F28: FALSE | G28: FALSE | H28: FALSE | I28: FALSE | J28: FALSE | K28: FALSE | L28: FALSE | M28: FALSE | N28: FALSE | O28: FALSE | P28: FALSE | Q28: FALSE | R28: FALSE | S28: FALSE | T28: FALSE | U28: FALSE | V28: FALSE | W28: FALSE | X28: FALSE | Y28: FALSE | Z28: FALSE | AA28: FALSE | AB28: FALSE | AC28: FALSE | AD28: FALSE | AE28: FALSE | AF28: FALSE | AG28: FALSE | AH28: FALSE | AI28: FALSE | AJ28: FALSE | AK28: FALSE | AL28: FALSE | AM28: FALSE | AN28: FALSE | AO28: FALSE | AP28: FALSE | AQ28: FALSE | AR28: FALSE | AS28: FALSE | AT28: TRUE | AU28: TRUE | AV28: TRUE | AW28: TRUE | AX28: TRUE | AY28: TRUE | AZ28: TRUE | BA28: TRUE | BB28: TRUE | BC28: TRUE | BD28: TRUE | BE28: TRUE | BF28: TRUE | BG28: TRUE | BH28: TRUE | BI28: TRUE | BJ28: TRUE | BK28: TRUE | BL28: TRUE | BM28: TRUE | BN28: FALSE | BO28: FALSE
A29: =A28&C29 -> AprilLIPANOT HOURS | C29: OT HOURS | E29: =SUM(F29:BO29) -> 38 | AT29: 5 | AV29: 8 | AX29: 6 | AZ29: 6 | BD29: 6 | BJ29: 3 | BL29: 4
A30: =B30&D30 -> AprilNILAMANI KISAN.B | B30: April | C30: PR 24 | D30: =IFERROR(VLOOKUP(C30,'Employees List'!$B$2:$E1424,4,0),"") -> NILAMANI KISAN.B | E30: =COUNTIF(F30:BO30,TRUE)/2 -> 27 | F30: FALSE | G30: FALSE | H30: FALSE | I30: FALSE | J30: FALSE | K30: FALSE | L30: TRUE | M30: TRUE | N30: TRUE | O30: TRUE | P30: TRUE | Q30: TRUE | R30: TRUE | S30: TRUE | T30: TRUE | U30: TRUE | V30: TRUE | W30: TRUE | X30: TRUE | Y30: TRUE | Z30: TRUE | AA30: TRUE | AB30: TRUE | AC30: TRUE | AD30: TRUE | AE30: TRUE | AF30: TRUE | AG30: TRUE | AH30: TRUE | AI30: TRUE | AJ30: TRUE | AK30: TRUE | AL30: TRUE | AM30: TRUE | AN30: TRUE | AO30: TRUE | AP30: TRUE | AQ30: TRUE | AR30: TRUE | AS30: TRUE | AT30: TRUE | AU30: TRUE | AV30: TRUE | AW30: TRUE | AX30: TRUE | AY30: TRUE | AZ30: TRUE | BA30: TRUE | BB30: TRUE | BC30: TRUE | BD30: TRUE | BE30: TRUE | BF30: TRUE | BG30: TRUE | BH30: TRUE | BI30: TRUE | BJ30: TRUE | BK30: TRUE | BL30: TRUE | BM30: TRUE | BN30: FALSE | BO30: FALSE
A31: =A30&C31 -> AprilNILAMANI KISAN.BOT HOURS | C31: OT HOURS | E31: =SUM(F31:BO31) -> 40 | N31: 2 | R31: 2 | T31: 2 | V31: 2 | X31: 2 | AH31: 2 | AJ31: 4 | AL31: 2 | AN31: 4 | AP31: 6 | AT31: 3 | AV31: 2 | AX31: 2 | AZ31: 2 | BJ31: 3
C34: 45778
C35: Employee Code | D35: Name | E35: Days Present / OT Hours | F35: M | G35: A | H35: M | I35: A | J35: M | K35: A | L35: M | M35: A | N35: M | O35: A | P35: M | Q35: A | R35: M | S35: A | T35: M | U35: A | V35: M | W35: A | X35: M | Y35: A | Z35: M | AA35: A | AB35: M | AC35: A | AD35: M | AE35: A | AF35: M | AG35: A | AH35: M | AI35: A | AJ35: M | AK35: A | AL35: M | AM35: A | AN35: M | AO35: A | AP35: M | AQ35: A | AR35: M | AS35: A | AT35: M | AU35: A | AV35: M | AW35: A | AX35: M | AY35: A | AZ35: M | BA35: A | BB35: M | BC35: A | BD35: M | BE35: A | BF35: M | BG35: A | BH35: M | BI35: A | BJ35: M | BK35: A | BL35: M | BM35: A | BN35: M | BO35: A
A36: =B36&D36 -> MayBHUVANESHWARAN.V | B36: May | C36: AC 01 | D36: =IFERROR(VLOOKUP(C36,'Employees List'!$B$2:$E1424,4,0),"") -> BHUVANESHWARAN.V | E36: =COUNTIF(F36:BO36,TRUE)/2 -> 31 | F36: TRUE | G36: TRUE | H36: TRUE | I36: TRUE | J36: TRUE | K36: TRUE | L36: TRUE | M36: TRUE | N36: TRUE | O36: TRUE | P36: TRUE | Q36: TRUE | R36: TRUE | S36: TRUE | T36: TRUE | U36: TRUE | V36: TRUE | W36: TRUE | X36: TRUE | Y36: TRUE | Z36: TRUE | AA36: TRUE | AB36: TRUE | AC36: TRUE | AD36: TRUE | AE36: TRUE | AF36: TRUE | AG36: TRUE | AH36: TRUE | AI36: TRUE | AJ36: TRUE | AK36: TRUE | AL36: TRUE | AM36: TRUE | AN36: TRUE | AO36: TRUE | AP36: TRUE | AQ36: TRUE | AR36: TRUE | AS36: TRUE | AT36: TRUE | AU36: TRUE | AV36: TRUE | AW36: TRUE | AX36: TRUE | AY36: TRUE | AZ36: TRUE | BA36: TRUE | BB36: TRUE | BC36: TRUE | BD36: TRUE | BE36: TRUE | BF36: TRUE | BG36: TRUE | BH36: TRUE | BI36: TRUE | BJ36: TRUE | BK36: TRUE | BL36: TRUE | BM36: TRUE | BN36: TRUE | BO36: TRUE
A37: =A36&C37 -> MayBHUVANESHWARAN.VOT HOURS | C37: OT HOURS | E37: =SUM(F37:BO37) -> 0
A38: =B38&D38 -> MayTHIRIPURA SUNDARI.R | B38: May | C38: AC 02 | D38: =IFERROR(VLOOKUP(C38,'Employees List'!$B$2:$E1424,4,0),"") -> THIRIPURA SUNDARI.R | E38: =COUNTIF(F38:BO38,TRUE)/2 -> 31 | F38: TRUE | G38: TRUE | H38: TRUE | I38: TRUE | J38: TRUE | K38: TRUE | L38: TRUE | M38: TRUE | N38: TRUE | O38: TRUE | P38: TRUE | Q38: TRUE | R38: TRUE | S38: TRUE | T38: TRUE | U38: TRUE | V38: TRUE | W38: TRUE | X38: TRUE | Y38: TRUE | Z38: TRUE | AA38: TRUE | AB38: TRUE | AC38: TRUE | AD38: TRUE | AE38: TRUE | AF38: TRUE | AG38: TRUE | AH38: TRUE | AI38: TRUE | AJ38: TRUE | AK38: TRUE | AL38: TRUE | AM38: TRUE | AN38: TRUE | AO38: TRUE | AP38: TRUE | AQ38: TRUE | AR38: TRUE | AS38: TRUE | AT38: TRUE | AU38: TRUE | AV38: TRUE | AW38: TRUE | AX38: TRUE | AY38: TRUE | AZ38: TRUE | BA38: TRUE | BB38: TRUE | BC38: TRUE | BD38: TRUE | BE38: TRUE | BF38: TRUE | BG38: TRUE | BH38: TRUE | BI38: TRUE | BJ38: TRUE | BK38: TRUE | BL38: TRUE | BM38: TRUE | BN38: TRUE | BO38: TRUE
A39: =A38&C39 -> MayTHIRIPURA SUNDARI.ROT HOURS | C39: OT HOURS | E39: =SUM(F39:BO39) -> 10 | N39: 1 | P39: 1 | R39: 1 | X39: 1 | AL39: 2 | AR39: 1 | BD39: 1 | BF39: 2
A40: =B40&D40 -> MayGANESH | B40: May | C40: PR 02 | D40: =IFERROR(VLOOKUP(C40,'Employees List'!$B$2:$E1424,4,0),"") -> GANESH | E40: =COUNTIF(F40:BO40,TRUE)/2 -> 24.5 | F40: TRUE | G40: TRUE | H40: TRUE | I40: TRUE | J40: TRUE | K40: TRUE | L40: TRUE | M40: TRUE | N40: TRUE | O40: TRUE | P40: TRUE | Q40: TRUE | R40: TRUE | S40: TRUE | T40: TRUE | U40: TRUE | V40: TRUE | W40: TRUE | X40: TRUE | Y40: TRUE | Z40: TRUE | AA40: TRUE | AB40: FALSE | AC40: FALSE | AD40: TRUE | AE40: TRUE | AF40: TRUE | AG40: FALSE | AH40: FALSE | AI40: FALSE | AJ40: FALSE | AK40: FALSE | AL40: FALSE | AM40: FALSE | AN40: FALSE | AO40: FALSE | AP40: FALSE | AQ40: FALSE | AR40: TRUE | AS40: TRUE | AT40: TRUE | AU40: TRUE | AV40: TRUE | AW40: TRUE | AX40: TRUE | AY40: TRUE | AZ40: TRUE | BA40: TRUE | BB40: TRUE | BC40: TRUE | BD40: TRUE | BE40: TRUE | BF40: TRUE | BG40: TRUE | BH40: TRUE | BI40: TRUE | BJ40: TRUE | BK40: TRUE | BL40: TRUE | BM40: TRUE | BN40: TRUE | BO40: TRUE
A41: =A40&C41 -> MayGANESHOT HOURS | C41: OT HOURS | E41: =SUM(F41:BO41) -> 45 | J41: 2 | P41: 2 | T41: 4 | V41: 3 | X41: 2 | AD41: 3 | AR41: 2 | AT41: 4 | AV41: 2 | AX41: 2 | AZ41: 7 | BD41: 3 | BF41: 3 | BH41: 2 | BJ41: 2 | BN41: 2
A42: =B42&D42 -> MayILAMATHIVANAN.S | B42: May | C42: DR 01 | D42: =IFERROR(VLOOKUP(C42,'Employees List'!$B$2:$E1424,4,0),"") -> ILAMATHIVANAN.S | E42: =COUNTIF(F42:BO42,TRUE)/2 -> 28.5 | F42: TRUE | G42: TRUE | H42: TRUE | I42: TRUE | J42: FALSE | K42: TRUE | L42: TRUE | M42: TRUE | N42: TRUE | O42: TRUE | P42: TRUE | Q42: TRUE | R42: TRUE | S42: TRUE | T42: FALSE | U42: FALSE | V42: TRUE | W42: TRUE | X42: TRUE | Y42: TRUE | Z42: TRUE | AA42: TRUE | AB42: TRUE | AC42: TRUE | AD42: TRUE | AE42: TRUE | AF42: TRUE | AG42: TRUE | AH42: TRUE | AI42: TRUE | AJ42: FALSE | AK42: FALSE | AL42: TRUE | AM42: TRUE | AN42: TRUE | AO42: TRUE | AP42: TRUE | AQ42: TRUE | AR42: TRUE | AS42: TRUE | AT42: TRUE | AU42: TRUE | AV42: TRUE | AW42: TRUE | AX42: TRUE | AY42: TRUE | AZ42: TRUE | BA42: TRUE | BB42: TRUE | BC42: TRUE | BD42: TRUE | BE42: TRUE | BF42: TRUE | BG42: TRUE | BH42: TRUE | BI42: TRUE | BJ42: TRUE | BK42: TRUE | BL42: TRUE | BM42: TRUE | BN42: TRUE | BO42: TRUE
A43: =A42&C43 -> MayILAMATHIVANAN.SOT HOURS | C43: OT HOURS | E43: =SUM(F43:BO43) -> 76 | F43: 4 | H43: 2 | R43: 1 | V43: 4 | X43: 5 | AB43: 2 | AD43: 4 | AF43: 2 | AL43: 4 | AP43: 4 | AR43: 2 | AT43: 5 | AV43: 5 | AX43: 4 | AZ43: 7 | BD43: 5 | BF43: 5 | BH43: 1 | BJ43: 4 | BL43: 3 | BN43: 3
A44: =B44&D44 -> MayAMMU.S | B44: May | C44: PR 07 | D44: =IFERROR(VLOOKUP(C44,'Employees List'!$B$2:$E1424,4,0),"") -> AMMU.S | E44: =COUNTIF(F44:BO44,TRUE)/2 -> 27 | F44: TRUE | G44: TRUE | H44: TRUE | I44: TRUE | J44: TRUE | K44: TRUE | L44: TRUE | M44: TRUE | N44: TRUE | O44: TRUE | P44: TRUE | Q44: TRUE | R44: FALSE | S44: FALSE | T44: FALSE | U44: FALSE | V44: FALSE | W44: FALSE | X44: FALSE | Y44: FALSE | Z44: TRUE | AA44: TRUE | AB44: TRUE | AC44: TRUE | AD44: TRUE | AE44: TRUE | AF44: TRUE | AG44: TRUE | AH44: TRUE | AI44: TRUE | AJ44: TRUE | AK44: TRUE | AL44: TRUE | AM44: TRUE | AN44: TRUE | AO44: TRUE | AP44: TRUE | AQ44: TRUE | AR44: TRUE | AS44: TRUE | AT44: TRUE | AU44: TRUE | AV44: TRUE | AW44: TRUE | AX44: TRUE | AY44: TRUE | AZ44: TRUE | BA44: TRUE | BB44: TRUE | BC44: TRUE | BD44: TRUE | BE44: TRUE | BF44: TRUE | BG44: TRUE | BH44: TRUE | BI44: TRUE | BJ44: TRUE | BK44: TRUE | BL44: TRUE | BM44: TRUE | BN44: TRUE | BO44: TRUE
A45: =A44&C45 -> MayAMMU.SOT HOURS | C45: OT HOURS | E45: =SUM(F45:BO45) -> 33 | H45: 2 | J45: 2 | N45: 2 | AD45: 2 | AF45: 2 | AH45: 2 | AL45: 2 | AP45: 2 | AR45: 2 | AT45: 2 | AV45: 2 | AZ45: 2 | BD45: 2 | BF45: 2 | BH45: 1 | BJ45: 2 | BN45: 2
A46: =B46&D46 -> MayREVATHI.S | B46: May | C46: PR 08 | D46: =IFERROR(VLOOKUP(C46,'Employees List'!$B$2:$E1424,4,0),"") -> REVATHI.S | E46: =COUNTIF(F46:BO46,TRUE)/2 -> 30 | F46: TRUE | G46: TRUE | H46: TRUE | I46: TRUE | J46: TRUE | K46: TRUE | L46: TRUE | M46: TRUE | N46: FALSE | O46: FALSE | P46: TRUE | Q46: TRUE | R46: TRUE | S46: TRUE | T46: TRUE | U46: TRUE | V46: TRUE | W46: TRUE | X46: TRUE | Y46: TRUE | Z46: TRUE | AA46: TRUE | AB46: TRUE | AC46: TRUE | AD46: TRUE | AE46: TRUE | AF46: TRUE | AG46: TRUE | AH46: TRUE | AI46: TRUE | AJ46: TRUE | AK46: TRUE | AL46: TRUE | AM46: TRUE | AN46: TRUE | AO46: TRUE | AP46: TRUE | AQ46: TRUE | AR46: TRUE | AS46: TRUE | AT46: TRUE | AU46: TRUE | AV46: TRUE | AW46: TRUE | AX46: TRUE | AY46: TRUE | AZ46: TRUE | BA46: TRUE | BB46: TRUE | BC46: TRUE | BD46: TRUE | BE46: TRUE | BF46: TRUE | BG46: TRUE | BH46: TRUE | BI46: TRUE | BJ46: TRUE | BK46: TRUE | BL46: TRUE | BM46: TRUE | BN46: TRUE | BO46: TRUE
A47: =A46&C47 -> MayREVATHI.SOT HOURS | C47: OT HOURS | E47: =SUM(F47:BO47) -> 39 | H47: 2 | J47: 2 | V47: 2 | X47: 2 | Z47: 6 | AD47: 2 | AF47: 2 | AH47: 2 | AL47: 2 | AR47: 2 | AT47: 2 | AV47: 2 | AZ47: 2 | BD47: 2 | BF47: 2 | BH47: 1 | BJ47: 2 | BN47: 2
A48: =B48&D48 -> MayLEELAVATHI.M | B48: May | C48: AC 03 | D48: =IFERROR(VLOOKUP(C48,'Employees List'!$B$2:$E1424,4,0),"") -> LEELAVATHI.M | E48: =COUNTIF(F48:BO48,TRUE)/2 -> 29 | F48: TRUE | G48: TRUE | H48: FALSE | I48: TRUE | J48: TRUE | K48: TRUE | L48: TRUE | M48: TRUE | N48: TRUE | O48: TRUE | P48: TRUE | Q48: TRUE | R48: FALSE | S48: TRUE | T48: TRUE | U48: TRUE | V48: TRUE | W48: TRUE | X48: TRUE | Y48: TRUE | Z48: TRUE | AA48: TRUE | AB48: TRUE | AC48: TRUE | AD48: TRUE | AE48: TRUE | AF48: TRUE | AG48: TRUE | AH48: TRUE | AI48: TRUE | AJ48: TRUE | AK48: TRUE | AL48: TRUE | AM48: TRUE | AN48: TRUE | AO48: TRUE | AP48: TRUE | AQ48: TRUE | AR48: TRUE | AS48: TRUE | AT48: TRUE | AU48: TRUE | AV48: TRUE | AW48: TRUE | AX48: TRUE | AY48: TRUE | AZ48: FALSE | BA48: FALSE | BB48: TRUE | BC48: TRUE | BD48: TRUE | BE48: TRUE | BF48: TRUE | BG48: TRUE | BH48: TRUE | BI48: TRUE | BJ48: TRUE | BK48: TRUE | BL48: TRUE | BM48: TRUE | BN48: TRUE | BO48: TRUE
A49: =A48&C49 -> MayLEELAVATHI.MOT HOURS | C49: OT HOURS | E49: =SUM(F49:BO49) -> 5 | N49: 2 | T49: 1 | X49: 1 | BF49: 1
A50: =B50&D50 -> MaySANJAY BAGARTTI.K | B50: May | C50: PR 05 | D50: =IFERROR(VLOOKUP(C50,'Employees List'!$B$2:$E1424,4,0),"") -> SANJAY BAGARTTI.K | E50: =COUNTIF(F50:BO50,TRUE)/2 -> 31 | F50: TRUE | G50: TRUE | H50: TRUE | I50: TRUE | J50: TRUE | K50: TRUE | L50: TRUE | M50: TRUE | N50: TRUE | O50: TRUE | P50: TRUE | Q50: TRUE | R50: TRUE | S50: TRUE | T50: TRUE | U50: TRUE | V50: TRUE | W50: TRUE | X50: TRUE | Y50: TRUE | Z50: TRUE | AA50: TRUE | AB50: TRUE | AC50: TRUE | AD50: TRUE | AE50: TRUE | AF50: TRUE | AG50: TRUE | AH50: TRUE | AI50: TRUE | AJ50: TRUE | AK50: TRUE | AL50: TRUE | AM50: TRUE | AN50: TRUE | AO50: TRUE | AP50: TRUE | AQ50: TRUE | AR50: TRUE | AS50: TRUE | AT50: TRUE | AU50: TRUE | AV50: TRUE | AW50: TRUE | AX50: TRUE | AY50: TRUE | AZ50: TRUE | BA50: TRUE | BB50: TRUE | BC50: TRUE | BD50: TRUE | BE50: TRUE | BF50: TRUE | BG50: TRUE | BH50: TRUE | BI50: TRUE | BJ50: TRUE | BK50: TRUE | BL50: TRUE | BM50: TRUE | BN50: TRUE | BO50: TRUE
A51: =A50&C51 -> MaySANJAY BAGARTTI.KOT HOURS | C51: OT HOURS | E51: =SUM(F51:BO51) -> 150 | H51: 7 | J51: 6 | N51: 2 | P51: 5 | R51: 2 | T51: 6 | V51: 5 | X51: 6 | Z51: 8 | AD51: 3 | AF51: 4 | AH51: 5 | AJ51: 5 | AL51: 8 | AN51: 8 | AP51: 7 | AR51: 4 | AT51: 7 | AV51: 5 | AX51: 5 | AZ51: 9 | BB51: 6 | BD51: 6 | BF51: 7 | BH51: 5 | BJ51: 2 | BL51: 2 | BN51: 5
A52: =B52&D52 -> MayADHIKARI BALIA.A | B52: May | C52: PR 03 | D52: =IFERROR(VLOOKUP(C52,'Employees List'!$B$2:$E1424,4,0),"") -> ADHIKARI BALIA.A | E52: =COUNTIF(F52:BO52,TRUE)/2 -> 31 | F52: TRUE | G52: TRUE | H52: TRUE | I52: TRUE | J52: TRUE | K52: TRUE | L52: TRUE | M52: TRUE | N52: TRUE | O52: TRUE | P52: TRUE | Q52: TRUE | R52: TRUE | S52: TRUE | T52: TRUE | U52: TRUE | V52: TRUE | W52: TRUE | X52: TRUE | Y52: TRUE | Z52: TRUE | AA52: TRUE | AB52: TRUE | AC52: TRUE | AD52: TRUE | AE52: TRUE | AF52: TRUE | AG52: TRUE | AH52: TRUE | AI52: TRUE | AJ52: TRUE | AK52: TRUE | AL52: TRUE | AM52: TRUE | AN52: TRUE | AO52: TRUE | AP52: TRUE | AQ52: TRUE | AR52: TRUE | AS52: TRUE | AT52: TRUE | AU52: TRUE | AV52: TRUE | AW52: TRUE | AX52: TRUE | AY52: TRUE | AZ52: TRUE | BA52: TRUE | BB52: TRUE | BC52: TRUE | BD52: TRUE | BE52: TRUE | BF52: TRUE | BG52: TRUE | BH52: TRUE | BI52: TRUE | BJ52: TRUE | BK52: TRUE | BL52: TRUE | BM52: TRUE | BN52: TRUE | BO52: TRUE
A53: =A52&C53 -> MayADHIKARI BALIA.AOT HOURS | C53: OT HOURS | E53: =SUM(F53:BO53) -> 130 | H53: 7 | J53: 6 | N53: 2 | P53: 5 | T53: 6 | V53: 4 | X53: 4 | Z53: 8 | AD53: 3 | AF53: 4 | AH53: 5 | AJ53: 5 | AL53: 6 | AN53: 6 | AP53: 7 | AR53: 4 | AT53: 7 | AV53: 7 | AX53: 5 | AZ53: 7 | BB53: 4 | BD53: 3 | BF53: 2 | BH53: 4 | BJ53: 2 | BL53: 2 | BN53: 5
A54: =B54&D54 -> MayRUPESH KISAN | B54: May | C54: PR 04 | D54: =IFERROR(VLOOKUP(C54,'Employees List'!$B$2:$E1424,4,0),"") -> RUPESH KISAN | E54: =COUNTIF(F54:BO54,TRUE)/2 -> 31 | F54: TRUE | G54: TRUE | H54: TRUE | I54: TRUE | J54: TRUE | K54: TRUE | L54: TRUE | M54: TRUE | N54: TRUE | O54: TRUE | P54: TRUE | Q54: TRUE | R54: TRUE | S54: TRUE | T54: TRUE | U54: TRUE | V54: TRUE | W54: TRUE | X54: TRUE | Y54: TRUE | Z54: TRUE | AA54: TRUE | AB54: TRUE | AC54: TRUE | AD54: TRUE | AE54: TRUE | AF54: TRUE | AG54: TRUE | AH54: TRUE | AI54: TRUE | AJ54: TRUE | AK54: TRUE | AL54: TRUE | AM54: TRUE | AN54: TRUE | AO54: TRUE | AP54: TRUE | AQ54: TRUE | AR54: TRUE | AS54: TRUE | AT54: TRUE | AU54: TRUE | AV54: TRUE | AW54: TRUE | AX54: TRUE | AY54: TRUE | AZ54: TRUE | BA54: TRUE | BB54: TRUE | BC54: TRUE | BD54: TRUE | BE54: TRUE | BF54: TRUE | BG54: TRUE | BH54: TRUE | BI54: TRUE | BJ54: TRUE | BK54: TRUE | BL54: TRUE | BM54: TRUE | BN54: TRUE | BO54: TRUE
A55: =A54&C55 -> MayRUPESH KISANOT HOURS | C55: OT HOURS | E55: =SUM(F55:BO55) -> 131 | H55: 4 | J55: 4 | N55: 2 | P55: 4 | R55: 2 | T55: 4 | V55: 4 | X55: 4 | Z55: 8 | AB55: 3 | AD55: 5 | AF55: 4 | AH55: 8 | AJ55: 5 | AL55: 4 | AN55: 6 | AP55: 4 | AR55: 3 | AT55: 6 | AV55: 7 | AX55: 4 | AZ55: 9 | BB55: 6 | BD55: 3 | BF55: 5 | BH55: 6 | BJ55: 2 | BL55: 2 | BN55: 3
A56: =B56&D56 -> MayLIPAN | B56: May | C56: PR 21 | D56: =IFERROR(VLOOKUP(C56,'Employees List'!$B$2:$E1424,4,0),"") -> LIPAN | E56: =COUNTIF(F56:BO56,TRUE)/2 -> 30 | F56: TRUE | G56: TRUE | H56: TRUE | I56: TRUE | J56: TRUE | K56: TRUE | L56: TRUE | M56: TRUE | N56: TRUE | O56: TRUE | P56: TRUE | Q56: TRUE | R56: TRUE | S56: TRUE | T56: TRUE | U56: TRUE | V56: TRUE | W56: TRUE | X56: TRUE | Y56: TRUE | Z56: TRUE | AA56: TRUE | AB56: TRUE | AC56: TRUE | AD56: TRUE | AE56: TRUE | AF56: TRUE | AG56: TRUE | AH56: TRUE | AI56: TRUE | AJ56: TRUE | AK56: TRUE | AL56: TRUE | AM56: TRUE | AN56: TRUE | AO56: TRUE | AP56: TRUE | AQ56: TRUE | AR56: TRUE | AS56: TRUE | AT56: TRUE | AU56: TRUE | AV56: TRUE | AW56: TRUE | AX56: TRUE | AY56: TRUE | AZ56: TRUE | BA56: TRUE | BB56: TRUE | BC56: TRUE | BD56: TRUE | BE56: TRUE | BF56: TRUE | BG56: TRUE | BH56: FALSE | BI56: FALSE | BJ56: TRUE | BK56: TRUE | BL56: TRUE | BM56: TRUE | BN56: TRUE | BO56: TRUE
A57: =A56&C57 -> MayLIPANOT HOURS | C57: OT HOURS | E57: =SUM(F57:BO57) -> 135 | H57: 7 | J57: 6 | P57: 4 | R57: 2 | T57: 6 | V57: 4 | X57: 6 | Z57: 8 | AD57: 3 | AF57: 4 | AH57: 5 | AJ57: 5 | AL57: 8 | AN57: 8 | AP57: 4 | AR57: 2 | AT57: 6 | AV57: 7 | AX57: 5 | AZ57: 7 | BB57: 4 | BD57: 6 | BF57: 7 | BJ57: 2 | BL57: 4 | BN57: 5
A58: =B58&D58 -> MayNILAMANI KISAN.B | B58: May | C58: PR 24 | D58: =IFERROR(VLOOKUP(C58,'Employees List'!$B$2:$E1424,4,0),"") -> NILAMANI KISAN.B | E58: =COUNTIF(F58:BO58,TRUE)/2 -> 29 | F58: TRUE | G58: TRUE | H58: TRUE | I58: TRUE | J58: TRUE | K58: TRUE | L58: TRUE | M58: TRUE | N58: TRUE | O58: TRUE | P58: TRUE | Q58: TRUE | R58: TRUE | S58: TRUE | T58: TRUE | U58: TRUE | V58: TRUE | W58: TRUE | X58: TRUE | Y58: TRUE | Z58: TRUE | AA58: TRUE | AB58: TRUE | AC58: TRUE | AD58: TRUE | AE58: TRUE | AF58: FALSE | AG58: FALSE | AH58: FALSE | AI58: FALSE | AJ58: TRUE | AK58: TRUE | AL58: TRUE | AM58: TRUE | AN58: TRUE | AO58: TRUE | AP58: TRUE | AQ58: TRUE | AR58: TRUE | AS58: TRUE | AT58: TRUE | AU58: TRUE | AV58: TRUE | AW58: TRUE | AX58: TRUE | AY58: TRUE | AZ58: TRUE | BA58: TRUE | BB58: TRUE | BC58: TRUE | BD58: TRUE | BE58: TRUE | BF58: TRUE | BG58: TRUE | BH58: TRUE | BI58: TRUE | BJ58: TRUE | BK58: TRUE | BL58: TRUE | BM58: TRUE | BN58: TRUE | BO58: TRUE
A59: =A58&C59 -> MayNILAMANI KISAN.BOT HOURS | C59: OT HOURS | E59: =SUM(F59:BO59) -> 101 | H59: 2 | J59: 4 | N59: 2 | P59: 2 | T59: 4 | V59: 3 | X59: 2 | Z59: 8 | AD59: 3 | AJ59: 5 | AL59: 4 | AN59: 6 | AP59: 4 | AR59: 3 | AT59: 4 | AV59: 7 | AX59: 4 | AZ59: 7 | BB59: 4 | BD59: 2 | BF59: 8 | BH59: 2 | BJ59: 5 | BL59: 4 | BN59: 2
C60: 45809
C61: Employee Code | D61: Name | E61: Days Present / OT Hours | F61: M | G61: A | H61: M | I61: A | J61: M | K61: A | L61: M | M61: A | N61: M | O61: A | P61: M | Q61: A | R61: M | S61: A | T61: M | U61: A | V61: M | W61: A | X61: M | Y61: A | Z61: M | AA61: A | AB61: M | AC61: A | AD61: M | AE61: A | AF61: M | AG61: A | AH61: M | AI61: A | AJ61: M | AK61: A | AL61: M | AM61: A | AN61: M | AO61: A | AP61: M | AQ61: A | AR61: M | AS61: A | AT61: M | AU61: A | AV61: M | AW61: A | AX61: M | AY61: A | AZ61: M | BA61: A | BB61: M | BC61: A | BD61: M | BE61: A | BF61: M | BG61: A | BH61: M | BI61: A | BJ61: M | BK61: A | BL61: M | BM61: A | BN61: M | BO61: A
A62: =B62&D62 -> JuneBHUVANESHWARAN.V | B62: June | C62: AC 01 | D62: =IFERROR(VLOOKUP(C62,'Employees List'!$B$2:$E1424,4,0),"") -> BHUVANESHWARAN.V | E62: =COUNTIF(F62:BO62,TRUE)/2 -> 30 | F62: TRUE | G62: TRUE | H62: TRUE | I62: TRUE | J62: TRUE | K62: TRUE | L62: TRUE | M62: TRUE | N62: TRUE | O62: TRUE | P62: TRUE | Q62: TRUE | R62: TRUE | S62: TRUE | T62: TRUE | U62: TRUE | V62: TRUE | W62: TRUE | X62: TRUE | Y62: TRUE | Z62: TRUE | AA62: TRUE | AB62: TRUE | AC62: TRUE | AD62: TRUE | AE62: TRUE | AF62: TRUE | AG62: TRUE | AH62: TRUE | AI62: TRUE | AJ62: TRUE | AK62: TRUE | AL62: TRUE | AM62: TRUE | AN62: TRUE | AO62: TRUE | AP62: TRUE | AQ62: TRUE | AR62: TRUE | AS62: TRUE | AT62: TRUE | AU62: TRUE | AV62: TRUE | AW62: TRUE | AX62: TRUE | AY62: TRUE | AZ62: TRUE | BA62: TRUE | BB62: TRUE | BC62: TRUE | BD62: TRUE | BE62: TRUE | BF62: TRUE | BG62: TRUE | BH62: TRUE | BI62: TRUE | BJ62: TRUE | BK62: TRUE | BL62: TRUE | BM62: TRUE | BN62: FALSE | BO62: FALSE
A63: =A62&C63 -> JuneBHUVANESHWARAN.VOT HOURS | C63: OT HOURS | E63: =COUNTIF(F63:BO63,TRUE)/2 -> 0
A64: =B64&D64 -> JuneTHIRIPURA SUNDARI.R | B64: June | C64: AC 02 | D64: =IFERROR(VLOOKUP(C64,'Employees List'!$B$2:$E1424,4,0),"") -> THIRIPURA SUNDARI.R | E64: =COUNTIF(F64:BO64,TRUE)/2 -> 30 | F64: TRUE | G64: TRUE | H64: TRUE | I64: TRUE | J64: TRUE | K64: TRUE | L64: TRUE | M64: TRUE | N64: TRUE | O64: TRUE | P64: TRUE | Q64: TRUE | R64: TRUE | S64: TRUE | T64: TRUE | U64: TRUE | V64: TRUE | W64: TRUE | X64: TRUE | Y64: TRUE | Z64: TRUE | AA64: TRUE | AB64: TRUE | AC64: TRUE | AD64: TRUE | AE64: TRUE | AF64: TRUE | AG64: TRUE | AH64: TRUE | AI64: TRUE | AJ64: TRUE | AK64: TRUE | AL64: TRUE | AM64: TRUE | AN64: TRUE | AO64: TRUE | AP64: TRUE | AQ64: TRUE | AR64: TRUE | AS64: TRUE | AT64: TRUE | AU64: TRUE | AV64: TRUE | AW64: TRUE | AX64: TRUE | AY64: TRUE | AZ64: TRUE | BA64: TRUE | BB64: TRUE | BC64: TRUE | BD64: TRUE | BE64: TRUE | BF64: TRUE | BG64: TRUE | BH64: TRUE | BI64: TRUE | BJ64: TRUE | BK64: TRUE | BL64: TRUE | BM64: TRUE | BN64: FALSE | BO64: FALSE
A65: =A64&C65 -> JuneTHIRIPURA SUNDARI.ROT HOURS | C65: OT HOURS | E65: =SUM(F65:BO65) -> 6 | J65: 1 | Z65: 1 | AF65: 1 | AH65: 2 | AV65: 1
A66: =B66&D66 -> JuneGANESH | B66: June | C66: PR 02 | D66: =IFERROR(VLOOKUP(C66,'Employees List'!$B$2:$E1424,4,0),"") -> GANESH | E66: =COUNTIF(F66:BO66,TRUE)/2 -> 25 | F66: TRUE | G66: TRUE | H66: TRUE | I66: TRUE | J66: TRUE | K66: TRUE | L66: TRUE | M66: TRUE | N66: TRUE | O66: TRUE | P66: TRUE | Q66: TRUE | R66: TRUE | S66: TRUE | T66: TRUE | U66: TRUE | V66: FALSE | W66: FALSE | X66: FALSE | Y66: FALSE | Z66: FALSE | AA66: FALSE | AB66: FALSE | AC66: FALSE | AD66: TRUE | AE66: TRUE | AF66: TRUE | AG66: TRUE | AH66: TRUE | AI66: TRUE | AJ66: TRUE | AK66: TRUE | AL66: TRUE | AM66: TRUE | AN66: TRUE | AO66: TRUE | AP66: TRUE | AQ66: TRUE | AR66: TRUE | AS66: TRUE | AT66: TRUE | AU66: TRUE | AV66: TRUE | AW66: TRUE | AX66: TRUE | AY66: TRUE | AZ66: FALSE | BA66: FALSE | BB66: TRUE | BC66: TRUE | BD66: TRUE | BE66: TRUE | BF66: TRUE | BG66: TRUE | BH66: TRUE | BI66: TRUE | BJ66: TRUE | BK66: TRUE | BL66: TRUE | BM66: TRUE | BN66: FALSE | BO66: FALSE
A67: =A66&C67 -> JuneGANESHOT HOURS | C67: OT HOURS | E67: =SUM(F67:BO67) -> 30 | H67: 2 | J67: 3 | L67: 2 | P67: 2 | AD67: 2 | AF67: 3 | AJ67: 2 | AP67: 3 | AR67: 4 | AT67: 2 | AX67: 2 | BL67: 3
A68: =B68&D68 -> JuneILAMATHIVANAN.S | B68: June | C68: DR 01 | D68: =IFERROR(VLOOKUP(C68,'Employees List'!$B$2:$E1424,4,0),"") -> ILAMATHIVANAN.S | E68: =COUNTIF(F68:BO68,TRUE)/2 -> 22 | F68: TRUE | G68: TRUE | H68: FALSE | I68: FALSE | J68: FALSE | K68: FALSE | L68: FALSE | M68: FALSE | N68: TRUE | O68: TRUE | P68: TRUE | Q68: TRUE | R68: TRUE | S68: TRUE | T68: TRUE | U68: TRUE | V68: TRUE | W68: TRUE | X68: FALSE | Y68: FALSE | Z68: FALSE | AA68: FALSE | AB68: TRUE | AC68: TRUE | AD68: TRUE | AE68: TRUE | AF68: TRUE | AG68: TRUE | AH68: TRUE | AI68: TRUE | AJ68: TRUE | AK68: TRUE | AL68: FALSE | AM68: FALSE | AN68: TRUE | AO68: TRUE | AP68: TRUE | AQ68: TRUE | AR68: TRUE | AS68: TRUE | AT68: TRUE | AU68: TRUE | AV68: TRUE | AW68: TRUE | AX68: FALSE | AY68: FALSE | AZ68: TRUE | BA68: TRUE | BB68: TRUE | BC68: TRUE | BD68: TRUE | BE68: TRUE | BF68: TRUE | BG68: TRUE | BH68: TRUE | BI68: TRUE | BJ68: TRUE | BK68: TRUE | BL68: FALSE | BM68: FALSE | BN68: FALSE | BO68: FALSE
A69: =A68&C69 -> JuneILAMATHIVANAN.SOT HOURS | C69: OT HOURS | E69: =SUM(F69:BO69) -> 37 | N69: 4 | P69: 4 | R69: 1 | V69: 1 | AB69: 5 | AD69: 4 | AF69: 5 | AN69: 1 | AP69: 4 | AR69: 4 | AT69: 3 | AZ69: 1
A70: =B70&D70 -> JuneAMMU.S | B70: June | C70: PR 07 | D70: =IFERROR(VLOOKUP(C70,'Employees List'!$B$2:$E1424,4,0),"") -> AMMU.S | E70: =COUNTIF(F70:BO70,TRUE)/2 -> 28 | F70: TRUE | G70: TRUE | H70: TRUE | I70: TRUE | J70: TRUE | K70: TRUE | L70: TRUE | M70: TRUE | N70: TRUE | O70: TRUE | P70: FALSE | Q70: FALSE | R70: TRUE | S70: TRUE | T70: TRUE | U70: TRUE | V70: TRUE | W70: TRUE | X70: TRUE | Y70: TRUE | Z70: TRUE | AA70: TRUE | AB70: TRUE | AC70: TRUE | AD70: TRUE | AE70: TRUE | AF70: TRUE | AG70: TRUE | AH70: TRUE | AI70: TRUE | AJ70: TRUE | AK70: TRUE | AL70: TRUE | AM70: TRUE | AN70: TRUE | AO70: TRUE | AP70: TRUE | AQ70: TRUE | AR70: TRUE | AS70: TRUE | AT70: TRUE | AU70: TRUE | AV70: TRUE | AW70: TRUE | AX70: TRUE | AY70: TRUE | AZ70: TRUE | BA70: TRUE | BB70: TRUE | BC70: TRUE | BD70: TRUE | BE70: TRUE | BF70: TRUE | BG70: TRUE | BH70: TRUE | BI70: TRUE | BJ70: TRUE | BK70: TRUE | BL70: FALSE | BM70: FALSE | BN70: FALSE | BO70: FALSE
A71: =A70&C71 -> JuneAMMU.SOT HOURS | C71: OT HOURS | E71: =SUM(F71:BO71) -> 38 | H71: 2 | J71: 1 | L71: 2 | N71: 2 | R71: 2 | X71: 2 | Z71: 2 | AB71: 2 | AD71: 2 | AF71: 2 | AH71: 5 | AJ71: 2 | AL71: 2 | AP71: 2 | AR71: 2 | AT71: 2 | AX71: 2 | AZ71: 2
A72: =B72&D72 -> JuneREVATHI.S | B72: June | C72: PR 08 | D72: =IFERROR(VLOOKUP(C72,'Employees List'!$B$2:$E1424,4,0),"") -> REVATHI.S | E72: =COUNTIF(F72:BO72,TRUE)/2 -> 29 | F72: TRUE | G72: TRUE | H72: FALSE | I72: FALSE | J72: TRUE | K72: TRUE | L72: TRUE | M72: TRUE | N72: TRUE | O72: TRUE | P72: TRUE | Q72: TRUE | R72: TRUE | S72: TRUE | T72: TRUE | U72: TRUE | V72: TRUE | W72: TRUE | X72: TRUE | Y72: TRUE | Z72: TRUE | AA72: TRUE | AB72: TRUE | AC72: TRUE | AD72: TRUE | AE72: TRUE | AF72: TRUE | AG72: TRUE | AH72: TRUE | AI72: TRUE | AJ72: TRUE | AK72: TRUE | AL72: TRUE | AM72: TRUE | AN72: TRUE | AO72: TRUE | AP72: TRUE | AQ72: TRUE | AR72: TRUE | AS72: TRUE | AT72: TRUE | AU72: TRUE | AV72: TRUE | AW72: TRUE | AX72: TRUE | AY72: TRUE | AZ72: TRUE | BA72: TRUE | BB72: TRUE | BC72: TRUE | BD72: TRUE | BE72: TRUE | BF72: TRUE | BG72: TRUE | BH72: TRUE | BI72: TRUE | BJ72: TRUE | BK72: TRUE | BL72: TRUE | BM72: TRUE | BN72: FALSE | BO72: FALSE
A73: =A72&C73 -> JuneREVATHI.SOT HOURS | C73: OT HOURS | E73: =SUM(F73:BO73) -> 38 | J73: 1 | L73: 2 | N73: 2 | P73: 2 | R73: 2 | X73: 2 | Z73: 2 | AB73: 2 | AD73: 2 | AF73: 2 | AH73: 5 | AJ73: 2 | AP73: 2 | AR73: 2 | AT73: 2 | AX73: 2 | AZ73: 2 | BL73: 2
A74: =B74&D74 -> JuneLEELAVATHI.M | B74: June | C74: AC 03 | D74: =IFERROR(VLOOKUP(C74,'Employees List'!$B$2:$E1424,4,0),"") -> LEELAVATHI.M | E74: =COUNTIF(F74:BO74,TRUE)/2 -> 29 | F74: TRUE | G74: TRUE | H74: TRUE | I74: TRUE | J74: TRUE | K74: TRUE | L74: TRUE | M74: TRUE | N74: TRUE | O74: TRUE | P74: TRUE | Q74: TRUE | R74: TRUE | S74: TRUE | T74: TRUE | U74: TRUE | V74: TRUE | W74: TRUE | X74: TRUE | Y74: TRUE | Z74: TRUE | AA74: TRUE | AB74: TRUE | AC74: TRUE | AD74: TRUE | AE74: TRUE | AF74: TRUE | AG74: TRUE | AH74: TRUE | AI74: TRUE | AJ74: TRUE | AK74: TRUE | AL74: TRUE | AM74: TRUE | AN74: TRUE | AO74: TRUE | AP74: TRUE | AQ74: TRUE | AR74: TRUE | AS74: TRUE | AT74: TRUE | AU74: TRUE | AV74: TRUE | AW74: TRUE | AX74: TRUE | AY74: TRUE | AZ74: TRUE | BA74: TRUE | BB74: FALSE | BC74: FALSE | BD74: TRUE | BE74: TRUE | BF74: TRUE | BG74: TRUE | BH74: TRUE | BI74: TRUE | BJ74: TRUE | BK74: TRUE | BL74: TRUE | BM74: TRUE | BN74: FALSE | BO74: FALSE
A75: =A74&C75 -> JuneLEELAVATHI.MOT HOURS | C75: OT HOURS | E75: =SUM(F75:BO75) -> 3 | H75: 1 | Z75: 1 | AB75: 1
A76: =B76&D76 -> JuneSANJAY BAGARTTI.K | B76: June | C76: PR 05 | D76: =IFERROR(VLOOKUP(C76,'Employees List'!$B$2:$E1424,4,0),"") -> SANJAY BAGARTTI.K | E76: =COUNTIF(F76:BO76,TRUE)/2 -> 29 | F76: TRUE | G76: TRUE | H76: TRUE | I76: TRUE | J76: TRUE | K76: TRUE | L76: TRUE | M76: TRUE | N76: TRUE | O76: TRUE | P76: TRUE | Q76: TRUE | R76: TRUE | S76: TRUE | T76: TRUE | U76: TRUE | V76: TRUE | W76: TRUE | X76: TRUE | Y76: TRUE | Z76: TRUE | AA76: TRUE | AB76: TRUE | AC76: TRUE | AD76: TRUE | AE76: TRUE | AF76: TRUE | AG76: TRUE | AH76: TRUE | AI76: TRUE | AJ76: TRUE | AK76: TRUE | AL76: TRUE | AM76: TRUE | AN76: TRUE | AO76: TRUE | AP76: TRUE | AQ76: TRUE | AR76: TRUE | AS76: TRUE | AT76: TRUE | AU76: TRUE | AV76: TRUE | AW76: TRUE | AX76: TRUE | AY76: TRUE | AZ76: TRUE | BA76: TRUE | BB76: TRUE | BC76: TRUE | BD76: TRUE | BE76: TRUE | BF76: FALSE | BG76: FALSE | BH76: TRUE | BI76: TRUE | BJ76: TRUE | BK76: TRUE | BL76: TRUE | BM76: TRUE | BN76: FALSE | BO76: FALSE
A77: =A76&C77 -> JuneSANJAY BAGARTTI.KOT HOURS | C77: OT HOURS | E77: =SUM(F77:BO77) -> 98 | H77: 2 | J77: 3 | L77: 4 | N77: 4 | P77: 2 | R77: 6 | T77: 4 | V77: 4 | X77: 5 | Z77: 7 | AB77: 4 | AD77: 5 | AF77: 6 | AH77: 5 | AJ77: 2 | AL77: 4 | AN77: 2 | AP77: 7 | AR77: 4 | AT77: 5 | AX77: 2 | AZ77: 4 | BB77: 4 | BL77: 3
A78: =B78&D78 -> JuneADHIKARI BALIA.A | B78: June | C78: PR 03 | D78: =IFERROR(VLOOKUP(C78,'Employees List'!$B$2:$E1424,4,0),"") -> ADHIKARI BALIA.A | E78: =COUNTIF(F78:BO78,TRUE)/2 -> 29 | F78: TRUE | G78: TRUE | H78: TRUE | I78: TRUE | J78: TRUE | K78: TRUE | L78: TRUE | M78: TRUE | N78: TRUE | O78: TRUE | P78: TRUE | Q78: TRUE | R78: TRUE | S78: TRUE | T78: TRUE | U78: TRUE | V78: FALSE | W78: FALSE | X78: TRUE | Y78: TRUE | Z78: TRUE | AA78: TRUE | AB78: TRUE | AC78: TRUE | AD78: TRUE | AE78: TRUE | AF78: TRUE | AG78: TRUE | AH78: TRUE | AI78: TRUE | AJ78: TRUE | AK78: TRUE | AL78: TRUE | AM78: TRUE | AN78: TRUE | AO78: TRUE | AP78: TRUE | AQ78: TRUE | AR78: TRUE | AS78: TRUE | AT78: TRUE | AU78: TRUE | AV78: TRUE | AW78: TRUE | AX78: TRUE | AY78: TRUE | AZ78: TRUE | BA78: TRUE | BB78: TRUE | BC78: TRUE | BD78: TRUE | BE78: TRUE | BF78: TRUE | BG78: TRUE | BH78: TRUE | BI78: TRUE | BJ78: TRUE | BK78: TRUE | BL78: TRUE | BM78: TRUE | BN78: FALSE | BO78: FALSE
A79: =A78&C79 -> JuneADHIKARI BALIA.AOT HOURS | C79: OT HOURS | E79: =SUM(F79:BO79) -> 88 | H79: 2 | J79: 3 | L79: 4 | N79: 4 | P79: 2 | R79: 6 | T79: 4 | X79: 5 | Z79: 5 | AB79: 4 | AD79: 5 | AF79: 6 | AH79: 5 | AJ79: 2 | AL79: 4 | AN79: 2 | AP79: 7 | AR79: 4 | AT79: 4 | AX79: 2 | AZ79: 3 | BB79: 2 | BL79: 3
A80: =B80&D80 -> JuneRUPESH KISAN | B80: June | C80: PR 04 | D80: =IFERROR(VLOOKUP(C80,'Employees List'!$B$2:$E1424,4,0),"") -> RUPESH KISAN | E80: =COUNTIF(F80:BO80,TRUE)/2 -> 29 | F80: TRUE | G80: TRUE | H80: TRUE | I80: TRUE | J80: TRUE | K80: TRUE | L80: TRUE | M80: TRUE | N80: TRUE | O80: TRUE | P80: TRUE | Q80: TRUE | R80: TRUE | S80: TRUE | T80: TRUE | U80: TRUE | V80: TRUE | W80: TRUE | X80: TRUE | Y80: TRUE | Z80: TRUE | AA80: TRUE | AB80: TRUE | AC80: TRUE | AD80: TRUE | AE80: TRUE | AF80: TRUE | AG80: TRUE | AH80: TRUE | AI80: TRUE | AJ80: TRUE | AK80: TRUE | AL80: TRUE | AM80: TRUE | AN80: TRUE | AO80: TRUE | AP80: TRUE | AQ80: TRUE | AR80: TRUE | AS80: TRUE | AT80: TRUE | AU80: TRUE | AV80: TRUE | AW80: TRUE | AX80: FALSE | AY80: FALSE | AZ80: TRUE | BA80: TRUE | BB80: TRUE | BC80: TRUE | BD80: TRUE | BE80: TRUE | BF80: TRUE | BG80: TRUE | BH80: TRUE | BI80: TRUE | BJ80: TRUE | BK80: TRUE | BL80: TRUE | BM80: TRUE | BN80: FALSE | BO80: FALSE
A81: =A80&C81 -> JuneRUPESH KISANOT HOURS | C81: OT HOURS | E81: =SUM(F81:BO81) -> 80 | H81: 2 | J81: 3 | L81: 8 | N81: 4 | P81: 2 | R81: 2 | T81: 4 | V81: 2 | X81: 5 | Z81: 5 | AB81: 4 | AD81: 4 | AF81: 5 | AH81: 5 | AJ81: 2 | AL81: 4 | AN81: 2 | AP81: 4 | AR81: 4 | AT81: 2 | AZ81: 3 | BB81: 2 | BL81: 2
A82: =B82&D82 -> JuneLIPAN | B82: June | C82: PR 21 | D82: =IFERROR(VLOOKUP(C82,'Employees List'!$B$2:$E1424,4,0),"") -> LIPAN | E82: =COUNTIF(F82:BO82,TRUE)/2 -> 30 | F82: TRUE | G82: TRUE | H82: TRUE | I82: TRUE | J82: TRUE | K82: TRUE | L82: TRUE | M82: TRUE | N82: TRUE | O82: TRUE | P82: TRUE | Q82: TRUE | R82: TRUE | S82: TRUE | T82: TRUE | U82: TRUE | V82: TRUE | W82: TRUE | X82: TRUE | Y82: TRUE | Z82: TRUE | AA82: TRUE | AB82: TRUE | AC82: TRUE | AD82: TRUE | AE82: TRUE | AF82: TRUE | AG82: TRUE | AH82: TRUE | AI82: TRUE | AJ82: TRUE | AK82: TRUE | AL82: TRUE | AM82: TRUE | AN82: TRUE | AO82: TRUE | AP82: TRUE | AQ82: TRUE | AR82: TRUE | AS82: TRUE | AT82: TRUE | AU82: TRUE | AV82: TRUE | AW82: TRUE | AX82: TRUE | AY82: TRUE | AZ82: TRUE | BA82: TRUE | BB82: TRUE | BC82: TRUE | BD82: TRUE | BE82: TRUE | BF82: TRUE | BG82: TRUE | BH82: TRUE | BI82: TRUE | BJ82: TRUE | BK82: TRUE | BL82: TRUE | BM82: TRUE | BN82: FALSE | BO82: FALSE
A83: =A82&C83 -> JuneLIPANOT HOURS | C83: OT HOURS | E83: =SUM(F83:BO83) -> 95 | H83: 2 | J83: 3 | L83: 4 | N83: 4 | P83: 2 | R83: 6 | T83: 4 | V83: 3 | X83: 5 | Z83: 7 | AB83: 4 | AD83: 4 | AF83: 5 | AH83: 5 | AJ83: 2 | AL83: 4 | AN83: 2 | AP83: 5 | AR83: 4 | AT83: 4 | AX83: 5 | AZ83: 4 | BB83: 4 | BL83: 3
A84: =B84&D84 -> JuneNILAMANI KISAN.B | B84: June | C84: PR 24 | D84: =IFERROR(VLOOKUP(C84,'Employees List'!$B$2:$E1424,4,0),"") -> NILAMANI KISAN.B | E84: =COUNTIF(F84:BO84,TRUE)/2 -> 15 | F84: TRUE | G84: TRUE | H84: TRUE | I84: TRUE | J84: TRUE | K84: TRUE | L84: FALSE | M84: FALSE | N84: TRUE | O84: TRUE | P84: TRUE | Q84: TRUE | R84: TRUE | S84: TRUE | T84: TRUE | U84: TRUE | V84: TRUE | W84: TRUE | X84: TRUE | Y84: TRUE | Z84: TRUE | AA84: TRUE | AB84: TRUE | AC84: TRUE | AD84: TRUE | AE84: TRUE | AF84: TRUE | AG84: TRUE | AH84: TRUE | AI84: TRUE | AJ84: TRUE | AK84: TRUE | AL84: FALSE | AM84: FALSE | AN84: FALSE | AO84: FALSE | AP84: FALSE | AQ84: FALSE | AR84: FALSE | AS84: FALSE | AT84: FALSE | AU84: FALSE | AV84: FALSE | AW84: FALSE | AX84: FALSE | AY84: FALSE | AZ84: FALSE | BA84: FALSE | BB84: FALSE | BC84: FALSE | BD84: FALSE | BE84: FALSE | BF84: FALSE | BG84: FALSE | BH84: FALSE | BI84: FALSE | BJ84: FALSE | BK84: FALSE | BL84: FALSE | BM84: FALSE | BN84: FALSE | BO84: FALSE
A85: =A84&C85 -> JuneNILAMANI KISAN.BOT HOURS | C85: OT HOURS | E85: =SUM(F85:BO85) -> 42 | F85: 2 | H85: 2 | J85: 3 | N85: 4 | P85: 5 | R85: 2 | V85: 2 | X85: 3 | Z85: 2 | AB85: 2 | AD85: 7 | AF85: 6 | AJ85: 2
A86: =B86&D86 -> JuneVASANTHA.E | B86: June | C86: PR 01 | D86: =IFERROR(VLOOKUP(C86,'Employees List'!$B$2:$E1424,4,0),"") -> VASANTHA.E | E86: =COUNTIF(F86:BO86,TRUE)/2 -> 30 | F86: TRUE | G86: TRUE | H86: TRUE | I86: TRUE | J86: TRUE | K86: TRUE | L86: TRUE | M86: TRUE | N86: TRUE | O86: TRUE | P86: TRUE | Q86: TRUE | R86: TRUE | S86: TRUE | T86: TRUE | U86: TRUE | V86: TRUE | W86: TRUE | X86: TRUE | Y86: TRUE | Z86: TRUE | AA86: TRUE | AB86: TRUE | AC86: TRUE | AD86: TRUE | AE86: TRUE | AF86: TRUE | AG86: TRUE | AH86: TRUE | AI86: TRUE | AJ86: TRUE | AK86: TRUE | AL86: TRUE | AM86: TRUE | AN86: TRUE | AO86: TRUE | AP86: TRUE | AQ86: TRUE | AR86: TRUE | AS86: TRUE | AT86: TRUE | AU86: TRUE | AV86: TRUE | AW86: TRUE | AX86: TRUE | AY86: TRUE | AZ86: TRUE | BA86: TRUE | BB86: TRUE | BC86: TRUE | BD86: TRUE | BE86: TRUE | BF86: TRUE | BG86: TRUE | BH86: TRUE | BI86: TRUE | BJ86: TRUE | BK86: TRUE | BL86: TRUE | BM86: TRUE | BN86: FALSE | BO86: FALSE
A87: =A86&C87 -> JuneVASANTHA.EOT HOURS | C87: OT HOURS | E87: =SUM(F87:BO87) -> 36 | J87: 1 | L87: 2 | P87: 2 | R87: 2 | X87: 2 | AB87: 2 | AD87: 2 | AF87: 2 | AH87: 5 | AJ87: 2 | AL87: 2 | AP87: 2 | AR87: 2 | AT87: 2 | AX87: 2 | AZ87: 2 | BL87: 2
C88: 45839
C89: Employee Code | D89: Name | E89: Days Present / OT Hours | F89: M | G89: A | H89: M | I89: A | J89: M | K89: A | L89: M | M89: A | N89: M | O89: A | P89: M | Q89: A | R89: M | S89: A | T89: M | U89: A | V89: M | W89: A | X89: M | Y89: A | Z89: M | AA89: A | AB89: M | AC89: A | AD89: M | AE89: A | AF89: M | AG89: A | AH89: M | AI89: A | AJ89: M | AK89: A | AL89: M | AM89: A | AN89: M | AO89: A | AP89: M | AQ89: A | AR89: M | AS89: A | AT89: M | AU89: A | AV89: M | AW89: A | AX89: M | AY89: A | AZ89: M | BA89: A | BB89: M | BC89: A | BD89: M | BE89: A | BF89: M | BG89: A | BH89: M | BI89: A | BJ89: M | BK89: A | BL89: M | BM89: A | BN89: M | BO89: A
A90: =B90&D90 -> JulyBHUVANESHWARAN.V | B90: July | C90: AC 01 | D90: =IFERROR(VLOOKUP(C90,'Employees List'!$B$2:$E1424,4,0),"") -> BHUVANESHWARAN.V | E90: =COUNTIF(F90:BO90,TRUE)/2 -> 31 | F90: TRUE | G90: TRUE | H90: TRUE | I90: TRUE | J90: TRUE | K90: TRUE | L90: TRUE | M90: TRUE | N90: TRUE | O90: TRUE | P90: TRUE | Q90: TRUE | R90: TRUE | S90: TRUE | T90: TRUE | U90: TRUE | V90: TRUE | W90: TRUE | X90: TRUE | Y90: TRUE | Z90: TRUE | AA90: TRUE | AB90: TRUE | AC90: TRUE | AD90: TRUE | AE90: TRUE | AF90: TRUE | AG90: TRUE | AH90: TRUE | AI90: TRUE | AJ90: TRUE | AK90: TRUE | AL90: TRUE | AM90: TRUE | AN90: TRUE | AO90: TRUE | AP90: TRUE | AQ90: TRUE | AR90: TRUE | AS90: TRUE | AT90: TRUE | AU90: TRUE | AV90: TRUE | AW90: TRUE | AX90: TRUE | AY90: TRUE | AZ90: TRUE | BA90: TRUE | BB90: TRUE | BC90: TRUE | BD90: TRUE | BE90: TRUE | BF90: TRUE | BG90: TRUE | BH90: TRUE | BI90: TRUE | BJ90: TRUE | BK90: TRUE | BL90: TRUE | BM90: TRUE | BN90: TRUE | BO90: TRUE
A91: =A90&C91 -> JulyBHUVANESHWARAN.VOT HOURS | C91: OT HOURS | E91: =COUNTIF(F91:BO91,TRUE)/2 -> 0
A92: =B92&D92 -> JulyTHIRIPURA SUNDARI.R | B92: July | C92: AC 02 | D92: =IFERROR(VLOOKUP(C92,'Employees List'!$B$2:$E1424,4,0),"") -> THIRIPURA SUNDARI.R | E92: =COUNTIF(F92:BO92,TRUE)/2 -> 25 | F92: TRUE | G92: TRUE | H92: TRUE | I92: TRUE | J92: TRUE | K92: TRUE | L92: TRUE | M92: TRUE | N92: TRUE | O92: TRUE | P92: TRUE | Q92: TRUE | R92: TRUE | S92: TRUE | T92: TRUE | U92: TRUE | V92: TRUE | W92: TRUE | X92: TRUE | Y92: TRUE | Z92: TRUE | AA92: TRUE | AB92: TRUE | AC92: TRUE | AD92: TRUE | AE92: TRUE | AF92: TRUE | AG92: TRUE | AH92: TRUE | AI92: TRUE | AJ92: TRUE | AK92: TRUE | AL92: TRUE | AM92: TRUE | AN92: TRUE | AO92: TRUE | AP92: TRUE | AQ92: TRUE | AR92: TRUE | AS92: TRUE | AT92: TRUE | AU92: TRUE | AV92: TRUE | AW92: TRUE | AX92: FALSE | AY92: FALSE | AZ92: FALSE | BA92: FALSE | BB92: FALSE | BC92: FALSE | BD92: FALSE | BE92: FALSE | BF92: TRUE | BG92: TRUE | BH92: FALSE | BI92: FALSE | BJ92: FALSE | BK92: FALSE | BL92: TRUE | BM92: TRUE | BN92: TRUE | BO92: TRUE
A93: =A92&C93 -> JulyTHIRIPURA SUNDARI.ROT HOURS | C93: OT HOURS | E93: =SUM(F93:BO93) -> 4 | AB93: 2 | AL93: 1 | AN93: 1
A94: =B94&D94 -> JulyGANESH | B94: July | C94: PR 02 | D94: =IFERROR(VLOOKUP(C94,'Employees List'!$B$2:$E1424,4,0),"") -> GANESH | E94: =COUNTIF(F94:BO94,TRUE)/2 -> 22 | F94: FALSE | G94: FALSE | H94: TRUE | I94: TRUE | J94: TRUE | K94: TRUE | L94: TRUE | M94: TRUE | N94: TRUE | O94: TRUE | P94: TRUE | Q94: TRUE | R94: TRUE | S94: TRUE | T94: TRUE | U94: TRUE | V94: TRUE | W94: TRUE | X94: TRUE | Y94: TRUE | Z94: TRUE | AA94: TRUE | AB94: TRUE | AC94: TRUE | AD94: TRUE | AE94: TRUE | AF94: FALSE | AG94: FALSE | AH94: FALSE | AI94: FALSE | AJ94: FALSE | AK94: FALSE | AL94: FALSE | AM94: FALSE | AN94: FALSE | AO94: FALSE | AP94: FALSE | AQ94: FALSE | AR94: FALSE | AS94: FALSE | AT94: FALSE | AU94: FALSE | AV94: TRUE | AW94: TRUE | AX94: TRUE | AY94: TRUE | AZ94: TRUE | BA94: TRUE | BB94: TRUE | BC94: TRUE | BD94: TRUE | BE94: TRUE | BF94: TRUE | BG94: TRUE | BH94: TRUE | BI94: TRUE | BJ94: TRUE | BK94: TRUE | BL94: TRUE | BM94: TRUE | BN94: TRUE | BO94: TRUE
A95: =A94&C95 -> JulyGANESHOT HOURS | C95: OT HOURS | E95: =SUM(F95:BO95) -> 16 | N95: 2 | V95: 2 | X95: 2 | AB95: 2 | AX95: 2 | BB95: 2 | BD95: 2 | BL95: 2
A96: =B96&D96 -> JulyILAMATHIVANAN.S | B96: July | C96: DR 01 | D96: =IFERROR(VLOOKUP(C96,'Employees List'!$B$2:$E1424,4,0),"") -> ILAMATHIVANAN.S | E96: =COUNTIF(F96:BO96,TRUE)/2 -> 5 | F96: FALSE | G96: FALSE | H96: FALSE | I96: FALSE | J96: FALSE | K96: FALSE | L96: FALSE | M96: FALSE | N96: FALSE | O96: FALSE | P96: FALSE | Q96: FALSE | R96: TRUE | S96: TRUE | T96: TRUE | U96: TRUE | V96: TRUE | W96: TRUE | X96: TRUE | Y96: TRUE | Z96: FALSE | AA96: FALSE | AB96: TRUE | AC96: TRUE | AD96: FALSE | AE96: FALSE | AF96: FALSE | AG96: FALSE | AH96: FALSE | AI96: FALSE | AJ96: FALSE | AK96: FALSE | AL96: FALSE | AM96: FALSE | AN96: FALSE | AO96: FALSE | AP96: FALSE | AQ96: FALSE | AR96: FALSE | AS96: FALSE | AT96: FALSE | AU96: FALSE | AV96: FALSE | AW96: FALSE | AX96: FALSE | AY96: FALSE | AZ96: FALSE | BA96: FALSE | BB96: FALSE | BC96: FALSE | BD96: FALSE | BE96: FALSE | BF96: FALSE | BG96: FALSE | BH96: FALSE | BI96: FALSE | BJ96: FALSE | BK96: FALSE | BL96: FALSE | BM96: FALSE | BN96: FALSE | BO96: FALSE
A97: =A96&C97 -> JulyILAMATHIVANAN.SOT HOURS | C97: OT HOURS | E97: =SUM(F97:BO97) -> 6 | R97: 2 | V97: 4
A98: =B98&D98 -> JulyAMMU.S | B98: July | C98: PR 07 | D98: =IFERROR(VLOOKUP(C98,'Employees List'!$B$2:$E1424,4,0),"") -> AMMU.S | E98: =COUNTIF(F98:BO98,TRUE)/2 -> 23 | F98: TRUE | G98: TRUE | H98: TRUE | I98: TRUE | J98: TRUE | K98: TRUE | L98: TRUE | M98: TRUE | N98: TRUE | O98: TRUE | P98: TRUE | Q98: TRUE | R98: TRUE | S98: TRUE | T98: TRUE | U98: TRUE | V98: TRUE | W98: TRUE | X98: TRUE | Y98: TRUE | Z98: TRUE | AA98: TRUE | AB98: TRUE | AC98: TRUE | AD98: TRUE | AE98: TRUE | AF98: TRUE | AG98: TRUE | AH98: TRUE | AI98: TRUE | AJ98: TRUE | AK98: TRUE | AL98: TRUE | AM98: TRUE | AN98: TRUE | AO98: TRUE | AP98: TRUE | AQ98: TRUE | AR98: TRUE | AS98: TRUE | AT98: FALSE | AU98: FALSE | AV98: FALSE | AW98: FALSE | AX98: FALSE | AY98: FALSE | AZ98: FALSE | BA98: FALSE | BB98: FALSE | BC98: FALSE | BD98: FALSE | BE98: FALSE | BF98: TRUE | BG98: TRUE | BH98: FALSE | BI98: FALSE | BJ98: FALSE | BK98: FALSE | BL98: TRUE | BM98: TRUE | BN98: TRUE | BO98: TRUE
A99: =A98&C99 -> JulyAMMU.SOT HOURS | C99: OT HOURS | E99: =SUM(F99:BO99) -> 16 | V99: 2 | X99: 2 | AB99: 2 | AJ99: 2 | AN99: 2 | AP99: 2 | BL99: 2 | BN99: 2
A100: =B100&D100 -> JulyREVATHI.S | B100: July | C100: PR 08 | D100: =IFERROR(VLOOKUP(C100,'Employees List'!$B$2:$E1424,4,0),"") -> REVATHI.S | E100: =COUNTIF(F100:BO100,TRUE)/2 -> 30 | F100: TRUE | G100: TRUE | H100: FALSE | I100: FALSE | J100: TRUE | K100: TRUE | L100: TRUE | M100: TRUE | N100: TRUE | O100: TRUE | P100: TRUE | Q100: TRUE | R100: TRUE | S100: TRUE | T100: TRUE | U100: TRUE | V100: TRUE | W100: TRUE | X100: TRUE | Y100: TRUE | Z100: TRUE | AA100: TRUE | AB100: TRUE | AC100: TRUE | AD100: TRUE | AE100: TRUE | AF100: TRUE | AG100: TRUE | AH100: TRUE | AI100: TRUE | AJ100: TRUE | AK100: TRUE | AL100: TRUE | AM100: TRUE | AN100: TRUE | AO100: TRUE | AP100: TRUE | AQ100: TRUE | AR100: TRUE | AS100: TRUE | AT100: TRUE | AU100: TRUE | AV100: TRUE | AW100: TRUE | AX100: TRUE | AY100: TRUE | AZ100: TRUE | BA100: TRUE | BB100: TRUE | BC100: TRUE | BD100: TRUE | BE100: TRUE | BF100: TRUE | BG100: TRUE | BH100: TRUE | BI100: TRUE | BJ100: TRUE | BK100: TRUE | BL100: TRUE | BM100: TRUE | BN100: TRUE | BO100: TRUE
A101: =A100&C101 -> JulyREVATHI.SOT HOURS | C101: OT HOURS | E101: =SUM(F101:BO101) -> 32 | V101: 2 | X101: 2 | AB101: 2 | AJ101: 2 | AN101: 2 | AP101: 2 | AR101: 6 | AT101: 2 | AX101: 2 | BB101: 2 | BD101: 2 | BJ101: 2 | BL101: 2 | BN101: 2
A102: =B102&D102 -> JulyLEELAVATHI.M | B102: July | C102: AC 03 | D102: =IFERROR(VLOOKUP(C102,'Employees List'!$B$2:$E1424,4,0),"") -> LEELAVATHI.M | E102: =COUNTIF(F102:BO102,TRUE)/2 -> 30 | F102: TRUE | G102: TRUE | H102: TRUE | I102: TRUE | J102: TRUE | K102: TRUE | L102: TRUE | M102: TRUE | N102: TRUE | O102: TRUE | P102: TRUE | Q102: TRUE | R102: TRUE | S102: TRUE | T102: TRUE | U102: TRUE | V102: TRUE | W102: TRUE | X102: FALSE | Y102: FALSE | Z102: TRUE | AA102: TRUE | AB102: TRUE | AC102: TRUE | AD102: TRUE | AE102: TRUE | AF102: TRUE | AG102: TRUE | AH102: TRUE | AI102: TRUE | AJ102: TRUE | AK102: TRUE | AL102: TRUE | AM102: TRUE | AN102: TRUE | AO102: TRUE | AP102: TRUE | AQ102: TRUE | AR102: TRUE | AS102: TRUE | AT102: TRUE | AU102: TRUE | AV102: TRUE | AW102: TRUE | AX102: TRUE | AY102: TRUE | AZ102: TRUE | BA102: TRUE | BB102: TRUE | BC102: TRUE | BD102: TRUE | BE102: TRUE | BF102: TRUE | BG102: TRUE | BH102: TRUE | BI102: TRUE | BJ102: TRUE | BK102: TRUE | BL102: TRUE | BM102: TRUE | BN102: TRUE | BO102: TRUE
...

Sheet Attendance Report
A1: Emp Id | B1: Name | O1: April | P1: May | Q1: June | R1: July | S1: August | T1: September | U1: October | V1: November | W1: December | X1: January | Y1: February | Z1: March | AA1: Total Present
A2: AC 01 | B2: =IFERROR(VLOOKUP(A2,'Employees List'!$B$2:E981,4,0),"") -> BHUVANESHWARAN.V | C2: =$O$1&B2 -> AprilBHUVANESHWARAN.V | D2: =$P$1&B2 -> MayBHUVANESHWARAN.V | E2: =$Q$1&B2 -> JuneBHUVANESHWARAN.V | F2: =$R$1&B2 -> JulyBHUVANESHWARAN.V | G2: =$S$1&B2 -> AugustBHUVANESHWARAN.V | H2: =$T$1&B2 -> SeptemberBHUVANESHWARAN.V | I2: =$U$1&B2 -> OctoberBHUVANESHWARAN.V | J2: =$V$1&B2 -> NovemberBHUVANESHWARAN.V | K2: =$W$1&B2 -> DecemberBHUVANESHWARAN.V | L2: =$X$1&B2 -> JanuaryBHUVANESHWARAN.V | M2: =$Y$1&B2 -> FebruaryBHUVANESHWARAN.V | N2: =$Z$1&B2 -> MarchBHUVANESHWARAN.V | O2: =IFERROR(VLOOKUP(C2,'Daily Attendance 25-26'!$A$1:BP981,5,0),"") -> 30 | P2: =IFERROR(VLOOKUP(D2,'Daily Attendance 25-26'!$A$1:BP981,5,0),"") -> 31 | Q2: =IFERROR(VLOOKUP(E2,'Daily Attendance 25-26'!$A$1:BP981,5,0),"") -> 30 | R2: =IFERROR(VLOOKUP(F2,'Daily Attendance 25-26'!$A$1:BP981,5,0),"") -> 31 | S2: =IFERROR(VLOOKUP(G2,'Daily Attendance 25-26'!$A$1:BP981,5,0),"") -> 31 | T2: =IFERROR(VLOOKUP(H2,'Daily Attendance 25-26'!$A$1:BP981,5,0),"") | U2: =IFERROR(VLOOKUP(I2,'Daily Attendance 25-26'!$A$1:BP981,5,0),"") | V2: =IFERROR(VLOOKUP(J2,'Daily Attendance 25-26'!$A$1:BP981,5,0),"") -> 30 | W2: =IFERROR(VLOOKUP(K2,'Daily Attendance 25-26'!$A$1:BP981,5,0),"") -> 31 | X2: =IFERROR(VLOOKUP(L2,'Daily Attendance 25-26'!$A$1:BP981,5,0),"") -> 31 | Y2: =IFERROR(VLOOKUP(M2,'Daily Attendance 25-26'!$A$1:BP981,5,0),"") -> 28 | Z2: =IFERROR(VLOOKUP(N2,'Daily Attendance 25-26'!$A$1:BP981,5,0),"") | AA2: =SUM(D2:Z2) -> 273
A3: AC 02 | B3: =IFERROR(VLOOKUP(A3,'Employees List'!$B$2:E981,4,0),"") -> THIRIPURA SUNDARI.R | C3: =$O$1&B3 -> AprilTHIRIPURA SUNDARI.R | D3: =$P$1&B3 -> MayTHIRIPURA SUNDARI.R | E3: =$Q$1&B3 -> JuneTHIRIPURA SUNDARI.R | F3: =$R$1&B3 -> JulyTHIRIPURA SUNDARI.R | G3: =$S$1&B3 -> AugustTHIRIPURA SUNDARI.R | H3: =$T$1&B3 -> SeptemberTHIRIPURA SUNDARI.R | I3: =$U$1&B3 -> OctoberTHIRIPURA SUNDARI.R | J3: =$V$1&B3 -> NovemberTHIRIPURA SUNDARI.R | K3: =$W$1&B3 -> DecemberTHIRIPURA SUNDARI.R | L3: =$X$1&B3 -> JanuaryTHIRIPURA SUNDARI.R | M3: =$Y$1&B3 -> FebruaryTHIRIPURA SUNDARI.R | N3: =$Z$1&B3 -> MarchTHIRIPURA SUNDARI.R | O3: =IFERROR(VLOOKUP(C3,'Daily Attendance 25-26'!$A$1:BP981,5,0),"") -> 30 | P3: =IFERROR(VLOOKUP(D3,'Daily Attendance 25-26'!$A$1:BP981,5,0),"") -> 31 | Q3: =IFERROR(VLOOKUP(E3,'Daily Attendance 25-26'!$A$1:BP981,5,0),"") -> 30 | R3: =IFERROR(VLOOKUP(F3,'Daily Attendance 25-26'!$A$1:BP981,5,0),"") -> 25 | S3: =IFERROR(VLOOKUP(G3,'Daily Attendance 25-26'!$A$1:BP981,5,0),"") -> 29 | T3: =IFERROR(VLOOKUP(H3,'Daily Attendance 25-26'!$A$1:BP981,5,0),"") | U3: =IFERROR(VLOOKUP(I3,'Daily Attendance 25-26'!$A$1:BP981,5,0),"") | V3: =IFERROR(VLOOKUP(J3,'Daily Attendance 25-26'!$A$1:BP981,5,0),"") -> 30 | W3: =IFERROR(VLOOKUP(K3,'Daily Attendance 25-26'!$A$1:BP981,5,0),"") -> 31 | X3: =IFERROR(VLOOKUP(L3,'Daily Attendance 25-26'!$A$1:BP981,5,0),"") -> 31 | Y3: =IFERROR(VLOOKUP(M3,'Daily Attendance 25-26'!$A$1:BP981,5,0),"") -> 28 | Z3: =IFERROR(VLOOKUP(N3,'Daily Attendance 25-26'!$A$1:BP981,5,0),"") | AA3: =SUM(D3:Z3) -> 265
A4: PR 02 | B4: =IFERROR(VLOOKUP(A4,'Employees List'!$B$2:E981,4,0),"") -> GANESH | C4: =$O$1&B4 -> AprilGANESH | D4: =$P$1&B4 -> MayGANESH | E4: =$Q$1&B4 -> JuneGANESH | F4: =$R$1&B4 -> JulyGANESH | G4: =$S$1&B4 -> AugustGANESH | H4: =$T$1&B4 -> SeptemberGANESH | I4: =$U$1&B4 -> OctoberGANESH | J4: =$V$1&B4 -> NovemberGANESH | K4: =$W$1&B4 -> DecemberGANESH | L4: =$X$1&B4 -> JanuaryGANESH | M4: =$Y$1&B4 -> FebruaryGANESH | N4: =$Z$1&B4 -> MarchGANESH | O4: =IFERROR(VLOOKUP(C4,'Daily Attendance 25-26'!$A$1:BP981,5,0),"") -> 22 | P4: =IFERROR(VLOOKUP(D4,'Daily Attendance 25-26'!$A$1:BP981,5,0),"") -> 24.5 | Q4: =IFERROR(VLOOKUP(E4,'Daily Attendance 25-26'!$A$1:BP981,5,0),"") -> 25 | R4: =IFERROR(VLOOKUP(F4,'Daily Attendance 25-26'!$A$1:BP981,5,0),"") -> 22 | S4: =IFERROR(VLOOKUP(G4,'Daily Attendance 25-26'!$A$1:BP981,5,0),"") -> 29 | T4: =IFERROR(VLOOKUP(H4,'Daily Attendance 25-26'!$A$1:BP981,5,0),"") | U4: =IFERROR(VLOOKUP(I4,'Daily Attendance 25-26'!$A$1:BP981,5,0),"") | V4: =IFERROR(VLOOKUP(J4,'Daily Attendance 25-26'!$A$1:BP981,5,0),"") -> 24 | W4: =IFERROR(VLOOKUP(K4,'Daily Attendance 25-26'!$A$1:BP981,5,0),"") -> 26 | X4: =IFERROR(VLOOKUP(L4,'Daily Attendance 25-26'!$A$1:BP981,5,0),"") -> 25 | Y4: =IFERROR(VLOOKUP(M4,'Daily Attendance 25-26'!$A$1:BP981,5,0),"") -> 25 | Z4: =IFERROR(VLOOKUP(N4,'Daily Attendance 25-26'!$A$1:BP981,5,0),"") | AA4: =SUM(D4:Z4) -> 222.5
A5: DR 01 | B5: =IFERROR(VLOOKUP(A5,'Employees List'!$B$2:E981,4,0),"") -> ILAMATHIVANAN.S | C5: =$O$1&B5 -> AprilILAMATHIVANAN.S | D5: =$P$1&B5 -> MayILAMATHIVANAN.S | E5: =$Q$1&B5 -> JuneILAMATHIVANAN.S | F5: =$R$1&B5 -> JulyILAMATHIVANAN.S | G5: =$S$1&B5 -> AugustILAMATHIVANAN.S | H5: =$T$1&B5 -> SeptemberILAMATHIVANAN.S | I5: =$U$1&B5 -> OctoberILAMATHIVANAN.S | J5: =$V$1&B5 -> NovemberILAMATHIVANAN.S | K5: =$W$1&B5 -> DecemberILAMATHIVANAN.S | L5: =$X$1&B5 -> JanuaryILAMATHIVANAN.S | M5: =$Y$1&B5 -> FebruaryILAMATHIVANAN.S | N5: =$Z$1&B5 -> MarchILAMATHIVANAN.S | O5: =IFERROR(VLOOKUP(C5,'Daily Attendance 25-26'!$A$1:BP981,5,0),"") -> 23 | P5: =IFERROR(VLOOKUP(D5,'Daily Attendance 25-26'!$A$1:BP981,5,0),"") -> 28.5 | Q5: =IFERROR(VLOOKUP(E5,'Daily Attendance 25-26'!$A$1:BP981,5,0),"") -> 22 | R5: =IFERROR(VLOOKUP(F5,'Daily Attendance 25-26'!$A$1:BP981,5,0),"") -> 5 | S5: =IFERROR(VLOOKUP(G5,'Daily Attendance 25-26'!$A$1:BP981,5,0),"") -> 0 | T5: =IFERROR(VLOOKUP(H5,'Daily Attendance 25-26'!$A$1:BP981,5,0),"") | U5: =IFERROR(VLOOKUP(I5,'Daily Attendance 25-26'!$A$1:BP981,5,0),"") | V5: =IFERROR(VLOOKUP(J5,'Daily Attendance 25-26'!$A$1:BP981,5,0),"") -> 0 | W5: =IFERROR(VLOOKUP(K5,'Daily Attendance 25-26'!$A$1:BP981,5,0),"") | X5: =IFERROR(VLOOKUP(L5,'Daily Attendance 25-26'!$A$1:BP981,5,0),"") | Y5: =IFERROR(VLOOKUP(M5,'Daily Attendance 25-26'!$A$1:BP981,5,0),"") | Z5: =IFERROR(VLOOKUP(N5,'Daily Attendance 25-26'!$A$1:BP981,5,0),"") | AA5: =SUM(D5:Z5) -> 78.5
A6: PR 07 | B6: =IFERROR(VLOOKUP(A6,'Employees List'!$B$2:E981,4,0),"") -> AMMU.S | C6: =$O$1&B6 -> AprilAMMU.S | D6: =$P$1&B6 -> MayAMMU.S | E6: =$Q$1&B6 -> JuneAMMU.S | F6: =$R$1&B6 -> JulyAMMU.S | G6: =$S$1&B6 -> AugustAMMU.S | H6: =$T$1&B6 -> SeptemberAMMU.S | I6: =$U$1&B6 -> OctoberAMMU.S | J6: =$V$1&B6 -> NovemberAMMU.S | K6: =$W$1&B6 -> DecemberAMMU.S | L6: =$X$1&B6 -> JanuaryAMMU.S | M6: =$Y$1&B6 -> FebruaryAMMU.S | N6: =$Z$1&B6 -> MarchAMMU.S | O6: =IFERROR(VLOOKUP(C6,'Daily Attendance 25-26'!$A$1:BP981,5,0),"") -> 30 | P6: =IFERROR(VLOOKUP(D6,'Daily Attendance 25-26'!$A$1:BP981,5,0),"") -> 27 | Q6: =IFERROR(VLOOKUP(E6,'Daily Attendance 25-26'!$A$1:BP981,5,0),"") -> 28 | R6: =IFERROR(VLOOKUP(F6,'Daily Attendance 25-26'!$A$1:BP981,5,0),"") -> 23 | S6: =IFERROR(VLOOKUP(G6,'Daily Attendance 25-26'!$A$1:BP981,5,0),"") -> 31 | T6: =IFERROR(VLOOKUP(H6,'Daily Attendance 25-26'!$A$1:BP981,5,0),"") | U6: =IFERROR(VLOOKUP(I6,'Daily Attendance 25-26'!$A$1:BP981,5,0),"") | V6: =IFERROR(VLOOKUP(J6,'Daily Attendance 25-26'!$A$1:BP981,5,0),"") -> 28 | W6: =IFERROR(VLOOKUP(K6,'Daily Attendance 25-26'!$A$1:BP981,5,0),"") -> 29 | X6: =IFERROR(VLOOKUP(L6,'Daily Attendance 25-26'!$A$1:BP981,5,0),"") -> 28 | Y6: =IFERROR(VLOOKUP(M6,'Daily Attendance 25-26'!$A$1:BP981,5,0),"") -> 28 | Z6: =IFERROR(VLOOKUP(N6,'Daily Attendance 25-26'!$A$1:BP981,5,0),"") | AA6: =SUM(D6:Z6) -> 252
A7: PR 08 | B7: =IFERROR(VLOOKUP(A7,'Employees List'!$B$2:E981,4,0),"") -> REVATHI.S | C7: =$O$1&B7 -> AprilREVATHI.S | D7: =$P$1&B7 -> MayREVATHI.S | E7: =$Q$1&B7 -> JuneREVATHI.S | F7: =$R$1&B7 -> JulyREVATHI.S | G7: =$S$1&B7 -> AugustREVATHI.S | H7: =$T$1&B7 -> SeptemberREVATHI.S | I7: =$U$1&B7 -> OctoberREVATHI.S | J7: =$V$1&B7 -> NovemberREVATHI.S | K7: =$W$1&B7 -> DecemberREVATHI.S | L7: =$X$1&B7 -> JanuaryREVATHI.S | M7: =$Y$1&B7 -> FebruaryREVATHI.S | N7: =$Z$1&B7 -> MarchREVATHI.S | O7: =IFERROR(VLOOKUP(C7,'Daily Attendance 25-26'!$A$1:BP981,5,0),"") -> 29 | P7: =IFERROR(VLOOKUP(D7,'Daily Attendance 25-26'!$A$1:BP981,5,0),"") -> 30 | Q7: =IFERROR(VLOOKUP(E7,'Daily Attendance 25-26'!$A$1:BP981,5,0),"") -> 29 | R7: =IFERROR(VLOOKUP(F7,'Daily Attendance 25-26'!$A$1:BP981,5,0),"") -> 30 | S7: =IFERROR(VLOOKUP(G7,'Daily Attendance 25-26'!$A$1:BP981,5,0),"") -> 29 | T7: =IFERROR(VLOOKUP(H7,'Daily Attendance 25-26'!$A$1:BP981,5,0),"") | U7: =IFERROR(VLOOKUP(I7,'Daily Attendance 25-26'!$A$1:BP981,5,0),"") | V7: =IFERROR(VLOOKUP(J7,'Daily Attendance 25-26'!$A$1:BP981,5,0),"") -> 27 | W7: =IFERROR(VLOOKUP(K7,'Daily Attendance 25-26'!$A$1:BP981,5,0),"") -> 30 | X7: =IFERROR(VLOOKUP(L7,'Daily Attendance 25-26'!$A$1:BP981,5,0),"") -> 26 | Y7: =IFERROR(VLOOKUP(M7,'Daily Attendance 25-26'!$A$1:BP981,5,0),"") -> 25 | Z7: =IFERROR(VLOOKUP(N7,'Daily Attendance 25-26'!$A$1:BP981,5,0),"") | AA7: =SUM(D7:Z7) -> 255
A8: AC 03 | B8: =IFERROR(VLOOKUP(A8,'Employees List'!$B$2:E981,4,0),"") -> LEELAVATHI.M | C8: =$O$1&B8 -> AprilLEELAVATHI.M | D8: =$P$1&B8 -> MayLEELAVATHI.M | E8: =$Q$1&B8 -> JuneLEELAVATHI.M | F8: =$R$1&B8 -> JulyLEELAVATHI.M | G8: =$S$1&B8 -> AugustLEELAVATHI.M | H8: =$T$1&B8 -> SeptemberLEELAVATHI.M | I8: =$U$1&B8 -> OctoberLEELAVATHI.M | J8: =$V$1&B8 -> NovemberLEELAVATHI.M | K8: =$W$1&B8 -> DecemberLEELAVATHI.M | L8: =$X$1&B8 -> JanuaryLEELAVATHI.M | M8: =$Y$1&B8 -> FebruaryLEELAVATHI.M | N8: =$Z$1&B8 -> MarchLEELAVATHI.M | O8: =IFERROR(VLOOKUP(C8,'Daily Attendance 25-26'!$A$1:BP981,5,0),"") -> 30 | P8: =IFERROR(VLOOKUP(D8,'Daily Attendance 25-26'!$A$1:BP981,5,0),"") -> 29 | Q8: =IFERROR(VLOOKUP(E8,'Daily Attendance 25-26'!$A$1:BP981,5,0),"") -> 29 | R8: =IFERROR(VLOOKUP(F8,'Daily Attendance 25-26'!$A$1:BP981,5,0),"") -> 30 | S8: =IFERROR(VLOOKUP(G8,'Daily Attendance 25-26'!$A$1:BP981,5,0),"") -> 30 | T8: =IFERROR(VLOOKUP(H8,'Daily Attendance 25-26'!$A$1:BP981,5,0),"") | U8: =IFERROR(VLOOKUP(I8,'Daily Attendance 25-26'!$A$1:BP981,5,0),"") | V8: =IFERROR(VLOOKUP(J8,'Daily Attendance 25-26'!$A$1:BP981,5,0),"") -> 30 | W8: =IFERROR(VLOOKUP(K8,'Daily Attendance 25-26'!$A$1:BP981,5,0),"") -> 31 | X8: =IFERROR(VLOOKUP(L8,'Daily Attendance 25-26'!$A$1:BP981,5,0),"") -> 31 | Y8: =IFERROR(VLOOKUP(M8,'Daily Attendance 25-26'!$A$1:BP981,5,0),"") -> 28 | Z8: =IFERROR(VLOOKUP(N8,'Daily Attendance 25-26'!$A$1:BP981,5,0),"") | AA8: =SUM(D8:Z8) -> 268
A9: PR 27 | B9: =IFERROR(VLOOKUP(A9,'Employees List'!$B$2:E981,4,0),"") -> PARSHU BAGH | C9: =$O$1&B9 -> AprilPARSHU BAGH | D9: =$P$1&B9 -> MayPARSHU BAGH | E9: =$Q$1&B9 -> JunePARSHU BAGH | F9: =$R$1&B9 -> JulyPARSHU BAGH | G9: =$S$1&B9 -> AugustPARSHU BAGH | H9: =$T$1&B9 -> SeptemberPARSHU BAGH | I9: =$U$1&B9 -> OctoberPARSHU BAGH | J9: =$V$1&B9 -> NovemberPARSHU BAGH | K9: =$W$1&B9 -> DecemberPARSHU BAGH | L9: =$X$1&B9 -> JanuaryPARSHU BAGH | M9: =$Y$1&B9 -> FebruaryPARSHU BAGH | N9: =$Z$1&B9 -> MarchPARSHU BAGH | O9: =IFERROR(VLOOKUP(C9,'Daily Attendance 25-26'!$A$1:BP981,5,0),"") -> 9 | P9: =IFERROR(VLOOKUP(D9,'Daily Attendance 25-26'!$A$1:BP981,5,0),"") | Q9: =IFERROR(VLOOKUP(E9,'Daily Attendance 25-26'!$A$1:BP981,5,0),"") | R9: =IFERROR(VLOOKUP(F9,'Daily Attendance 25-26'!$A$1:BP981,5,0),"") -> 24 | S9: =IFERROR(VLOOKUP(G9,'Daily Attendance 25-26'!$A$1:BP981,5,0),"") -> 4.5 | T9: =IFERROR(VLOOKUP(H9,'Daily Attendance 25-26'!$A$1:BP981,5,0),"") | U9: =IFERROR(VLOOKUP(I9,'Daily Attendance 25-26'!$A$1:BP981,5,0),"") | V9: =IFERROR(VLOOKUP(J9,'Daily Attendance 25-26'!$A$1:BP981,5,0),"") | W9: =IFERROR(VLOOKUP(K9,'Daily Attendance 25-26'!$A$1:BP981,5,0),"") | X9: =IFERROR(VLOOKUP(L9,'Daily Attendance 25-26'!$A$1:BP981,5,0),"") -> 26 | Y9: =IFERROR(VLOOKUP(M9,'Daily Attendance 25-26'!$A$1:BP981,5,0),"") -> 24 | Z9: =IFERROR(VLOOKUP(N9,'Daily Attendance 25-26'!$A$1:BP981,5,0),"") | AA9: =SUM(D9:Z9) -> 87.5
A10: PR 12 | B10: =IFERROR(VLOOKUP(A10,'Employees List'!$B$2:E981,4,0),"") -> PINU | C10: =$O$1&B10 -> AprilPINU | D10: =$P$1&B10 -> MayPINU | E10: =$Q$1&B10 -> JunePINU | F10: =$R$1&B10 -> JulyPINU | G10: =$S$1&B10 -> AugustPINU | H10: =$T$1&B10 -> SeptemberPINU | I10: =$U$1&B10 -> OctoberPINU | J10: =$V$1&B10 -> NovemberPINU | K10: =$W$1&B10 -> DecemberPINU | L10: =$X$1&B10 -> JanuaryPINU | M10: =$Y$1&B10 -> FebruaryPINU | N10: =$Z$1&B10 -> MarchPINU | O10: =IFERROR(VLOOKUP(C10,'Daily Attendance 25-26'!$A$1:BP981,5,0),"") -> 9 | P10: =IFERROR(VLOOKUP(D10,'Daily Attendance 25-26'!$A$1:BP981,5,0),"") | Q10: =IFERROR(VLOOKUP(E10,'Daily Attendance 25-26'!$A$1:BP981,5,0),"") | R10: =IFERROR(VLOOKUP(F10,'Daily Attendance 25-26'!$A$1:BP981,5,0),"") | S10: =IFERROR(VLOOKUP(G10,'Daily Attendance 25-26'!$A$1:BP981,5,0),"") | T10: =IFERROR(VLOOKUP(H10,'Daily Attendance 25-26'!$A$1:BP981,5,0),"") | U10: =IFERROR(VLOOKUP(I10,'Daily Attendance 25-26'!$A$1:BP981,5,0),"") | V10: =IFERROR(VLOOKUP(J10,'Daily Attendance 25-26'!$A$1:BP981,5,0),"") | W10: =IFERROR(VLOOKUP(K10,'Daily Attendance 25-26'!$A$1:BP981,5,0),"") | X10: =IFERROR(VLOOKUP(L10,'Daily Attendance 25-26'!$A$1:BP981,5,0),"") | Y10: =IFERROR(VLOOKUP(M10,'Daily Attendance 25-26'!$A$1:BP981,5,0),"") | Z10: =IFERROR(VLOOKUP(N10,'Daily Attendance 25-26'!$A$1:BP981,5,0),"") | AA10: =SUM(D10:Z10) -> 9
A11: PR 05 | B11: =IFERROR(VLOOKUP(A11,'Employees List'!$B$2:E981,4,0),"") -> SANJAY BAGARTTI.K | C11: =$O$1&B11 -> AprilSANJAY BAGARTTI.K | D11: =$P$1&B11 -> MaySANJAY BAGARTTI.K | E11: =$Q$1&B11 -> JuneSANJAY BAGARTTI.K | F11: =$R$1&B11 -> JulySANJAY BAGARTTI.K | G11: =$S$1&B11 -> AugustSANJAY BAGARTTI.K | H11: =$T$1&B11 -> SeptemberSANJAY BAGARTTI.K | I11: =$U$1&B11 -> OctoberSANJAY BAGARTTI.K | J11: =$V$1&B11 -> NovemberSANJAY BAGARTTI.K | K11: =$W$1&B11 -> DecemberSANJAY BAGARTTI.K | L11: =$X$1&B11 -> JanuarySANJAY BAGARTTI.K | M11: =$Y$1&B11 -> FebruarySANJAY BAGARTTI.K | N11: =$Z$1&B11 -> MarchSANJAY BAGARTTI.K | O11: =IFERROR(VLOOKUP(C11,'Daily Attendance 25-26'!$A$1:BP981,5,0),"") -> 30 | P11: =IFERROR(VLOOKUP(D11,'Daily Attendance 25-26'!$A$1:BP981,5,0),"") -> 31 | Q11: =IFERROR(VLOOKUP(E11,'Daily Attendance 25-26'!$A$1:BP981,5,0),"") -> 29 | R11: =IFERROR(VLOOKUP(F11,'Daily Attendance 25-26'!$A$1:BP981,5,0),"") -> 31 | S11: =IFERROR(VLOOKUP(G11,'Daily Attendance 25-26'!$A$1:BP981,5,0),"") -> 30 | T11: =IFERROR(VLOOKUP(H11,'Daily Attendance 25-26'!$A$1:BP981,5,0),"") | U11: =IFERROR(VLOOKUP(I11,'Daily Attendance 25-26'!$A$1:BP981,5,0),"") | V11: =IFERROR(VLOOKUP(J11,'Daily Attendance 25-26'!$A$1:BP981,5,0),"") -> 30 | W11: =IFERROR(VLOOKUP(K11,'Daily Attendance 25-26'!$A$1:BP981,5,0),"") -> 19 | X11: =IFERROR(VLOOKUP(L11,'Daily Attendance 25-26'!$A$1:BP981,5,0),"") -> 26 | Y11: =IFERROR(VLOOKUP(M11,'Daily Attendance 25-26'!$A$1:BP981,5,0),"") -> 28 | Z11: =IFERROR(VLOOKUP(N11,'Daily Attendance 25-26'!$A$1:BP981,5,0),"") | AA11: =SUM(D11:Z11) -> 254
A12: PR 03 | B12: =IFERROR(VLOOKUP(A12,'Employees List'!$B$2:E981,4,0),"") -> ADHIKARI BALIA.A | C12: =$O$1&B12 -> AprilADHIKARI BALIA.A | D12: =$P$1&B12 -> MayADHIKARI BALIA.A | E12: =$Q$1&B12 -> JuneADHIKARI BALIA.A | F12: =$R$1&B12 -> JulyADHIKARI BALIA.A | G12: =$S$1&B12 -> AugustADHIKARI BALIA.A | H12: =$T$1&B12 -> SeptemberADHIKARI BALIA.A | I12: =$U$1&B12 -> OctoberADHIKARI BALIA.A | J12: =$V$1&B12 -> NovemberADHIKARI BALIA.A | K12: =$W$1&B12 -> DecemberADHIKARI BALIA.A | L12: =$X$1&B12 -> JanuaryADHIKARI BALIA.A | M12: =$Y$1&B12 -> FebruaryADHIKARI BALIA.A | N12: =$Z$1&B12 -> MarchADHIKARI BALIA.A | O12: =IFERROR(VLOOKUP(C12,'Daily Attendance 25-26'!$A$1:BP981,5,0),"") -> 10 | P12: =IFERROR(VLOOKUP(D12,'Daily Attendance 25-26'!$A$1:BP981,5,0),"") -> 31 | Q12: =IFERROR(VLOOKUP(E12,'Daily Attendance 25-26'!$A$1:BP981,5,0),"") -> 29 | R12: =IFERROR(VLOOKUP(F12,'Daily Attendance 25-26'!$A$1:BP981,5,0),"") -> 30 | S12: =IFERROR(VLOOKUP(G12,'Daily Attendance 25-26'!$A$1:BP981,5,0),"") -> 30 | T12: =IFERROR(VLOOKUP(H12,'Daily Attendance 25-26'!$A$1:BP981,5,0),"") | U12: =IFERROR(VLOOKUP(I12,'Daily Attendance 25-26'!$A$1:BP981,5,0),"") | V12: =IFERROR(VLOOKUP(J12,'Daily Attendance 25-26'!$A$1:BP981,5,0),"") | W12: =IFERROR(VLOOKUP(K12,'Daily Attendance 25-26'!$A$1:BP981,5,0),"") | X12: =IFERROR(VLOOKUP(L12,'Daily Attendance 25-26'!$A$1:BP981,5,0),"") -> 26 | Y12: =IFERROR(VLOOKUP(M12,'Daily Attendance 25-26'!$A$1:BP981,5,0),"") -> 28 | Z12: =IFERROR(VLOOKUP(N12,'Daily Attendance 25-26'!$A$1:BP981,5,0),"") | AA12: =SUM(D12:Z12) -> 184
A13: PR 04 | B13: =IFERROR(VLOOKUP(A13,'Employees List'!$B$2:E981,4,0),"") -> RUPESH KISAN | C13: =$O$1&B13 -> AprilRUPESH KISAN | D13: =$P$1&B13 -> MayRUPESH KISAN | E13: =$Q$1&B13 -> JuneRUPESH KISAN | F13: =$R$1&B13 -> JulyRUPESH KISAN | G13: =$S$1&B13 -> AugustRUPESH KISAN | H13: =$T$1&B13 -> SeptemberRUPESH KISAN | I13: =$U$1&B13 -> OctoberRUPESH KISAN | J13: =$V$1&B13 -> NovemberRUPESH KISAN | K13: =$W$1&B13 -> DecemberRUPESH KISAN | L13: =$X$1&B13 -> JanuaryRUPESH KISAN | M13: =$Y$1&B13 -> FebruaryRUPESH KISAN | N13: =$Z$1&B13 -> MarchRUPESH KISAN | O13: =IFERROR(VLOOKUP(C13,'Daily Attendance 25-26'!$A$1:BP981,5,0),"") -> 10 | P13: =IFERROR(VLOOKUP(D13,'Daily Attendance 25-26'!$A$1:BP981,5,0),"") -> 31 | Q13: =IFERROR(VLOOKUP(E13,'Daily Attendance 25-26'!$A$1:BP981,5,0),"") -> 29 | R13: =IFERROR(VLOOKUP(F13,'Daily Attendance 25-26'!$A$1:BP981,5,0),"") -> 31 | S13: =IFERROR(VLOOKUP(G13,'Daily Attendance 25-26'!$A$1:BP981,5,0),"") -> 30 | T13: =IFERROR(VLOOKUP(H13,'Daily Attendance 25-26'!$A$1:BP981,5,0),"") | U13: =IFERROR(VLOOKUP(I13,'Daily Attendance 25-26'!$A$1:BP981,5,0),"") | V13: =IFERROR(VLOOKUP(J13,'Daily Attendance 25-26'!$A$1:BP981,5,0),"") | W13: =IFERROR(VLOOKUP(K13,'Daily Attendance 25-26'!$A$1:BP981,5,0),"") | X13: =IFERROR(VLOOKUP(L13,'Daily Attendance 25-26'!$A$1:BP981,5,0),"") | Y13: =IFERROR(VLOOKUP(M13,'Daily Attendance 25-26'!$A$1:BP981,5,0),"") | Z13: =IFERROR(VLOOKUP(N13,'Daily Attendance 25-26'!$A$1:BP981,5,0),"") | AA13: =SUM(D13:Z13) -> 131
A14: PR 21 | B14: =IFERROR(VLOOKUP(A14,'Employees List'!$B$2:E981,4,0),"") -> LIPAN | C14: =$O$1&B14 -> AprilLIPAN | D14: =$P$1&B14 -> MayLIPAN | E14: =$Q$1&B14 -> JuneLIPAN | F14: =$R$1&B14 -> JulyLIPAN | G14: =$S$1&B14 -> AugustLIPAN | H14: =$T$1&B14 -> SeptemberLIPAN | I14: =$U$1&B14 -> OctoberLIPAN | J14: =$V$1&B14 -> NovemberLIPAN | K14: =$W$1&B14 -> DecemberLIPAN | L14: =$X$1&B14 -> JanuaryLIPAN | M14: =$Y$1&B14 -> FebruaryLIPAN | N14: =$Z$1&B14 -> MarchLIPAN | O14: =IFERROR(VLOOKUP(C14,'Daily Attendance 25-26'!$A$1:BP981,5,0),"") -> 10 | P14: =IFERROR(VLOOKUP(D14,'Daily Attendance 25-26'!$A$1:BP981,5,0),"") -> 30 | Q14: =IFERROR(VLOOKUP(E14,'Daily Attendance 25-26'!$A$1:BP981,5,0),"") -> 30 | R14: =IFERROR(VLOOKUP(F14,'Daily Attendance 25-26'!$A$1:BP981,5,0),"") -> 31 | S14: =IFERROR(VLOOKUP(G14,'Daily Attendance 25-26'!$A$1:BP981,5,0),"") -> 31 | T14: =IFERROR(VLOOKUP(H14,'Daily Attendance 25-26'!$A$1:BP981,5,0),"") | U14: =IFERROR(VLOOKUP(I14,'Daily Attendance 25-26'!$A$1:BP981,5,0),"") | V14: =IFERROR(VLOOKUP(J14,'Daily Attendance 25-26'!$A$1:BP981,5,0),"") | W14: =IFERROR(VLOOKUP(K14,'Daily Attendance 25-26'!$A$1:BP981,5,0),"") | X14: =IFERROR(VLOOKUP(L14,'Daily Attendance 25-26'!$A$1:BP981,5,0),"") | Y14: =IFERROR(VLOOKUP(M14,'Daily Attendance 25-26'!$A$1:BP981,5,0),"") | Z14: =IFERROR(VLOOKUP(N14,'Daily Attendance 25-26'!$A$1:BP981,5,0),"") | AA14: =SUM(D14:Z14) -> 132
A15: PR 24 | B15: =IFERROR(VLOOKUP(A15,'Employees List'!$B$2:E981,4,0),"") -> NILAMANI KISAN.B | C15: =$O$1&B15 -> AprilNILAMANI KISAN.B | D15: =$P$1&B15 -> MayNILAMANI KISAN.B | E15: =$Q$1&B15 -> JuneNILAMANI KISAN.B | F15: =$R$1&B15 -> JulyNILAMANI KISAN.B | G15: =$S$1&B15 -> AugustNILAMANI KISAN.B | H15: =$T$1&B15 -> SeptemberNILAMANI KISAN.B | I15: =$U$1&B15 -> OctoberNILAMANI KISAN.B | J15: =$V$1&B15 -> NovemberNILAMANI KISAN.B | K15: =$W$1&B15 -> DecemberNILAMANI KISAN.B | L15: =$X$1&B15 -> JanuaryNILAMANI KISAN.B | M15: =$Y$1&B15 -> FebruaryNILAMANI KISAN.B | N15: =$Z$1&B15 -> MarchNILAMANI KISAN.B | O15: =IFERROR(VLOOKUP(C15,'Daily Attendance 25-26'!$A$1:BP981,5,0),"") -> 27 | P15: =IFERROR(VLOOKUP(D15,'Daily Attendance 25-26'!$A$1:BP981,5,0),"") -> 29 | Q15: =IFERROR(VLOOKUP(E15,'Daily Attendance 25-26'!$A$1:BP981,5,0),"") -> 15 | R15: =IFERROR(VLOOKUP(F15,'Daily Attendance 25-26'!$A$1:BP981,5,0),"") | S15: =IFERROR(VLOOKUP(G15,'Daily Attendance 25-26'!$A$1:BP981,5,0),"") | T15: =IFERROR(VLOOKUP(H15,'Daily Attendance 25-26'!$A$1:BP981,5,0),"") | U15: =IFERROR(VLOOKUP(I15,'Daily Attendance 25-26'!$A$1:BP981,5,0),"") | V15: =IFERROR(VLOOKUP(J15,'Daily Attendance 25-26'!$A$1:BP981,5,0),"") | W15: =IFERROR(VLOOKUP(K15,'Daily Attendance 25-26'!$A$1:BP981,5,0),"") -> 27 | X15: =IFERROR(VLOOKUP(L15,'Daily Attendance 25-26'!$A$1:BP981,5,0),"") -> 10 | Y15: =IFERROR(VLOOKUP(M15,'Daily Attendance 25-26'!$A$1:BP981,5,0),"") -> 0 | Z15: =IFERROR(VLOOKUP(N15,'Daily Attendance 25-26'!$A$1:BP981,5,0),"") | AA15: =SUM(D15:Z15) -> 108
A16: PR 27 | B16: =IFERROR(VLOOKUP(A16,'Employees List'!$B$2:E981,4,0),"") -> PARSHU BAGH | C16: =$O$1&B16 -> AprilPARSHU BAGH | D16: =$P$1&B16 -> MayPARSHU BAGH | E16: =$Q$1&B16 -> JunePARSHU BAGH | F16: =$R$1&B16 -> JulyPARSHU BAGH | G16: =$S$1&B16 -> AugustPARSHU BAGH | H16: =$T$1&B16 -> SeptemberPARSHU BAGH | I16: =$U$1&B16 -> OctoberPARSHU BAGH | J16: =$V$1&B16 -> NovemberPARSHU BAGH | K16: =$W$1&B16 -> DecemberPARSHU BAGH | L16: =$X$1&B16 -> JanuaryPARSHU BAGH | M16: =$Y$1&B16 -> FebruaryPARSHU BAGH | N16: =$Z$1&B16 -> MarchPARSHU BAGH | O16: =IFERROR(VLOOKUP(C16,'Daily Attendance 25-26'!$A$1:BP981,5,0),"") -> 9 | P16: =IFERROR(VLOOKUP(D16,'Daily Attendance 25-26'!$A$1:BP981,5,0),"") | Q16: =IFERROR(VLOOKUP(E16,'Daily Attendance 25-26'!$A$1:BP981,5,0),"") | R16: =IFERROR(VLOOKUP(F16,'Daily Attendance 25-26'!$A$1:BP981,5,0),"") -> 24 | S16: =IFERROR(VLOOKUP(G16,'Daily Attendance 25-26'!$A$1:BP981,5,0),"") -> 4.5 | T16: =IFERROR(VLOOKUP(H16,'Daily Attendance 25-26'!$A$1:BP981,5,0),"") | U16: =IFERROR(VLOOKUP(I16,'Daily Attendance 25-26'!$A$1:BP981,5,0),"") | V16: =IFERROR(VLOOKUP(J16,'Daily Attendance 25-26'!$A$1:BP981,5,0),"") | W16: =IFERROR(VLOOKUP(K16,'Daily Attendance 25-26'!$A$1:BP981,5,0),"") | X16: =IFERROR(VLOOKUP(L16,'Daily Attendance 25-26'!$A$1:BP981,5,0),"") -> 26 | Y16: =IFERROR(VLOOKUP(M16,'Daily Attendance 25-26'!$A$1:BP981,5,0),"") -> 24 | Z16: =IFERROR(VLOOKUP(N16,'Daily Attendance 25-26'!$A$1:BP981,5,0),"") | AA16: =SUM(D16:Z16) -> 87.5
O17: =IFERROR(VLOOKUP(C17,'Daily Attendance 25-26'!$A$1:BP981,5,0),"")

Sheet Advance Sheet
A1: Date | B1: Name | C1: Emp id | D1: Month | E1: Advance Requested | F1: Advance Provided | G1: Advance Deducted | H1: Reason | I1: Status
A2: 45889 | B2: =IFERROR(VLOOKUP(C2,'Employees List'!$B$1:$G$999,4,0),"") -> GANESH | C2: PR 02 | D2: August | F2: 40500 | H2: Opening Balance | I2: Paid
A3: 45889 | B3: =IFERROR(VLOOKUP(C3,'Employees List'!$B$1:$G$999,4,0),"") -> REVATHI.S | C3: PR 08 | D3: August | F3: 2000 | G3: 1000 | H3: Opening Balance | I3: Paid
A4: 45889 | B4: =IFERROR(VLOOKUP(C4,'Employees List'!$B$1:$G$999,4,0),"") -> REVATHI.S | C4: PR 08 | D4: August | E4: 2000 | F4: 2000 | G4: 2000 | H4: Hospital Expenses | I4: Paid
A5: 45894 | B5: =IFERROR(VLOOKUP(C5,'Employees List'!$B$1:$G$999,4,0),"") -> LIPAN | C5: PR 21 | D5: August | E5: 5000 | F5: 5000 | G5: 5000 | H5: Bike EMI | I5: Paid
A6: 45897 | B6: =IFERROR(VLOOKUP(C6,'Employees List'!$B$1:$G$999,4,0),"") -> ADHIKARI BALIA.A | C6: PR 03 | D6: August | E6: 2000 | F6: 2000 | H6: Home | I6: Paid
A7: 45901 | B7: =IFERROR(VLOOKUP(C7,'Employees List'!$B$1:$G$999,4,0),"") -> ADHIKARI BALIA.A | C7: PR 03 | D7: September | E7: 5000 | F7: 5000 | G7: 7000 | H7: Grandma Passed | I7: Paid
A8: 45903 | B8: =IFERROR(VLOOKUP(C8,'Employees List'!$B$1:$G$999,4,0),"") -> RUPESH KISAN | C8: PR 04 | D8: September | E8: 10000 | F8: 7000 | G8: 7000 | H8: Loan EMI | I8: Paid
A9: 45904 | B9: =IFERROR(VLOOKUP(C9,'Employees List'!$B$1:$G$999,4,0),"") -> GANESH | C9: PR 02 | D9: September | E9: 500 | F9: 500 | G9: 5000 | H9: Gift purpose | I9: Paid
A10: 45917 | B10: =IFERROR(VLOOKUP(C10,'Employees List'!$B$1:$G$999,4,0),"") -> REVATHI.S | C10: PR 08 | D10: September | E10: 3000 | F10: 3000 | G10: 3000 | H10: Loan EMI | I10: Paid
A11: 45922 | B11: =IFERROR(VLOOKUP(C11,'Employees List'!$B$1:$G$999,4,0),"") -> SANJAY BAGARTTI.K | C11: PR 05 | D11: September | E11: 5000 | F11: 5000 | G11: 5000 | H11: EMI For Loan | I11: Paid
A12: 45929 | B12: =IFERROR(VLOOKUP(C12,'Employees List'!$B$1:$G$999,4,0),"") -> RUPESH KISAN | C12: PR 04 | D12: September | E12: 1000 | H12: Personal | I12: Not Paid
A13: 45929 | B13: =IFERROR(VLOOKUP(C13,'Employees List'!$B$1:$G$999,4,0),"") -> GANESH | C13: PR 02 | D13: September | E13: 500 | G13: 2000 | H13: Personal | I13: Not Paid
A14: 45940 | B14: =IFERROR(VLOOKUP(C14,'Employees List'!$B$1:$G$999,4,0),"") -> REVATHI.S | C14: PR 08
A15: 45953 | B15: =IFERROR(VLOOKUP(C15,'Employees List'!$B$1:$G$999,4,0),"") -> LIPAN | C15: PR 21 | D15: October | E15: 5000 | F15: 5000 | H15: Personal | I15: Paid
A16: 45965 | B16: =IFERROR(VLOOKUP(C16,'Employees List'!$B$1:$G$999,4,0),"") -> REVATHI.S | C16: PR 08 | D16: October | E16: 500 | F16: 500 | G16: 500 | H16: Hospital | I16: Paid
A17: 45980 | B17: =IFERROR(VLOOKUP(C17,'Employees List'!$B$1:$G$999,4,0),"") -> REVATHI.S | C17: PR 08 | D17: November | E17: 3000 | F17: 3000 | G17: 1500 | H17: Loan | I17: Paid
A18: 45990 | B18: =IFERROR(VLOOKUP(C18,'Employees List'!$B$1:$G$999,4,0),"") -> GANESH | C18: PR 02 | D18: November | E18: 800 | F18: 800 | G18: 1800 | H18: Personal | I18: Paid
A19: 45995 | B19: =IFERROR(VLOOKUP(C19,'Employees List'!$B$1:$G$999,4,0),"") -> NILAMANI KISAN.B | C19: PR 24 | D19: December | E19: 3000 | F19: 3000 | H19: SBI AC - Food | I19: Paid
A20: 46012 | B20: =IFERROR(VLOOKUP(C20,'Employees List'!$B$1:$G$999,4,0),"") -> SANJAY BAGARTTI.K | C20: PR 05 | D20: December | E20: 5000 | F20: 5000 | I20: Paid
A21: 46014 | B21: =IFERROR(VLOOKUP(C21,'Employees List'!$B$1:$G$999,4,0),"") -> REVATHI.S | C21: PR 08 | D21: December | E21: 500 | F21: 500 | I21: Paid
A22: 46053 | B22: =IFERROR(VLOOKUP(C22,'Employees List'!$B$1:$G$999,4,0),"") -> GANESH | C22: PR 02 | D22: December | E22: 500 | F22: 500 | G22: 2500 | H22: Personal | I22: Request Apply
B23: =IFERROR(VLOOKUP(C23,'Employees List'!$B$1:$G$999,4,0),"") -> NILAMANI KISAN.B | C23: PR 24 | D23: December | E23: 2000 | F23: 2000 | H23: FOOD | I23: Request Apply
B24: =IFERROR(VLOOKUP(C24,'Employees List'!$B$1:$G$999,4,0),"") -> ADHIKARI BALIA.A | C24: PR 03 | D24: January | E24: 2000 | F24: 2000 | G24: 2000 | I24: Paid
B25: =IFERROR(VLOOKUP(C25,'Employees List'!$B$1:$G$999,4,0),"") -> ADHIKARI BALIA.A | C25: PR 03 | D25: January | E25: 4000 | F25: 4000 | G25: 4000
B26: =IFERROR(VLOOKUP(C26,'Employees List'!$B$1:$G$999,4,0),"") -> PARSHU BAGH | C26: PR 27 | D26: January | E26: 2000 | F26: 2000 | G26: 2000 | I26: Paid
A27: 46032 | B27: =IFERROR(VLOOKUP(C27,'Employees List'!$B$1:$G$999,4,0),"") -> REVATHI.S | C27: PR 08 | D27: January | G27: 1000 | I27: Received
A28: 46056 | B28: =IFERROR(VLOOKUP(C28,'Employees List'!$B$1:$G$999,4,0),"") -> GANESH | C28: PR 02 | D28: February | E28: 200 | F28: 200 | G28: 10000
A29: 46074 | B29: =IFERROR(VLOOKUP(C29,'Employees List'!$B$1:$G$999,4,0),"") -> PARSHU BAGH | C29: PR 27 | D29: February | E29: 4000 | F29: 4000 | H29: Going To Native | I29: Paid
A30: 46083 | B30: =IFERROR(VLOOKUP(C30,'Employees List'!$B$1:$G$999,4,0),"") -> REVATHI.S | C30: PR 08 | D30: March | E30: 300 | F30: 300 | I30: Paid
A31: 46084 | B31: =IFERROR(VLOOKUP(C31,'Employees List'!$B$1:$G$999,4,0),"") -> ADHIKARI BALIA.A | C31: PR 03 | D31: March | E31: 2000 | H31: Food | I31: Paid
B32: =IFERROR(VLOOKUP(C32,'Employees List'!$B$1:$G$999,4,0),"")
B33: =IFERROR(VLOOKUP(C33,'Employees List'!$B$1:$G$999,4,0),"")
B34: =IFERROR(VLOOKUP(C34,'Employees List'!$B$1:$G$999,4,0),"")
B35: =IFERROR(VLOOKUP(C35,'Employees List'!$B$1:$G$999,4,0),"")
B36: =IFERROR(VLOOKUP(C36,'Employees List'!$B$1:$G$999,4,0),"")
B37: =IFERROR(VLOOKUP(C37,'Employees List'!$B$1:$G$999,4,0),"")
B38: =IFERROR(VLOOKUP(C38,'Employees List'!$B$1:$G$999,4,0),"")
B39: =IFERROR(VLOOKUP(C39,'Employees List'!$B$1:$G$999,4,0),"")
B40: =IFERROR(VLOOKUP(C40,'Employees List'!$B$1:$G$999,4,0),"")
B41: =IFERROR(VLOOKUP(C41,'Employees List'!$B$1:$G$999,4,0),"")
B42: =IFERROR(VLOOKUP(C42,'Employees List'!$B$1:$G$999,4,0),"")
B43: =IFERROR(VLOOKUP(C43,'Employees List'!$B$1:$G$999,4,0),"")
... B1001: =IFERROR(VLOOKUP(C1001,'Employees List'!$B$1:$G$999,4,0),"")

Sheet Advance Report
A2: NAME | B2: GANESH | K2: =IF(B2="All","","and B = '"&B2&"'") -> and B = 'GANESH'
A3: MONTH | B3: All | K3: =IF(B3="All","","and C = '"&B3&"'")
A4: BALANCE | B4: =F1000-G1000 -> 21200 | K4: =CONCATENATE("select * where 1=1",K2,K3) -> select * where 1=1and B = 'GANESH'
A7: =IFERROR(__xludf.DUMMYFUNCTION("QUERY('Advance Sheet'!A1:I1000,K4)"),"Date") -> Date | B7: =IFERROR(__xludf.DUMMYFUNCTION("""COMPUTED_VALUE"""),"Name") -> Name | C7: =IFERROR(__xludf.DUMMYFUNCTION("""COMPUTED_VALUE"""),"Emp id") -> Emp id | D7: =IFERROR(__xludf.DUMMYFUNCTION("""COMPUTED_VALUE"""),"Month") -> Month | E7: =IFERROR(__xludf.DUMMYFUNCTION("""COMPUTED_VALUE"""),"Advance Requested") -> Advance Requested | F7: =IFERROR(__xludf.DUMMYFUNCTION("""COMPUTED_VALUE"""),"Advance Provided") -> Advance Provided | G7: =IFERROR(__xludf.DUMMYFUNCTION("""COMPUTED_VALUE"""),"Advance Deducted") -> Advance Deducted | H7: =IFERROR(__xludf.DUMMYFUNCTION("""COMPUTED_VALUE"""),"Reason") -> Reason | I7: =IFERROR(__xludf.DUMMYFUNCTION("""COMPUTED_VALUE"""),"Status") -> Status
A8: =IFERROR(__xludf.DUMMYFUNCTION("""COMPUTED_VALUE"""),45889.0) -> 45889 | B8: =IFERROR(__xludf.DUMMYFUNCTION("""COMPUTED_VALUE"""),"GANESH") -> GANESH | C8: =IFERROR(__xludf.DUMMYFUNCTION("""COMPUTED_VALUE"""),"PR 02") -> PR 02 | D8: =IFERROR(__xludf.DUMMYFUNCTION("""COMPUTED_VALUE"""),"August") -> August | F8: =IFERROR(__xludf.DUMMYFUNCTION("""COMPUTED_VALUE"""),40500.0) -> 40500 | H8: =IFERROR(__xludf.DUMMYFUNCTION("""COMPUTED_VALUE"""),"Opening Balance") -> Opening Balance | I8: =IFERROR(__xludf.DUMMYFUNCTION("""COMPUTED_VALUE"""),"Paid") -> Paid
A9: =IFERROR(__xludf.DUMMYFUNCTION("""COMPUTED_VALUE"""),45904.0) -> 45904 | B9: =IFERROR(__xludf.DUMMYFUNCTION("""COMPUTED_VALUE"""),"GANESH") -> GANESH | C9: =IFERROR(__xludf.DUMMYFUNCTION("""COMPUTED_VALUE"""),"PR 02") -> PR 02 | D9: =IFERROR(__xludf.DUMMYFUNCTION("""COMPUTED_VALUE"""),"September") -> September | E9: =IFERROR(__xludf.DUMMYFUNCTION("""COMPUTED_VALUE"""),500.0) -> 500 | F9: =IFERROR(__xludf.DUMMYFUNCTION("""COMPUTED_VALUE"""),500.0) -> 500 | G9: =IFERROR(__xludf.DUMMYFUNCTION("""COMPUTED_VALUE"""),5000.0) -> 5000 | H9: =IFERROR(__xludf.DUMMYFUNCTION("""COMPUTED_VALUE"""),"Gift purpose") -> Gift purpose | I9: =IFERROR(__xludf.DUMMYFUNCTION("""COMPUTED_VALUE"""),"Paid") -> Paid
A10: =IFERROR(__xludf.DUMMYFUNCTION("""COMPUTED_VALUE"""),45929.0) -> 45929 | B10: =IFERROR(__xludf.DUMMYFUNCTION("""COMPUTED_VALUE"""),"GANESH") -> GANESH | C10: =IFERROR(__xludf.DUMMYFUNCTION("""COMPUTED_VALUE"""),"PR 02") -> PR 02 | D10: =IFERROR(__xludf.DUMMYFUNCTION("""COMPUTED_VALUE"""),"September") -> September | E10: =IFERROR(__xludf.DUMMYFUNCTION("""COMPUTED_VALUE"""),500.0) -> 500 | G10: =IFERROR(__xludf.DUMMYFUNCTION("""COMPUTED_VALUE"""),2000.0) -> 2000 | H10: =IFERROR(__xludf.DUMMYFUNCTION("""COMPUTED_VALUE"""),"Personal") -> Personal | I10: =IFERROR(__xludf.DUMMYFUNCTION("""COMPUTED_VALUE"""),"Not Paid") -> Not Paid
A11: =IFERROR(__xludf.DUMMYFUNCTION("""COMPUTED_VALUE"""),45990.0) -> 45990 | B11: =IFERROR(__xludf.DUMMYFUNCTION("""COMPUTED_VALUE"""),"GANESH") -> GANESH | C11: =IFERROR(__xludf.DUMMYFUNCTION("""COMPUTED_VALUE"""),"PR 02") -> PR 02 | D11: =IFERROR(__xludf.DUMMYFUNCTION("""COMPUTED_VALUE"""),"November") -> November | E11: =IFERROR(__xludf.DUMMYFUNCTION("""COMPUTED_VALUE"""),800.0) -> 800 | F11: =IFERROR(__xludf.DUMMYFUNCTION("""COMPUTED_VALUE"""),800.0) -> 800 | G11: =IFERROR(__xludf.DUMMYFUNCTION("""COMPUTED_VALUE"""),1800.0) -> 1800 | H11: =IFERROR(__xludf.DUMMYFUNCTION("""COMPUTED_VALUE"""),"Personal") -> Personal | I11: =IFERROR(__xludf.DUMMYFUNCTION("""COMPUTED_VALUE"""),"Paid") -> Paid
A12: =IFERROR(__xludf.DUMMYFUNCTION("""COMPUTED_VALUE"""),46053.0) -> 46053 | B12: =IFERROR(__xludf.DUMMYFUNCTION("""COMPUTED_VALUE"""),"GANESH") -> GANESH | C12: =IFERROR(__xludf.DUMMYFUNCTION("""COMPUTED_VALUE"""),"PR 02") -> PR 02 | D12: =IFERROR(__xludf.DUMMYFUNCTION("""COMPUTED_VALUE"""),"December") -> December | E12: =IFERROR(__xludf.DUMMYFUNCTION("""COMPUTED_VALUE"""),500.0) -> 500 | F12: =IFERROR(__xludf.DUMMYFUNCTION("""COMPUTED_VALUE"""),500.0) -> 500 | G12: =IFERROR(__xludf.DUMMYFUNCTION("""COMPUTED_VALUE"""),2500.0) -> 2500 | H12: =IFERROR(__xludf.DUMMYFUNCTION("""COMPUTED_VALUE"""),"Personal") -> Personal | I12: =IFERROR(__xludf.DUMMYFUNCTION("""COMPUTED_VALUE"""),"Request Apply") -> Request Apply
A13: =IFERROR(__xludf.DUMMYFUNCTION("""COMPUTED_VALUE"""),46056.0) -> 46056 | B13: =IFERROR(__xludf.DUMMYFUNCTION("""COMPUTED_VALUE"""),"GANESH") -> GANESH | C13: =IFERROR(__xludf.DUMMYFUNCTION("""COMPUTED_VALUE"""),"PR 02") -> PR 02 | D13: =IFERROR(__xludf.DUMMYFUNCTION("""COMPUTED_VALUE"""),"February") -> February | E13: =IFERROR(__xludf.DUMMYFUNCTION("""COMPUTED_VALUE"""),200.0) -> 200 | F13: =IFERROR(__xludf.DUMMYFUNCTION("""COMPUTED_VALUE"""),200.0) -> 200 | G13: =IFERROR(__xludf.DUMMYFUNCTION("""COMPUTED_VALUE"""),10000.0) -> 10000
F1000: =SUM(F8:F999) -> 42500 | G1000: =SUM(G8:G999) -> 21300

Sheet Salary Calculation
A1: Salary Slip No | B1: Month | C1: Employee Code | D1: No of Days Name | E1: No of OT Name | F1: Name | G1: SALARY | H1: Account Number | I1: Total Wages 25-26 | J1: Basic Pay | K1: HRA | L1: No Of Days In a Month | M1: No Of Days Present | N1: OT Hours | O1: Bonus | P1: Advance | Q1: Gross Wages | R1: OT Amount | S1: Netpay | T1: ESI | U1: Total Salary
A2: CPIEMP001 | B2: April | C2: AC 01 | D2: =B2&F2 -> AprilBHUVANESHWARAN.V | E2: =D2&$N$1 -> AprilBHUVANESHWARAN.VOT Hours | F2: =IFERROR(VLOOKUP(C2,'Employees List'!$B$1:$I$999,4,0),"") -> BHUVANESHWARAN.V | G2: =S2 -> 66900 | H2: =IFERROR(VLOOKUP(C2,'Employees List'!$B$2:$I$991,7,0),"") -> 500101011548924 | I2: =IFERROR(VLOOKUP(F2,'Employees List'!$E$1:$AE$991,6,0),"") -> 66000 | J2: =I2*70% -> 46200 | K2: =I2*30% -> 19800 | L2: =IFERROR(VLOOKUP(B2,'Employees List'!$A$2:$K$991,11,0),"") -> 30 | M2: =IFERROR(VLOOKUP(D2,'Daily Attendance 25-26'!$A$4:BP999,5,0),"") -> 30 | N2: =IFERROR(VLOOKUP(E2,'Daily Attendance 25-26'!$A$1:$BO$1741,5,0),"") -> 0 | O2: 900 | Q2: =I2/L2*M2 -> 66000 | R2: =I2/L2/8*1.5*N2 -> 0 | S2: =Q2+R2-P2+O2 -> 66900 | T2: 0 | U2: =Q2+R2+O2 -> 66900
A3: CPIEMP002 | B3: April | C3: AC 02 | D3: =B3&F3 -> AprilTHIRIPURA SUNDARI.R | E3: =D3&$N$1 -> AprilTHIRIPURA SUNDARI.ROT Hours | F3: =IFERROR(VLOOKUP(C3,'Employees List'!$B$1:$I$999,4,0),"") -> THIRIPURA SUNDARI.R | G3: =S3-T3 -> 23075.625 | H3: =IFERROR(VLOOKUP(C3,'Employees List'!$B$2:$I$991,7,0),"") -> 8131010000016977 | I3: =IFERROR(VLOOKUP(F3,'Employees List'!$E$1:$AE$991,6,0),"") -> 21000 | J3: =I3*70% -> 14700 | K3: =I3*30% -> 6300 | L3: =IFERROR(VLOOKUP(B3,'Employees List'!$A$2:$K$991,11,0),"") -> 30 | M3: =IFERROR(VLOOKUP(D3,'Daily Attendance 25-26'!$A$4:BP999,5,0),"") -> 30 | N3: =IFERROR(VLOOKUP(E3,'Daily Attendance 25-26'!$A$1:$BO$1741,5,0),"") -> 8 | O3: 1200 | Q3: =I3/L3*M3 -> 21000 | R3: =I3/L3/8*1.5*N3 -> 1050 | S3: =Q3+R3-P3+O3 -> 23250 | T3: =U3*0.75% -> 174.375 | U3: =Q3+R3+O3 -> 23250
A4: CPIEMP003 | B4: April | C4: PR 02 | D4: =B4&F4 -> AprilGANESH | E4: =D4&$N$1 -> AprilGANESHOT Hours | F4: =IFERROR(VLOOKUP(C4,'Employees List'!$B$1:$I$999,4,0),"") -> GANESH | G4: =S4-T4 -> 13436.214 | H4: =IFERROR(VLOOKUP(C4,'Employees List'!$B$2:$I$991,7,0),"") -> 8811010012054879 | I4: =IFERROR(VLOOKUP(F4,'Employees List'!$E$1:$AE$991,6,0),"") -> 18500 | J4: =I4*70% -> 12950 | K4: =I4*30% -> 5550 | L4: =IFERROR(VLOOKUP(B4,'Employees List'!$A$2:$K$991,11,0),"") -> 30 | M4: =IFERROR(VLOOKUP(D4,'Daily Attendance 25-26'!$A$4:BP999,5,0),"") -> 22 | N4: =IFERROR(VLOOKUP(E4,'Daily Attendance 25-26'!$A$1:$BO$1741,5,0),"") -> 22 | O4: 450 | P4: 3000 | Q4: =I4/L4*M4 -> 13566.667 | R4: =I4/L4/8*1.5*N4 -> 2543.75 | S4: =Q4+R4-P4+O4 -> 13560.417 | T4: =U4*0.75% -> 124.20312 | U4: =Q4+R4+O4 -> 16560.417
A5: CPIEMP004 | B5: April | C5: DR 01 | D5: =B5&F5 -> AprilILAMATHIVANAN.S | E5: =D5&$N$1 -> AprilILAMATHIVANAN.SOT Hours | F5: =IFERROR(VLOOKUP(C5,'Employees List'!$B$1:$I$999,4,0),"") -> ILAMATHIVANAN.S | G5: =S5-T5 -> 16766.766 | H5: =IFERROR(VLOOKUP(C5,'Employees List'!$B$2:$I$991,7,0),"") -> 8131010000016986 | I5: =IFERROR(VLOOKUP(F5,'Employees List'!$E$1:$AE$991,6,0),"") -> 21000 | J5: =I5*70% -> 14700 | K5: =I5*30% -> 6300 | L5: =IFERROR(VLOOKUP(B5,'Employees List'!$A$2:$K$991,11,0),"") -> 30 | M5: =IFERROR(VLOOKUP(D5,'Daily Attendance 25-26'!$A$4:BP999,5,0),"") -> 23 | N5: =IFERROR(VLOOKUP(E5,'Daily Attendance 25-26'!$A$1:$BO$1741,5,0),"") -> 41 | O5: 450 | P5: 5000 | Q5: =I5/L5*M5 -> 16100 | R5: =I5/L5/8*1.5*N5 -> 5381.25 | S5: =Q5+R5-P5+O5 -> 16931.25 | T5: =U5*0.75% -> 164.48438 | U5: =Q5+R5+O5 -> 21931.25
A6: CPIEMP005 | B6: April | C6: PR 07 | D6: =B6&F6 -> AprilAMMU.S | E6: =D6&$N$1 -> AprilAMMU.SOT Hours | F6: =IFERROR(VLOOKUP(C6,'Employees List'!$B$1:$I$999,4,0),"") -> AMMU.S | G6: =S6-T6 -> 12030.961 | H6: =IFERROR(VLOOKUP(C6,'Employees List'!$B$2:$I$991,7,0),"") -> 65801000040238 | I6: =IFERROR(VLOOKUP(F6,'Employees List'!$E$1:$AE$991,6,0),"") -> 10500 | J6: =I6*70% -> 7350 | K6: =I6*30% -> 3150 | L6: =IFERROR(VLOOKUP(B6,'Employees List'!$A$2:$K$991,11,0),"") -> 30 | M6: =IFERROR(VLOOKUP(D6,'Daily Attendance 25-26'!$A$4:BP999,5,0),"") -> 30 | N6: =IFERROR(VLOOKUP(E6,'Daily Attendance 25-26'!$A$1:$BO$1741,5,0),"") -> 11 | O6: 900 | Q6: =I6/L6*M6 -> 10500 | R6: =I6/L6/8*1.5*N6 -> 721.875 | S6: =Q6+R6-P6+O6 -> 12121.875 | T6: =U6*0.75% -> 90.914062 | U6: =Q6+R6+O6 -> 12121.875
A7: CPIEMP006 | B7: April | C7: PR 08 | D7: =B7&F7 -> AprilREVATHI.S | E7: =D7&$N$1 -> AprilREVATHI.SOT Hours | F7: =IFERROR(VLOOKUP(C7,'Employees List'!$B$1:$I$999,4,0),"") -> REVATHI.S | G7: =S7-T7 -> 9606.6953 | H7: =IFERROR(VLOOKUP(C7,'Employees List'!$B$2:$I$991,7,0),"") -> 8131010000016995 | I7: =IFERROR(VLOOKUP(F7,'Employees List'!$E$1:$AE$991,6,0),"") -> 10500 | J7: =I7*70% -> 7350 | K7: =I7*30% -> 3150 | L7: =IFERROR(VLOOKUP(B7,'Employees List'!$A$2:$K$991,11,0),"") -> 30 | M7: =IFERROR(VLOOKUP(D7,'Daily Attendance 25-26'!$A$4:BP999,5,0),"") -> 29 | N7: =IFERROR(VLOOKUP(E7,'Daily Attendance 25-26'!$A$1:$BO$1741,5,0),"") -> 9 | O7: 450 | P7: 1500 | Q7: =I7/L7*M7 -> 10150 | R7: =I7/L7/8*1.5*N7 -> 590.625 | S7: =Q7+R7-P7+O7 -> 9690.625 | T7: =U7*0.75% -> 83.929688 | U7: =Q7+R7+O7 -> 11190.625
A8: CPIEMP007 | B8: April | C8: AC 03 | D8: =B8&F8 -> AprilLEELAVATHI.M | E8: =D8&$N$1 -> AprilLEELAVATHI.MOT Hours | F8: =IFERROR(VLOOKUP(C8,'Employees List'!$B$1:$I$999,4,0),"") -> LEELAVATHI.M | G8: =S8-T8 -> 15048.781 | H8: =IFERROR(VLOOKUP(C8,'Employees List'!$B$2:$I$991,7,0),"") -> 8387010000017745 | I8: =IFERROR(VLOOKUP(F8,'Employees List'!$E$1:$AE$991,6,0),"") -> 14000 | J8: =I8*70% -> 9800 | K8: =I8*30% -> 4200 | L8: =IFERROR(VLOOKUP(B8,'Employees List'!$A$2:$K$991,11,0),"") -> 30 | M8: =IFERROR(VLOOKUP(D8,'Daily Attendance 25-26'!$A$4:BP999,5,0),"") -> 30 | N8: =IFERROR(VLOOKUP(E8,'Daily Attendance 25-26'!$A$1:$BO$1741,5,0),"") -> 3 | O8: 900 | Q8: =I8/L8*M8 -> 14000 | R8: =I8/L8/8*1.5*N8 -> 262.5 | S8: =Q8+R8-P8+O8 -> 15162.5 | T8: =U8*0.75% -> 113.71875 | U8: =Q8+R8+O8 -> 15162.5
A9: CPIEMP008 | B9: April | C9: PR 27 | D9: =B9&F9 -> AprilPARSHU BAGH | E9: =D9&$N$1 -> AprilPARSHU BAGHOT Hours | F9: =IFERROR(VLOOKUP(C9,'Employees List'!$B$1:$I$999,4,0),"") -> PARSHU BAGH | G9: =S9-T9 -> 4032.0312 | H9: =IFERROR(VLOOKUP(C9,'Employees List'!$B$2:$I$991,7,0),"") -> 40653547928 | I9: =IFERROR(VLOOKUP(F9,'Employees List'!$E$1:$AE$991,6,0),"") -> 13000 | J9: =I9*70% -> 9100 | K9: =I9*30% -> 3900 | L9: =IFERROR(VLOOKUP(B9,'Employees List'!$A$2:$K$991,11,0),"") -> 30 | M9: =IFERROR(VLOOKUP(D9,'Daily Attendance 25-26'!$A$4:BP999,5,0),"") -> 9 | N9: =IFERROR(VLOOKUP(E9,'Daily Attendance 25-26'!$A$1:$BO$1741,5,0),"") -> 2 | Q9: =I9/L9*M9 -> 3900 | R9: =I9/L9/8*1.5*N9 -> 162.5 | S9: =Q9+R9-P9+O9 -> 4062.5 | T9: =U9*0.75% -> 30.46875 | U9: =Q9+R9+O9 -> 4062.5
A10: CPIEMP009 | B10: April | C10: PR 12 | D10: =B10&F10 -> AprilPINU | E10: =D10&$N$1 -> AprilPINU OT Hours | F10: =IFERROR(VLOOKUP(C10,'Employees List'!$B$1:$I$999,4,0),"") -> PINU | G10: =S10-T10 -> 4298.7656 | H10: =IFERROR(VLOOKUP(C10,'Employees List'!$B$2:$I$991,7,0),"") -> 8131010000018814 | I10: =IFERROR(VLOOKUP(F10,'Employees List'!$E$1:$AE$991,6,0),"") -> 11000 | J10: =I10*70% -> 7700 | K10: =I10*30% -> 3300 | L10: =IFERROR(VLOOKUP(B10,'Employees List'!$A$2:$K$991,11,0),"") -> 30 | M10: =IFERROR(VLOOKUP(D10,'Daily Attendance 25-26'!$A$4:BP999,5,0),"") -> 9 | N10: =IFERROR(VLOOKUP(E10,'Daily Attendance 25-26'!$A$1:$BO$1741,5,0),"") -> 15 | Q10: =I10/L10*M10 -> 3300 | R10: =I10/L10/8*1.5*N10 -> 1031.25 | S10: =Q10+R10-P10+O10 -> 4331.25 | T10: =U10*0.75% -> 32.484375 | U10: =Q10+R10+O10 -> 4331.25
A11: CPIEMP010 | B11: April | C11: PR 05 | D11: =B11&F11 -> AprilSANJAY BAGARTTI.K | E11: =D11&$N$1 -> AprilSANJAY BAGARTTI.KOT Hours | F11: =IFERROR(VLOOKUP(C11,'Employees List'!$B$1:$I$999,4,0),"") -> SANJAY BAGARTTI.K | G11: =S11-T11 -> 20811.484 | H11: =IFERROR(VLOOKUP(C11,'Employees List'!$B$2:$I$991,7,0),"") -> 8131010000021225 | I11: =IFERROR(VLOOKUP(F11,'Employees List'!$E$1:$AE$991,6,0),"") -> 13000 | J11: =I11*70% -> 9100 | K11: =I11*30% -> 3900 | L11: =IFERROR(VLOOKUP(B11,'Employees List'!$A$2:$K$991,11,0),"") -> 30 | M11: =IFERROR(VLOOKUP(D11,'Daily Attendance 25-26'!$A$4:BP999,5,0),"") -> 30 | N11: =IFERROR(VLOOKUP(E11,'Daily Attendance 25-26'!$A$1:$BO$1741,5,0),"") -> 87 | O11: 900 | Q11: =I11/L11*M11 -> 13000 | R11: =I11/L11/8*1.5*N11 -> 7068.75 | S11: =Q11+R11-P11+O11 -> 20968.75 | T11: =U11*0.75% -> 157.26562 | U11: =Q11+R11+O11 -> 20968.75
A12: CPIEMP011 | B12: April | C12: PR 03 | D12: =B12&F12 -> AprilADHIKARI BALIA.A | E12: =D12&$N$1 -> AprilADHIKARI BALIA.AOT Hours | F12: =IFERROR(VLOOKUP(C12,'Employees List'!$B$1:$I$999,4,0),"") -> ADHIKARI BALIA.A | G12: =S12-T12 -> 1542.6146 | H12: =IFERROR(VLOOKUP(C12,'Employees List'!$B$2:$I$991,7,0),"") -> 8131010000018948 | I12: =IFERROR(VLOOKUP(F12,'Employees List'!$E$1:$AE$991,6,0),"") -> 13000 | J12: =I12*70% -> 9100 | K12: =I12*30% -> 3900 | L12: =IFERROR(VLOOKUP(B12,'Employees List'!$A$2:$K$991,11,0),"") -> 30 | M12: =IFERROR(VLOOKUP(D12,'Daily Attendance 25-26'!$A$4:BP999,5,0),"") -> 10 | N12: =IFERROR(VLOOKUP(E12,'Daily Attendance 25-26'!$A$1:$BO$1741,5,0),"") -> 34 | P12: 5500 | Q12: =I12/L12*M12 -> 4333.3333 | R12: =I12/L12/8*1.5*N12 -> 2762.5 | S12: =Q12+R12-P12+O12 -> 1595.8333 | T12: =U12*0.75% -> 53.21875 | U12: =Q12+R12+O12 -> 7095.8333
A13: CPIEMP012 | B13: April | C13: PR 04 | D13: =B13&F13 -> AprilRUPESH KISAN | E13: =D13&$N$1 -> AprilRUPESH KISANOT Hours | F13: =IFERROR(VLOOKUP(C13,'Employees List'!$B$1:$I$999,4,0),"") -> RUPESH KISAN | G13: =S13-T13 -> 4236.2083 | H13: =IFERROR(VLOOKUP(C13,'Employees List'!$B$2:$I$991,7,0),"") -> 411002010024591 | I13: =IFERROR(VLOOKUP(F13,'Employees List'!$E$1:$AE$991,6,0),"") -> 13000 | J13: =I13*70% -> 9100 | K13: =I13*30% -> 3900 | L13: =IFERROR(VLOOKUP(B13,'Employees List'!$A$2:$K$991,11,0),"") -> 30 | M13: =IFERROR(VLOOKUP(D13,'Daily Attendance 25-26'!$A$4:BP999,5,0),"") -> 10 | N13: =IFERROR(VLOOKUP(E13,'Daily Attendance 25-26'!$A$1:$BO$1741,5,0),"") -> 24 | P13: 2000 | Q13: =I13/L13*M13 -> 4333.3333 | R13: =I13/L13/8*1.5*N13 -> 1950 | S13: =Q13+R13-P13+O13 -> 4283.3333 | T13: =U13*0.75% -> 47.125 | U13: =Q13+R13+O13 -> 6283.3333
A14: CPIEMP013 | B14: April | C14: PR 21 | D14: =B14&F14 -> AprilLIPAN | E14: =D14&$N$1 -> AprilLIPANOT Hours | F14: =IFERROR(VLOOKUP(C14,'Employees List'!$B$1:$I$999,4,0),"") -> LIPAN | G14: =S14-T14 -> 365.17708 | H14: =IFERROR(VLOOKUP(C14,'Employees List'!$B$2:$I$991,7,0),"") -> 8131010000018957 | I14: =IFERROR(VLOOKUP(F14,'Employees List'!$E$1:$AE$991,6,0),"") -> 13000 | J14: =I14*70% -> 9100 | K14: =I14*30% -> 3900 | L14: =IFERROR(VLOOKUP(B14,'Employees List'!$A$2:$K$991,11,0),"") -> 30 | M14: =IFERROR(VLOOKUP(D14,'Daily Attendance 25-26'!$A$4:BP999,5,0),"") -> 10 | N14: =IFERROR(VLOOKUP(E14,'Daily Attendance 25-26'!$A$1:$BO$1741,5,0),"") -> 38 | P14: 7000 | Q14: =I14/L14*M14 -> 4333.3333 | R14: =I14/L14/8*1.5*N14 -> 3087.5 | S14: =Q14+R14-P14+O14 -> 420.83333 | T14: =U14*0.75% -> 55.65625 | U14: =Q14+R14+O14 -> 7420.8333
A15: CPIEMP014 | B15: April | C15: PR 24 | D15: =B15&F15 -> AprilNILAMANI KISAN.B | E15: =D15&$N$1 -> AprilNILAMANI KISAN.BOT Hours | F15: =IFERROR(VLOOKUP(C15,'Employees List'!$B$1:$I$999,4,0),"") -> NILAMANI KISAN.B | G15: =S15-T15 -> 14143.125 | H15: =IFERROR(VLOOKUP(C15,'Employees List'!$B$2:$I$991,7,0),"") -> 38254473147 | I15: =IFERROR(VLOOKUP(F15,'Employees List'!$E$1:$AE$991,6,0),"") -> 12000 | J15: =I15*70% -> 8400 | K15: =I15*30% -> 3600 | L15: =IFERROR(VLOOKUP(B15,'Employees List'!$A$2:$K$991,11,0),"") -> 30 | M15: =IFERROR(VLOOKUP(D15,'Daily Attendance 25-26'!$A$4:BP999,5,0),"") -> 27 | N15: =IFERROR(VLOOKUP(E15,'Daily Attendance 25-26'!$A$1:$BO$1741,5,0),"") -> 40 | O15: 450 | Q15: =I15/L15*M15 -> 10800 | R15: =I15/L15/8*1.5*N15 -> 3000 | S15: =Q15+R15-P15+O15 -> 14250 | T15: =U15*0.75% -> 106.875 | U15: =Q15+R15+O15 -> 14250
A16: CPIEMP015 | B16: May | C16: AC 01 | D16: =B16&F16 -> MayBHUVANESHWARAN.V | E16: =D16&$N$1 -> MayBHUVANESHWARAN.VOT Hours | F16: =IFERROR(VLOOKUP(C16,'Employees List'!$B$1:$I$999,4,0),"") -> BHUVANESHWARAN.V | G16: =S16 -> 66900 | H16: =IFERROR(VLOOKUP(C16,'Employees List'!$B$2:$I$991,7,0),"") -> 500101011548924 | I16: =IFERROR(VLOOKUP(F16,'Employees List'!$E$1:$AE$991,6,0),"") -> 66000 | J16: =I16*70% -> 46200 | K16: =I16*30% -> 19800 | L16: =IFERROR(VLOOKUP(B16,'Employees List'!$A$2:$K$991,11,0),"") -> 31 | M16: =IFERROR(VLOOKUP(D16,'Daily Attendance 25-26'!$A$4:BP999,5,0),"") -> 31 | N16: =IFERROR(VLOOKUP(E16,'Daily Attendance 25-26'!$A$1:$BO$1741,5,0),"") -> 0 | O16: 900 | Q16: =I16/L16*M16 -> 66000 | R16: =I16/L16/8*1.5*N16 -> 0 | S16: =Q16+R16-P16+O16 -> 66900 | T16: =U16*0.75% -> 501.75 | U16: =Q16+R16+O16 -> 66900
A17: CPIEMP016 | B17: May | C17: AC 02 | D17: =B17&F17 -> MayTHIRIPURA SUNDARI.R | E17: =D17&$N$1 -> MayTHIRIPURA SUNDARI.ROT Hours | F17: =IFERROR(VLOOKUP(C17,'Employees List'!$B$1:$I$999,4,0),"") -> THIRIPURA SUNDARI.R | G17: =S17-T17 -> 23294.135 | H17: =IFERROR(VLOOKUP(C17,'Employees List'!$B$2:$I$991,7,0),"") -> 8131010000016977 | I17: =IFERROR(VLOOKUP(F17,'Employees List'!$E$1:$AE$991,6,0),"") -> 21000 | J17: =I17*70% -> 14700 | K17: =I17*30% -> 6300 | L17: =IFERROR(VLOOKUP(B17,'Employees List'!$A$2:$K$991,11,0),"") -> 31 | M17: =IFERROR(VLOOKUP(D17,'Daily Attendance 25-26'!$A$4:BP999,5,0),"") -> 31 | N17: =IFERROR(VLOOKUP(E17,'Daily Attendance 25-26'!$A$1:$BO$1741,5,0),"") -> 10 | O17: 1200 | Q17: =I17/L17*M17 -> 21000 | R17: =I17/L17/8*1.5*N17 -> 1270.1613 | S17: =Q17+R17-P17+O17 -> 23470.161 | T17: =U17*0.75% -> 176.02621 | U17: =Q17+R17+O17 -> 23470.161
A18: CPIEMP017 | B18: May | C18: PR 02 | D18: =B18&F18 -> MayGANESH | E18: =D18&$N$1 -> MayGANESHOT Hours | F18: =IFERROR(VLOOKUP(C18,'Employees List'!$B$1:$I$999,4,0),"") -> GANESH | G18: =S18-T18 -> 19955.453 | H18: =IFERROR(VLOOKUP(C18,'Employees List'!$B$2:$I$991,7,0),"") -> 8811010012054879 | I18: =IFERROR(VLOOKUP(F18,'Employees List'!$E$1:$AE$991,6,0),"") -> 18500 | J18: =I18*70% -> 12950 | K18: =I18*30% -> 5550 | L18: =IFERROR(VLOOKUP(B18,'Employees List'!$A$2:$K$991,11,0),"") -> 31 | M18: =IFERROR(VLOOKUP(D18,'Daily Attendance 25-26'!$A$4:BP999,5,0),"") -> 24.5 | N18: =IFERROR(VLOOKUP(E18,'Daily Attendance 25-26'!$A$1:$BO$1741,5,0),"") -> 45 | O18: 450 | Q18: =I18/L18*M18 -> 14620.968 | R18: =I18/L18/8*1.5*N18 -> 5035.2823 | S18: =Q18+R18-P18+O18 -> 20106.25 | T18: =U18*0.75% -> 150.79688 | U18: =Q18+R18+O18 -> 20106.25
A19: CPIEMP018 | B19: May | C19: DR 01 | D19: =B19&F19 -> MayILAMATHIVANAN.S | E19: =D19&$N$1 -> MayILAMATHIVANAN.SOT Hours | F19: =IFERROR(VLOOKUP(C19,'Employees List'!$B$1:$I$999,4,0),"") -> ILAMATHIVANAN.S | G19: =S19-T19 -> 29189.105 | H19: =IFERROR(VLOOKUP(C19,'Employees List'!$B$2:$I$991,7,0),"") -> 8131010000016986 | I19: =IFERROR(VLOOKUP(F19,'Employees List'!$E$1:$AE$991,6,0),"") -> 21000 | J19: =I19*70% -> 14700 | K19: =I19*30% -> 6300 | L19: =IFERROR(VLOOKUP(B19,'Employees List'!$A$2:$K$991,11,0),"") -> 31 | M19: =IFERROR(VLOOKUP(D19,'Daily Attendance 25-26'!$A$4:BP999,5,0),"") -> 28.5 | N19: =IFERROR(VLOOKUP(E19,'Daily Attendance 25-26'!$A$1:$BO$1741,5,0),"") -> 76 | O19: 450 | Q19: =I19/L19*M19 -> 19306.452 | R19: =I19/L19/8*1.5*N19 -> 9653.2258 | S19: =Q19+R19-P19+O19 -> 29409.677 | T19: =U19*0.75% -> 220.57258 | U19: =Q19+R19+O19 -> 29409.677
A20: CPIEMP019 | B20: May | C20: PR 03 | D20: =B20&F20 -> MayADHIKARI BALIA.A | E20: =D20&$N$1 -> MayADHIKARI BALIA.AOT Hours | F20: =IFERROR(VLOOKUP(C20,'Employees List'!$B$1:$I$999,4,0),"") -> ADHIKARI BALIA.A | G20: =S20-T20 -> 19440.861 | H20: =IFERROR(VLOOKUP(C20,'Employees List'!$B$2:$I$991,7,0),"") -> 8131010000018948 | I20: =IFERROR(VLOOKUP(F20,'Employees List'!$E$1:$AE$991,6,0),"") -> 13000 | J20: =I20*70% -> 9100 | K20: =I20*30% -> 3900 | L20: =IFERROR(VLOOKUP(B20,'Employees List'!$A$2:$K$991,11,0),"") -> 31 | M20: =IFERROR(VLOOKUP(D20,'Daily Attendance 25-26'!$A$4:BP999,5,0),"") -> 31 | N20: =IFERROR(VLOOKUP(E20,'Daily Attendance 25-26'!$A$1:$BO$1741,5,0),"") -> 130 | O20: 900 | P20: 4500 | Q20: =I20/L20*M20 -> 13000 | R20: =I20/L20/8*1.5*N20 -> 10221.774 | S20: =Q20+R20-P20+O20 -> 19621.774 | T20: =U20*0.75% -> 180.91331 | U20: =Q20+R20+O20 -> 24121.774
A21: CPIEMP020 | B21: May | C21: PR 04 | D21: =B21&F21 -> MayRUPESH KISAN | E21: =D21&$N$1 -> MayRUPESH KISANOT Hours | F21: =IFERROR(VLOOKUP(C21,'Employees List'!$B$1:$I$999,4,0),"") -> RUPESH KISAN | G21: =S21-T21 -> 21018.9 | H21: =IFERROR(VLOOKUP(C21,'Employees List'!$B$2:$I$991,7,0),"") -> 411002010024591 | I21: =IFERROR(VLOOKUP(F21,'Employees List'!$E$1:$AE$991,6,0),"") -> 13000 | J21: =I21*70% -> 9100 | K21: =I21*30% -> 3900 | L21: =IFERROR(VLOOKUP(B21,'Employees List'!$A$2:$K$991,11,0),"") -> 31 | M21: =IFERROR(VLOOKUP(D21,'Daily Attendance 25-26'!$A$4:BP999,5,0),"") -> 31 | N21: =IFERROR(VLOOKUP(E21,'Daily Attendance 25-26'!$A$1:$BO$1741,5,0),"") -> 131 | O21: 900 | P21: 3000 | Q21: =I21/L21*M21 -> 13000 | R21: =I21/L21/8*1.5*N21 -> 10300.403 | S21: =Q21+R21-P21+O21 -> 21200.403 | T21: =U21*0.75% -> 181.50302 | U21: =Q21+R21+O21 -> 24200.403
A22: CPIEMP021 | B22: May | C22: PR 05 | D22: =B22&F22 -> MaySANJAY BAGARTTI.K | E22: =D22&$N$1 -> MaySANJAY BAGARTTI.KOT Hours | F22: =IFERROR(VLOOKUP(C22,'Employees List'!$B$1:$I$999,4,0),"") -> SANJAY BAGARTTI.K | G22: =S22-T22 -> 25501.647 | H22: =IFERROR(VLOOKUP(C22,'Employees List'!$B$2:$I$991,7,0),"") -> 8131010000021225 | I22: =IFERROR(VLOOKUP(F22,'Employees List'!$E$1:$AE$991,6,0),"") -> 13000 | J22: =I22*70% -> 9100 | K22: =I22*30% -> 3900 | L22: =IFERROR(VLOOKUP(B22,'Employees List'!$A$2:$K$991,11,0),"") -> 31 | M22: =IFERROR(VLOOKUP(D22,'Daily Attendance 25-26'!$A$4:BP999,5,0),"") -> 31 | N22: =IFERROR(VLOOKUP(E22,'Daily Attendance 25-26'!$A$1:$BO$1741,5,0),"") -> 150 | O22: 900 | Q22: =I22/L22*M22 -> 13000 | R22: =I22/L22/8*1.5*N22 -> 11794.355 | S22: =Q22+R22-P22+O22 -> 25694.355 | T22: =U22*0.75% -> 192.70766 | U22: =Q22+R22+O22 -> 25694.355
A23: CPIEMP022 | B23: May | C23: PR 21 | D23: =B23&F23 -> MayLIPAN | E23: =D23&$N$1 -> MayLIPANOT Hours | F23: =IFERROR(VLOOKUP(C23,'Employees List'!$B$1:$I$999,4,0),"") -> LIPAN | G23: =S23-T23 -> 20468.223 | H23: =IFERROR(VLOOKUP(C23,'Employees List'!$B$2:$I$991,7,0),"") -> 8131010000018957 | I23: =IFERROR(VLOOKUP(F23,'Employees List'!$E$1:$AE$991,6,0),"") -> 13000 | J23: =I23*70% -> 9100 | K23: =I23*30% -> 3900 | L23: =IFERROR(VLOOKUP(B23,'Employees List'!$A$2:$K$991,11,0),"") -> 31 | M23: =IFERROR(VLOOKUP(D23,'Daily Attendance 25-26'!$A$4:BP999,5,0),"") -> 30 | N23: =IFERROR(VLOOKUP(E23,'Daily Attendance 25-26'!$A$1:$BO$1741,5,0),"") -> 135 | O23: 450 | P23: 3000 | Q23: =I23/L23*M23 -> 12580.645 | R23: =I23/L23/8*1.5*N23 -> 10614.919 | S23: =Q23+R23-P23+O23 -> 20645.565 | T23: =U23*0.75% -> 177.34173 | U23: =Q23+R23+O23 -> 23645.565
A24: CPIEMP023 | B24: May | C24: PR 07 | D24: =B24&F24 -> MayAMMU.S | E24: =D24&$N$1 -> MayAMMU.SOT Hours | F24: =IFERROR(VLOOKUP(C24,'Employees List'!$B$1:$I$999,4,0),"") -> AMMU.S | G24: =S24-T24 -> 11603.245 | H24: =IFERROR(VLOOKUP(C24,'Employees List'!$B$2:$I$991,7,0),"") -> 65801000040238 | I24: =IFERROR(VLOOKUP(F24,'Employees List'!$E$1:$AE$991,6,0),"") -> 10500 | J24: =I24*70% -> 7350 | K24: =I24*30% -> 3150 | L24: =IFERROR(VLOOKUP(B24,'Employees List'!$A$2:$K$991,11,0),"") -> 31 | M24: =IFERROR(VLOOKUP(D24,'Daily Attendance 25-26'!$A$4:BP999,5,0),"") -> 27 | N24: =IFERROR(VLOOKUP(E24,'Daily Attendance 25-26'!$A$1:$BO$1741,5,0),"") -> 33 | O24: 450 | Q24: =I24/L24*M24 -> 9145.1613 | R24: =I24/L24/8*1.5*N24 -> 2095.7661 | S24: =Q24+R24-P24+O24 -> 11690.927 | T24: =U24*0.75% -> 87.681956 | U24: =Q24+R24+O24 -> 11690.927
A25: CPIEMP024 | B25: May | C25: PR 08 | D25: =B25&F25 -> MayREVATHI.S | E25: =D25&$N$1 -> MayREVATHI.SOT Hours | F25: =IFERROR(VLOOKUP(C25,'Employees List'!$B$1:$I$999,4,0),"") -> REVATHI.S | G25: =S25-T25 -> 11289.944 | H25: =IFERROR(VLOOKUP(C25,'Employees List'!$B$2:$I$991,7,0),"") -> 8131010000016995 | I25: =IFERROR(VLOOKUP(F25,'Employees List'!$E$1:$AE$991,6,0),"") -> 10500 | J25: =I25*70% -> 7350 | K25: =I25*30% -> 3150 | L25: =IFERROR(VLOOKUP(B25,'Employees List'!$A$2:$K$991,11,0),"") -> 31 | M25: =IFERROR(VLOOKUP(D25,'Daily Attendance 25-26'!$A$4:BP999,5,0),"") -> 30 | N25: =IFERROR(VLOOKUP(E25,'Daily Attendance 25-26'!$A$1:$BO$1741,5,0),"") -> 39 | O25: 450 | P25: 1700 | Q25: =I25/L25*M25 -> 10161.29 | R25: =I25/L25/8*1.5*N25 -> 2476.8145 | S25: =Q25+R25-P25+O25 -> 11388.105 | T25: =U25*0.75% -> 98.160786 | U25: =Q25+R25+O25 -> 13088.105
A26: CPIEMP025 | B26: May | C26: AC 03 | D26: =B26&F26 -> MayLEELAVATHI.M | E26: =D26&$N$1 -> MayLEELAVATHI.MOT Hours | F26: =IFERROR(VLOOKUP(C26,'Employees List'!$B$1:$I$999,4,0),"") -> LEELAVATHI.M | G26: =S26-T26 -> 13865.385 | H26: =IFERROR(VLOOKUP(C26,'Employees List'!$B$2:$I$991,7,0),"") -> 8387010000017745 | I26: =IFERROR(VLOOKUP(F26,'Employees List'!$E$1:$AE$991,6,0),"") -> 14000 | J26: =I26*70% -> 9800 | K26: =I26*30% -> 4200 | L26: =IFERROR(VLOOKUP(B26,'Employees List'!$A$2:$K$991,11,0),"") -> 31 | M26: =IFERROR(VLOOKUP(D26,'Daily Attendance 25-26'!$A$4:BP999,5,0),"") -> 29 | N26: =IFERROR(VLOOKUP(E26,'Daily Attendance 25-26'!$A$1:$BO$1741,5,0),"") -> 5 | O26: 450 | Q26: =I26/L26*M26 -> 13096.774 | R26: =I26/L26/8*1.5*N26 -> 423.3871 | S26: =Q26+R26-P26+O26 -> 13970.161 | T26: =U26*0.75% -> 104.77621 | U26: =Q26+R26+O26 -> 13970.161
A27: CPIEMP026 | B27: May | C27: PR 24 | D27: =B27&F27 -> MayNILAMANI KISAN.B | E27: =D27&$N$1 -> MayNILAMANI KISAN.BOT Hours | F27: =IFERROR(VLOOKUP(C27,'Employees List'!$B$1:$I$999,4,0),"") -> NILAMANI KISAN.B | G27: =S27-T27 -> 18863.903 | H27: =IFERROR(VLOOKUP(C27,'Employees List'!$B$2:$I$991,7,0),"") -> 38254473147 | I27: =IFERROR(VLOOKUP(F27,'Employees List'!$E$1:$AE$991,6,0),"") -> 12000 | J27: =I27*70% -> 8400 | K27: =I27*30% -> 3600 | L27: =IFERROR(VLOOKUP(B27,'Employees List'!$A$2:$K$991,11,0),"") -> 31 | M27: =IFERROR(VLOOKUP(D27,'Daily Attendance 25-26'!$A$4:BP999,5,0),"") -> 29 | N27: =IFERROR(VLOOKUP(E27,'Daily Attendance 25-26'!$A$1:$BO$1741,5,0),"") -> 101 | O27: 450 | Q27: =I27/L27*M27 -> 11225.806 | R27: =I27/L27/8*1.5*N27 -> 7330.6452 | S27: =Q27+R27-P27+O27 -> 19006.452 | T27: =U27*0.75% -> 142.54839 | U27: =Q27+R27+O27 -> 19006.452
A28: CPIEMP027 | B28: June | C28: AC 01 | D28: =B28&F28 -> JuneBHUVANESHWARAN.V | E28: =D28&$N$1 -> JuneBHUVANESHWARAN.VOT Hours | F28: =IFERROR(VLOOKUP(C28,'Employees List'!$B$1:$I$999,4,0),"") -> BHUVANESHWARAN.V | G28: =S28 -> 66900 | H28: =IFERROR(VLOOKUP(C28,'Employees List'!$B$2:$I$991,7,0),"") -> 500101011548924 | I28: =IFERROR(VLOOKUP(F28,'Employees List'!$E$1:$AE$991,6,0),"") -> 66000 | J28: =I28*70% -> 46200 | K28: =I28*30% -> 19800 | L28: =IFERROR(VLOOKUP(B28,'Employees List'!$A$2:$K$991,11,0),"") -> 30 | M28: =IFERROR(VLOOKUP(D28,'Daily Attendance 25-26'!$A$4:BP999,5,0),"") -> 30 | N28: =IFERROR(VLOOKUP(E28,'Daily Attendance 25-26'!$A$1:$BO$1741,5,0),"") -> 0 | O28: 900 | Q28: =I28/L28*M28 -> 66000 | R28: =I28/L28/8*1.5*N28 -> 0 | S28: =Q28+R28-P28+O28 -> 66900 | T28: 0 | U28: =Q28+R28+O28 -> 66900
A29: CPIEMP028 | B29: June | C29: AC 02 | D29: =B29&F29 -> JuneTHIRIPURA SUNDARI.R | E29: =D29&$N$1 -> JuneTHIRIPURA SUNDARI.ROT Hours | F29: =IFERROR(VLOOKUP(C29,'Employees List'!$B$1:$I$999,4,0),"") -> THIRIPURA SUNDARI.R | G29: =S29-T29 -> 22815.094 | H29: =IFERROR(VLOOKUP(C29,'Employees List'!$B$2:$I$991,7,0),"") -> 8131010000016977 | I29: =IFERROR(VLOOKUP(F29,'Employees List'!$E$1:$AE$991,6,0),"") -> 21000 | J29: =I29*70% -> 14700 | K29: =I29*30% -> 6300 | L29: =IFERROR(VLOOKUP(B29,'Employees List'!$A$2:$K$991,11,0),"") -> 30 | M29: =IFERROR(VLOOKUP(D29,'Daily Attendance 25-26'!$A$4:BP999,5,0),"") -> 30 | N29: =IFERROR(VLOOKUP(E29,'Daily Attendance 25-26'!$A$1:$BO$1741,5,0),"") -> 6 | O29: 1200 | Q29: =I29/L29*M29 -> 21000 | R29: =I29/L29/8*1.5*N29 -> 787.5 | S29: =Q29+R29-P29+O29 -> 22987.5 | T29: =U29*0.75% -> 172.40625 | U29: =Q29+R29+O29 -> 22987.5
A30: CPIEMP029 | B30: June | C30: PR 02 | D30: =B30&F30 -> JuneGANESH | E30: =D30&$N$1 -> JuneGANESHOT Hours | F30: =IFERROR(VLOOKUP(C30,'Employees List'!$B$1:$I$999,4,0),"") -> GANESH | G30: =S30-T30 -> 16190.401 | H30: =IFERROR(VLOOKUP(C30,'Employees List'!$B$2:$I$991,7,0),"") -> 8811010012054879 | I30: =IFERROR(VLOOKUP(F30,'Employees List'!$E$1:$AE$991,6,0),"") -> 18500 | J30: =I30*70% -> 12950 | K30: =I30*30% -> 5550 | L30: =IFERROR(VLOOKUP(B30,'Employees List'!$A$2:$K$991,11,0),"") -> 30 | M30: =IFERROR(VLOOKUP(D30,'Daily Attendance 25-26'!$A$4:BP999,5,0),"") -> 25 | N30: =IFERROR(VLOOKUP(E30,'Daily Attendance 25-26'!$A$1:$BO$1741,5,0),"") -> 30 | O30: 450 | P30: 3000 | Q30: =I30/L30*M30 -> 15416.667 | R30: =I30/L30/8*1.5*N30 -> 3468.75 | S30: =Q30+R30-P30+O30 -> 16335.417 | T30: =U30*0.75% -> 145.01562 | U30: =Q30+R30+O30 -> 19335.417
A31: CPIEMP030 | B31: June | C31: PR 01 | D31: =B31&F31 -> JuneVASANTHA.E | E31: =D31&$N$1 -> JuneVASANTHA.EOT Hours | F31: =IFERROR(VLOOKUP(C31,'Employees List'!$B$1:$I$999,4,0),"") -> VASANTHA.E | G31: =S31-T31 -> 18522.531 | H31: =IFERROR(VLOOKUP(C31,'Employees List'!$B$2:$I$991,7,0),"") -> 8131010000016959 | I31: =IFERROR(VLOOKUP(F31,'Employees List'!$E$1:$AE$991,6,0),"") -> 14500 | J31: =I31*70% -> 10150 | K31: =I31*30% -> 4350 | L31: =IFERROR(VLOOKUP(B31,'Employees List'!$A$2:$K$991,11,0),"") -> 30 | M31: =IFERROR(VLOOKUP(D31,'Daily Attendance 25-26'!$A$4:BP999,5,0),"") -> 30 | N31: =IFERROR(VLOOKUP(E31,'Daily Attendance 25-26'!$A$1:$BO$1741,5,0),"") -> 36 | O31: 900 | Q31: =I31/L31*M31 -> 14500 | R31: =I31/L31/8*1.5*N31 -> 3262.5 | S31: =Q31+R31-P31+O31 -> 18662.5 | T31: =U31*0.75% -> 139.96875 | U31: =Q31+R31+O31 -> 18662.5
A32: CPIEMP031 | B32: June | C32: DR 01 | D32: =B32&F32 -> JuneILAMATHIVANAN.S | E32: =D32&$N$1 -> JuneILAMATHIVANAN.SOT Hours | F32: =IFERROR(VLOOKUP(C32,'Employees List'!$B$1:$I$999,4,0),"") -> ILAMATHIVANAN.S | G32: =S32-T32 -> 13550.953 | H32: =IFERROR(VLOOKUP(C32,'Employees List'!$B$2:$I$991,7,0),"") -> 8131010000016986 | I32: =IFERROR(VLOOKUP(F32,'Employees List'!$E$1:$AE$991,6,0),"") -> 21000 | J32: =I32*70% -> 14700 | K32: =I32*30% -> 6300 | L32: =IFERROR(VLOOKUP(B32,'Employees List'!$A$2:$K$991,11,0),"") -> 30 | M32: =IFERROR(VLOOKUP(D32,'Daily Attendance 25-26'!$A$4:BP999,5,0),"") -> 22 | N32: =IFERROR(VLOOKUP(E32,'Daily Attendance 25-26'!$A$1:$BO$1741,5,0),"") -> 37 | O32: 450 | P32: 7000 | Q32: =I32/L32*M32 -> 15400 | R32: =I32/L32/8*1.5*N32 -> 4856.25 | S32: =Q32+R32-P32+O32 -> 13706.25 | T32: =U32*0.75% -> 155.29688 | U32: =Q32+R32+O32 -> 20706.25
A33: CPIEMP032 | B33: June | C33: PR 03 | D33: =B33&F33 -> JuneADHIKARI BALIA.A | E33: =D33&$N$1 -> JuneADHIKARI BALIA.AOT Hours | F33: =IFERROR(VLOOKUP(C33,'Employees List'!$B$1:$I$999,4,0),"") -> ADHIKARI BALIA.A | G33: =S33-T33 -> 19515.417 | H33: =IFERROR(VLOOKUP(C33,'Employees List'!$B$2:$I$991,7,0),"") -> 8131010000018948 | I33: =IFERROR(VLOOKUP(F33,'Employees List'!$E$1:$AE$991,6,0),"") -> 13000 | J33: =I33*70% -> 9100 | K33: =I33*30% -> 3900 | L33: =IFERROR(VLOOKUP(B33,'Employees List'!$A$2:$K$991,11,0),"") -> 30 | M33: =IFERROR(VLOOKUP(D33,'Daily Attendance 25-26'!$A$4:BP999,5,0),"") -> 29 | N33: =IFERROR(VLOOKUP(E33,'Daily Attendance 25-26'!$A$1:$BO$1741,5,0),"") -> 88 | O33: 450 | P33: 500 | Q33: =I33/L33*M33 -> 12566.667 | R33: =I33/L33/8*1.5*N33 -> 7150 | S33: =Q33+R33-P33+O33 -> 19666.667 | T33: =U33*0.75% -> 151.25 | U33: =Q33+R33+O33 -> 20166.667
A34: CPIEMP033 | B34: June | C34: PR 04 | D34: =B34&F34 -> JuneRUPESH KISAN | E34: =D34&$N$1 -> JuneRUPESH KISANOT Hours | F34: =IFERROR(VLOOKUP(C34,'Employees List'!$B$1:$I$999,4,0),"") -> RUPESH KISAN | G34: =S34-T34 -> 19370.292 | H34: =IFERROR(VLOOKUP(C34,'Employees List'!$B$2:$I$991,7,0),"") -> 411002010024591 | I34: =IFERROR(VLOOKUP(F34,'Employees List'!$E$1:$AE$991,6,0),"") -> 13000 | J34: =I34*70% -> 9100 | K34: =I34*30% -> 3900 | L34: =IFERROR(VLOOKUP(B34,'Employees List'!$A$2:$K$991,11,0),"") -> 30 | M34: =IFERROR(VLOOKUP(D34,'Daily Attendance 25-26'!$A$4:BP999,5,0),"") -> 29 | N34: =IFERROR(VLOOKUP(E34,'Daily Attendance 25-26'!$A$1:$BO$1741,5,0),"") -> 80 | O34: 450 | Q34: =I34/L34*M34 -> 12566.667 | R34: =I34/L34/8*1.5*N34 -> 6500 | S34: =Q34+R34-P34+O34 -> 19516.667 | T34: =U34*0.75% -> 146.375 | U34: =Q34+R34+O34 -> 19516.667
A35: CPIEMP034 | B35: June | C35: PR 05 | D35: =B35&F35 -> JuneSANJAY BAGARTTI.K | E35: =D35&$N$1 -> JuneSANJAY BAGARTTI.KOT Hours | F35: =IFERROR(VLOOKUP(C35,'Employees List'!$B$1:$I$999,4,0),"") -> SANJAY BAGARTTI.K | G35: =S35-T35 -> 20821.823 | H35: =IFERROR(VLOOKUP(C35,'Employees List'!$B$2:$I$991,7,0),"") -> 8131010000021225 | I35: =IFERROR(VLOOKUP(F35,'Employees List'!$E$1:$AE$991,6,0),"") -> 13000 | J35: =I35*70% -> 9100 | K35: =I35*30% -> 3900 | L35: =IFERROR(VLOOKUP(B35,'Employees List'!$A$2:$K$991,11,0),"") -> 30 | M35: =IFERROR(VLOOKUP(D35,'Daily Attendance 25-26'!$A$4:BP999,5,0),"") -> 29 | N35: =IFERROR(VLOOKUP(E35,'Daily Attendance 25-26'!$A$1:$BO$1741,5,0),"") -> 98 | O35: 450 | Q35: =I35/L35*M35 -> 12566.667 | R35: =I35/L35/8*1.5*N35 -> 7962.5 | S35: =Q35+R35-P35+O35 -> 20979.167 | T35: =U35*0.75% -> 157.34375 | U35: =Q35+R35+O35 -> 20979.167
A36: CPIEMP035 | B36: June | C36: PR 21 | D36: =B36&F36 -> JuneLIPAN | E36: =D36&$N$1 -> JuneLIPANOT Hours | F36: =IFERROR(VLOOKUP(C36,'Employees List'!$B$1:$I$999,4,0),"") -> LIPAN | G36: =S36-T36 -> 21456.609 | H36: =IFERROR(VLOOKUP(C36,'Employees List'!$B$2:$I$991,7,0),"") -> 8131010000018957 | I36: =IFERROR(VLOOKUP(F36,'Employees List'!$E$1:$AE$991,6,0),"") -> 13000 | J36: =I36*70% -> 9100 | K36: =I36*30% -> 3900 | L36: =IFERROR(VLOOKUP(B36,'Employees List'!$A$2:$K$991,11,0),"") -> 30 | M36: =IFERROR(VLOOKUP(D36,'Daily Attendance 25-26'!$A$4:BP999,5,0),"") -> 30 | N36: =IFERROR(VLOOKUP(E36,'Daily Attendance 25-26'!$A$1:$BO$1741,5,0),"") -> 95 | O36: 900 | Q36: =I36/L36*M36 -> 13000 | R36: =I36/L36/8*1.5*N36 -> 7718.75 | S36: =Q36+R36-P36+O36 -> 21618.75 | T36: =U36*0.75% -> 162.14062 | U36: =Q36+R36+O36 -> 21618.75
A37: CPIEMP036 | B37: June | C37: PR 24 | D37: =B37&F37 -> JuneNILAMANI KISAN.B | E37: =D37&$N$1 -> JuneNILAMANI KISAN.BOT Hours | F37: =IFERROR(VLOOKUP(C37,'Employees List'!$B$1:$I$999,4,0),"") -> NILAMANI KISAN.B | G37: =S37-T37 -> 9528 | H37: =IFERROR(VLOOKUP(C37,'Employees List'!$B$2:$I$991,7,0),"") -> 38254473147 | I37: =IFERROR(VLOOKUP(F37,'Employees List'!$E$1:$AE$991,6,0),"") -> 12000 | J37: =I37*70% -> 8400 | K37: =I37*30% -> 3600 | L37: =IFERROR(VLOOKUP(B37,'Employees List'!$A$2:$K$991,11,0),"") -> 30 | M37: =IFERROR(VLOOKUP(D37,'Daily Attendance 25-26'!$A$4:BP999,5,0),"") -> 15 | N37: =IFERROR(VLOOKUP(E37,'Daily Attendance 25-26'!$A$1:$BO$1741,5,0),"") -> 42 | O37: 450 | Q37: =I37/L37*M37 -> 6000 | R37: =I37/L37/8*1.5*N37 -> 3150 | S37: =Q37+R37-P37+O37 -> 9600 | T37: =U37*0.75% -> 72 | U37: =Q37+R37+O37 -> 9600
A38: CPIEMP037 | B38: June | C38: PR 07 | D38: =B38&F38 -> JuneAMMU.S | E38: =D38&$N$1 -> JuneAMMU.SOT Hours | F38: =IFERROR(VLOOKUP(C38,'Employees List'!$B$1:$I$999,4,0),"") -> AMMU.S | G38: =S38-T38 -> 12648.172 | H38: =IFERROR(VLOOKUP(C38,'Employees List'!$B$2:$I$991,7,0),"") -> 65801000040238 | I38: =IFERROR(VLOOKUP(F38,'Employees List'!$E$1:$AE$991,6,0),"") -> 10500 | J38: =I38*70% -> 7350 | K38: =I38*30% -> 3150 | L38: =IFERROR(VLOOKUP(B38,'Employees List'!$A$2:$K$991,11,0),"") -> 30 | M38: =IFERROR(VLOOKUP(D38,'Daily Attendance 25-26'!$A$4:BP999,5,0),"") -> 28 | N38: =IFERROR(VLOOKUP(E38,'Daily Attendance 25-26'!$A$1:$BO$1741,5,0),"") -> 38 | O38: 450 | Q38: =I38/L38*M38 -> 9800 | R38: =I38/L38/8*1.5*N38 -> 2493.75 | S38: =Q38+R38-P38+O38 -> 12743.75 | T38: =U38*0.75% -> 95.578125 | U38: =Q38+R38+O38 -> 12743.75
A39: CPIEMP038 | B39: June | C39: PR 08 | D39: =B39&F39 -> JuneREVATHI.S | E39: =D39&$N$1 -> JuneREVATHI.SOT Hours | F39: =IFERROR(VLOOKUP(C39,'Employees List'!$B$1:$I$999,4,0),"") -> REVATHI.S | G39: =S39-T39 -> 10995.547 | H39: =IFERROR(VLOOKUP(C39,'Employees List'!$B$2:$I$991,7,0),"") -> 8131010000016995 | I39: =IFERROR(VLOOKUP(F39,'Employees List'!$E$1:$AE$991,6,0),"") -> 10500 | J39: =I39*70% -> 7350 | K39: =I39*30% -> 3150 | L39: =IFERROR(VLOOKUP(B39,'Employees List'!$A$2:$K$991,11,0),"") -> 30 | M39: =IFERROR(VLOOKUP(D39,'Daily Attendance 25-26'!$A$4:BP999,5,0),"") -> 29 | N39: =IFERROR(VLOOKUP(E39,'Daily Attendance 25-26'!$A$1:$BO$1741,5,0),"") -> 38 | O39: 450 | P39: 2000 | Q39: =I39/L39*M39 -> 10150 | R39: =I39/L39/8*1.5*N39 -> 2493.75 | S39: =Q39+R39-P39+O39 -> 11093.75 | T39: =U39*0.75% -> 98.203125 | U39: =Q39+R39+O39 -> 13093.75
A40: CPIEMP039 | B40: June | C40: AC 03 | D40: =B40&F40 -> JuneLEELAVATHI.M | E40: =D40&$N$1 -> JuneLEELAVATHI.MOT Hours | F40: =IFERROR(VLOOKUP(C40,'Employees List'!$B$1:$I$999,4,0),"") -> LEELAVATHI.M | G40: =S40-T40 -> 14138.99 | H40: =IFERROR(VLOOKUP(C40,'Employees List'!$B$2:$I$991,7,0),"") -> 8387010000017745 | I40: =IFERROR(VLOOKUP(F40,'Employees List'!$E$1:$AE$991,6,0),"") -> 14000 | J40: =I40*70% -> 9800 | K40: =I40*30% -> 4200 | L40: =IFERROR(VLOOKUP(B40,'Employees List'!$A$2:$K$991,11,0),"") -> 30 | M40: =IFERROR(VLOOKUP(D40,'Daily Attendance 25-26'!$A$4:BP999,5,0),"") -> 29 | N40: =IFERROR(VLOOKUP(E40,'Daily Attendance 25-26'!$A$1:$BO$1741,5,0),"") -> 3 | O40: 450 | Q40: =I40/L40*M40 -> 13533.333 | R40: =I40/L40/8*1.5*N40 -> 262.5 | S40: =Q40+R40-P40+O40 -> 14245.833 | T40: =U40*0.75% -> 106.84375 | U40: =Q40+R40+O40 -> 14245.833
A41: CPIEMP040 | B41: July | C41: AC 01 | D41: =B41&F41 -> JulyBHUVANESHWARAN.V | E41: =D41&$N$1 -> JulyBHUVANESHWARAN.VOT Hours | F41: =IFERROR(VLOOKUP(C41,'Employees List'!$B$1:$I$999,4,0),"") -> BHUVANESHWARAN.V | G41: =S41-T41 -> 66900 | H41: =IFERROR(VLOOKUP(C41,'Employees List'!$B$2:$I$991,7,0),"") -> 500101011548924 | I41: =IFERROR(VLOOKUP(F41,'Employees List'!$E$1:$AE$991,6,0),"") -> 66000 | J41: =I41*70% -> 46200 | K41: =I41*30% -> 19800 | L41: =IFERROR(VLOOKUP(B41,'Employees List'!$A$2:$K$991,11,0),"") -> 31 | M41: =IFERROR(VLOOKUP(D41,'Daily Attendance 25-26'!$A$4:BP999,5,0),"") -> 31 | N41: =IFERROR(VLOOKUP(E41,'Daily Attendance 25-26'!$A$1:$BO$1741,5,0),"") -> 0 | O41: 900 | Q41: =I41/L41*M41 -> 66000 | R41: =I41/L41/8*1.5*N41 -> 0 | S41: =Q41+R41-P41+O41 -> 66900 | U41: =Q41+R41+O41 -> 66900
A42: CPIEMP041 | B42: July | C42: AC 02 | D42: =B42&F42 -> JulyTHIRIPURA SUNDARI.R | E42: =D42&$N$1 -> JulyTHIRIPURA SUNDARI.ROT Hours | F42: =IFERROR(VLOOKUP(C42,'Employees List'!$B$1:$I$999,4,0),"") -> THIRIPURA SUNDARI.R | G42: =S42-T42 -> 18503.722 | H42: =IFERROR(VLOOKUP(C42,'Employees List'!$B$2:$I$991,7,0),"") -> 8131010000016977 | I42: =IFERROR(VLOOKUP(F42,'Employees List'!$E$1:$AE$991,6,0),"") -> 21000 | J42: =I42*70% -> 14700 | K42: =I42*30% -> 6300 | L42: =IFERROR(VLOOKUP(B42,'Employees List'!$A$2:$K$991,11,0),"") -> 31 | M42: =IFERROR(VLOOKUP(D42,'Daily Attendance 25-26'!$A$4:BP999,5,0),"") -> 25 | N42: =IFERROR(VLOOKUP(E42,'Daily Attendance 25-26'!$A$1:$BO$1741,5,0),"") -> 4 | O42: 1200 | Q42: =I42/L42*M42 -> 16935.484 | R42: =I42/L42/8*1.5*N42 -> 508.06452 | S42: =Q42+R42-P42+O42 -> 18643.548 | T42: =U42*0.75% -> 139.82661 | U42: =Q42+R42+O42 -> 18643.548
A43: CPIEMP042 | B43: July | C43: PR 02 | D43: =B43&F43 -> JulyGANESH | E43: =D43&$N$1 -> JulyGANESHOT Hours | F43: =IFERROR(VLOOKUP(C43,'Employees List'!$B$1:$I$999,4,0),"") -> GANESH | G43: =S43-T43 -> 13754.085 | H43: =IFERROR(VLOOKUP(C43,'Employees List'!$B$2:$I$991,7,0),"") -> 8811010012054879 | I43: =IFERROR(VLOOKUP(F43,'Employees List'!$E$1:$AE$991,6,0),"") -> 18500 | J43: =I43*70% -> 12950 | K43: =I43*30% -> 5550 | L43: =IFERROR(VLOOKUP(B43,'Employees List'!$A$2:$K$991,11,0),"") -> 31 | M43: =IFERROR(VLOOKUP(D43,'Daily Attendance 25-26'!$A$4:BP999,5,0),"") -> 22 | N43: =IFERROR(VLOOKUP(E43,'Daily Attendance 25-26'!$A$1:$BO$1741,5,0),"") -> 16 | O43: 450 | P43: 1500 | Q43: =I43/L43*M43 -> 13129.032 | R43: =I43/L43/8*1.5*N43 -> 1790.3226 | S43: =Q43+R43-P43+O43 -> 13869.355 | T43: =U43*0.75% -> 115.27016 | U43: =Q43+R43+O43 -> 15369.355
A44: CPIEMP043 | B44: July | C44: PR 01 | D44: =B44&F44 -> JulyVASANTHA.E | E44: =D44&$N$1 -> JulyVASANTHA.EOT Hours | F44: =IFERROR(VLOOKUP(C44,'Employees List'!$B$1:$I$999,4,0),"") -> VASANTHA.E | G44: =S44-T44 -> 15244.08 | H44: =IFERROR(VLOOKUP(C44,'Employees List'!$B$2:$I$991,7,0),"") -> 8131010000016959 | I44: =IFERROR(VLOOKUP(F44,'Employees List'!$E$1:$AE$991,6,0),"") -> 14500 | J44: =I44*70% -> 10150 | K44: =I44*30% -> 4350 | L44: =IFERROR(VLOOKUP(B44,'Employees List'!$A$2:$K$991,11,0),"") -> 31 | M44: =IFERROR(VLOOKUP(D44,'Daily Attendance 25-26'!$A$4:BP999,5,0),"") -> 27 | N44: =IFERROR(VLOOKUP(E44,'Daily Attendance 25-26'!$A$1:$BO$1741,5,0),"") -> 26 | O44: 450 | Q44: =I44/L44*M44 -> 12629.032 | R44: =I44/L44/8*1.5*N44 -> 2280.2419 | S44: =Q44+R44-P44+O44 -> 15359.274 | T44: =U44*0.75% -> 115.19456 | U44: =Q44+R44+O44 -> 15359.274
A45: CPIEMP044 | B45: July | C45: DR 01 | D45: =B45&F45 -> JulyILAMATHIVANAN.S | E45: =D45&$N$1 -> JulyILAMATHIVANAN.SOT Hours | F45: =IFERROR(VLOOKUP(C45,'Employees List'!$B$1:$I$999,4,0),"") -> ILAMATHIVANAN.S | G45: =S45-T45 -> 4118.0746 | H45: =IFERROR(VLOOKUP(C45,'Employees List'!$B$2:$I$991,7,0),"") -> 8131010000016986 | I45: =IFERROR(VLOOKUP(F45,'Employees List'!$E$1:$AE$991,6,0),"") -> 21000 | J45: =I45*70% -> 14700 | K45: =I45*30% -> 6300 | L45: =IFERROR(VLOOKUP(B45,'Employees List'!$A$2:$K$991,11,0),"") -> 31 | M45: =IFERROR(VLOOKUP(D45,'Daily Attendance 25-26'!$A$4:BP999,5,0),"") -> 5 | N45: =IFERROR(VLOOKUP(E45,'Daily Attendance 25-26'!$A$1:$BO$1741,5,0),"") -> 6 | Q45: =I45/L45*M45 -> 3387.0968 | R45: =I45/L45/8*1.5*N45 -> 762.09677 | S45: =Q45+R45-P45+O45 -> 4149.1935 | T45: =U45*0.75% -> 31.118952 | U45: =Q45+R45+O45 -> 4149.1935
A46: CPIEMP045 | B46: July | C46: PR 04 | D46: =B46&F46 -> JulyRUPESH KISAN | E46: =D46&$N$1 -> JulyRUPESH KISANOT Hours | F46: =IFERROR(VLOOKUP(C46,'Employees List'!$B$1:$I$999,4,0),"") -> RUPESH KISAN | G46: =S46-T46 -> 19648.699 | H46: =IFERROR(VLOOKUP(C46,'Employees List'!$B$2:$I$991,7,0),"") -> 411002010024591 | I46: =IFERROR(VLOOKUP(F46,'Employees List'!$E$1:$AE$991,6,0),"") -> 13000 | J46: =I46*70% -> 9100 | K46: =I46*30% -> 3900 | L46: =IFERROR(VLOOKUP(B46,'Employees List'!$A$2:$K$991,11,0),"") -> 31 | M46: =IFERROR(VLOOKUP(D46,'Daily Attendance 25-26'!$A$4:BP999,5,0),"") -> 31 | N46: =IFERROR(VLOOKUP(E46,'Daily Attendance 25-26'!$A$1:$BO$1741,5,0),"") -> 75 | O46: 900 | Q46: =I46/L46*M46 -> 13000 | R46: =I46/L46/8*1.5*N46 -> 5897.1774 | S46: =Q46+R46-P46+O46 -> 19797.177 | T46: =U46*0.75% -> 148.47883 | U46: =Q46+R46+O46 -> 19797.177
A47: CPIEMP046 | B47: July | C47: PR 05 | D47: =B47&F47 -> JulySANJAY BAGARTTI.K | E47: =D47&$N$1 -> JulySANJAY BAGARTTI.KOT Hours | F47: =IFERROR(VLOOKUP(C47,'Employees List'!$B$1:$I$999,4,0),"") -> SANJAY BAGARTTI.K | G47: =S47-T47 -> 21599.681 | H47: =IFERROR(VLOOKUP(C47,'Employees List'!$B$2:$I$991,7,0),"") -> 8131010000021225 | I47: =IFERROR(VLOOKUP(F47,'Employees List'!$E$1:$AE$991,6,0),"") -> 13000 | J47: =I47*70% -> 9100 | K47: =I47*30% -> 3900 | L47: =IFERROR(VLOOKUP(B47,'Employees List'!$A$2:$K$991,11,0),"") -> 31 | M47: =IFERROR(VLOOKUP(D47,'Daily Attendance 25-26'!$A$4:BP999,5,0),"") -> 31 | N47: =IFERROR(VLOOKUP(E47,'Daily Attendance 25-26'!$A$1:$BO$1741,5,0),"") -> 100 | O47: 900 | Q47: =I47/L47*M47 -> 13000 | R47: =I47/L47/8*1.5*N47 -> 7862.9032 | S47: =Q47+R47-P47+O47 -> 21762.903 | T47: =U47*0.75% -> 163.22177 | U47: =Q47+R47+O47 -> 21762.903
A48: CPIEMP047 | B48: July | C48: PR 21 | D48: =B48&F48 -> JulyLIPAN | E48: =D48&$N$1 -> JulyLIPANOT Hours | F48: =IFERROR(VLOOKUP(C48,'Employees List'!$B$1:$I$999,4,0),"") -> LIPAN | G48: =S48-T48 -> 20897.328 | H48: =IFERROR(VLOOKUP(C48,'Employees List'!$B$2:$I$991,7,0),"") -> 8131010000018957 | I48: =IFERROR(VLOOKUP(F48,'Employees List'!$E$1:$AE$991,6,0),"") -> 13000 | J48: =I48*70% -> 9100 | K48: =I48*30% -> 3900 | L48: =IFERROR(VLOOKUP(B48,'Employees List'!$A$2:$K$991,11,0),"") -> 31 | M48: =IFERROR(VLOOKUP(D48,'Daily Attendance 25-26'!$A$4:BP999,5,0),"") -> 31 | N48: =IFERROR(VLOOKUP(E48,'Daily Attendance 25-26'!$A$1:$BO$1741,5,0),"") -> 91 | O48: 900 | Q48: =I48/L48*M48 -> 13000 | R48: =I48/L48/8*1.5*N48 -> 7155.2419 | S48: =Q48+R48-P48+O48 -> 21055.242 | T48: =U48*0.75% -> 157.91431 | U48: =Q48+R48+O48 -> 21055.242
A49: CPIEMP048 | B49: July | C49: PR 07 | D49: =B49&F49 -> JulyAMMU.S | E49: =D49&$N$1 -> JulyAMMU.SOT Hours | F49: =IFERROR(VLOOKUP(C49,'Employees List'!$B$1:$I$999,4,0),"") -> AMMU.S | G49: =S49-T49 -> 9187.0282 | H49: =IFERROR(VLOOKUP(C49,'Employees List'!$B$2:$I$991,7,0),"") -> 65801000040238 | I49: =IFERROR(VLOOKUP(F49,'Employees List'!$E$1:$AE$991,6,0),"") -> 10500 | J49: =I49*70% -> 7350 | K49: =I49*30% -> 3150 | L49: =IFERROR(VLOOKUP(B49,'Employees List'!$A$2:$K$991,11,0),"") -> 31 | M49: =IFERROR(VLOOKUP(D49,'Daily Attendance 25-26'!$A$4:BP999,5,0),"") -> 23 | N49: =IFERROR(VLOOKUP(E49,'Daily Attendance 25-26'!$A$1:$BO$1741,5,0),"") -> 16 | O49: 450 | Q49: =I49/L49*M49 -> 7790.3226 | R49: =I49/L49/8*1.5*N49 -> 1016.129 | S49: =Q49+R49-P49+O49 -> 9256.4516 | T49: =U49*0.75% -> 69.423387 | U49: =Q49+R49+O49 -> 9256.4516
A50: CPIEMP049 | B50: July | C50: PR 08 | D50: =B50&F50 -> JulyREVATHI.S | E50: =D50&$N$1 -> JulyREVATHI.SOT Hours | F50: =IFERROR(VLOOKUP(C50,'Employees List'!$B$1:$I$999,4,0),"") -> REVATHI.S | G50: =S50-T50 -> 10448.722 | H50: =IFERROR(VLOOKUP(C50,'Employees List'!$B$2:$I$991,7,0),"") -> 8131010000016995 | I50: =IFERROR(VLOOKUP(F50,'Employees List'!$E$1:$AE$991,6,0),"") -> 10500 | J50: =I50*70% -> 7350 | K50: =I50*30% -> 3150 | L50: =IFERROR(VLOOKUP(B50,'Employees List'!$A$2:$K$991,11,0),"") -> 31 | M50: =IFERROR(VLOOKUP(D50,'Daily Attendance 25-26'!$A$4:BP999,5,0),"") -> 30 | N50: =IFERROR(VLOOKUP(E50,'Daily Attendance 25-26'!$A$1:$BO$1741,5,0),"") -> 32 | O50: 450 | P50: 2100 | Q50: =I50/L50*M50 -> 10161.29 | R50: =I50/L50/8*1.5*N50 -> 2032.2581 | S50: =Q50+R50-P50+O50 -> 10543.548 | T50: =U50*0.75% -> 94.826613 | U50: =Q50+R50+O50 -> 12643.548
A51: CPIEMP050 | B51: July | C51: AC 03 | D51: =B51&F51 -> JulyLEELAVATHI.M | E51: =D51&$N$1 -> JulyLEELAVATHI.MOT Hours | F51: =IFERROR(VLOOKUP(C51,'Employees List'!$B$1:$I$999,4,0),"") -> LEELAVATHI.M | G51: =S51-T51 -> 14733.823 | H51: =IFERROR(VLOOKUP(C51,'Employees List'!$B$2:$I$991,7,0),"") -> 8387010000017745 | I51: =IFERROR(VLOOKUP(F51,'Employees List'!$E$1:$AE$991,6,0),"") -> 14000 | J51: =I51*70% -> 9800 | K51: =I51*30% -> 4200 | L51: =IFERROR(VLOOKUP(B51,'Employees List'!$A$2:$K$991,11,0),"") -> 31 | M51: =IFERROR(VLOOKUP(D51,'Daily Attendance 25-26'!$A$4:BP999,5,0),"") -> 30 | N51: =IFERROR(VLOOKUP(E51,'Daily Attendance 25-26'!$A$1:$BO$1741,5,0),"") -> 10 | O51: 450 | Q51: =I51/L51*M51 -> 13548.387 | R51: =I51/L51/8*1.5*N51 -> 846.77419 | S51: =Q51+R51-P51+O51 -> 14845.161 | T51: =U51*0.75% -> 111.33871 | U51: =Q51+R51+O51 -> 14845.161
A52: CPIEMP051 | B52: July | C52: PR 03 | D52: =B52&F52 -> JulyADHIKARI BALIA.A | E52: =D52&$N$1 -> JulyADHIKARI BALIA.AOT Hours | F52: =IFERROR(VLOOKUP(C52,'Employees List'!$B$1:$I$999,4,0),"") -> ADHIKARI BALIA.A | G52: =S52-T52 -> 16239.589 | H52: =IFERROR(VLOOKUP(C52,'Employees List'!$B$2:$I$991,7,0),"") -> 8131010000018948 | I52: =IFERROR(VLOOKUP(F52,'Employees List'!$E$1:$AE$991,6,0),"") -> 13000 | J52: =I52*70% -> 9100 | K52: =I52*30% -> 3900 | L52: =IFERROR(VLOOKUP(B52,'Employees List'!$A$2:$K$991,11,0),"") -> 31 | M52: =IFERROR(VLOOKUP(D52,'Daily Attendance 25-26'!$A$4:BP999,5,0),"") -> 30 | N52: =IFERROR(VLOOKUP(E52,'Daily Attendance 25-26'!$A$1:$BO$1741,5,0),"") -> 68 | O52: 450 | P52: 2000 | Q52: =I52/L52*M52 -> 12580.645 | R52: =I52/L52/8*1.5*N52 -> 5346.7742 | S52: =Q52+R52-P52+O52 -> 16377.419 | T52: =U52*0.75% -> 137.83065 | U52: =Q52+R52+O52 -> 18377.419
A53: CPIEMP052 | B53: July | C53: PR 27 | D53: =B53&F53 -> JulyPARSHU BAGH | E53: =D53&$N$1 -> JulyPARSHU BAGHOT Hours | F53: =IFERROR(VLOOKUP(C53,'Employees List'!$B$1:$I$999,4,0),"") -> PARSHU BAGH | G53: =S53-T53 -> 13196.055 | H53: =IFERROR(VLOOKUP(C53,'Employees List'!$B$2:$I$991,7,0),"") -> 40653547928 | I53: =IFERROR(VLOOKUP(F53,'Employees List'!$E$1:$AE$991,6,0),"") -> 13000 | J53: =I53*70% -> 9100 | K53: =I53*30% -> 3900 | L53: =IFERROR(VLOOKUP(B53,'Employees List'!$A$2:$K$991,11,0),"") -> 31 | M53: =IFERROR(VLOOKUP(D53,'Daily Attendance 25-26'!$A$4:BP999,5,0),"") -> 24 | N53: =IFERROR(VLOOKUP(E53,'Daily Attendance 25-26'!$A$1:$BO$1741,5,0),"") -> 61 | O53: 450 | P53: 2000 | Q53: =I53/L53*M53 -> 10064.516 | R53: =I53/L53/8*1.5*N53 -> 4796.371 | S53: =Q53+R53-P53+O53 -> 13310.887 | T53: =U53*0.75% -> 114.83165 | U53: =Q53+R53+O53 -> 15310.887
A54: CPIEMP053 | B54: August | C54: AC 01 | D54: =B54&F54 -> AugustBHUVANESHWARAN.V | E54: =D54&$N$1 -> AugustBHUVANESHWARAN.VOT Hours | F54: =IFERROR(VLOOKUP(C54,'Employees List'!$B$1:$I$999,4,0),"") -> BHUVANESHWARAN.V | G54: =S54-T54 -> 66900 | H54: =IFERROR(VLOOKUP(C54,'Employees List'!$B$2:$I$991,7,0),"") -> 500101011548924 | I54: =IFERROR(VLOOKUP(F54,'Employees List'!$E$1:$AE$991,6,0),"") -> 66000 | J54: =I54*70% -> 46200 | K54: =I54*30% -> 19800 | L54: =IFERROR(VLOOKUP(B54,'Employees List'!$A$2:$K$991,11,0),"") -> 31 | M54: =IFERROR(VLOOKUP(D54,'Daily Attendance 25-26'!$A$4:BP999,5,0),"") -> 31 | N54: =IFERROR(VLOOKUP(E54,'Daily Attendance 25-26'!$A$1:$BO$1741,5,0),"") -> 0 | O54: 900 | Q54: =I54/L54*M54 -> 66000 | R54: =I54/L54/8*1.5*N54 -> 0 | S54: =Q54+R54-P54+O54 -> 66900 | T54: 0 | U54: =Q54+R54+O54 -> 66900
A55: CPIEMP054 | B55: August | C55: AC 02 | D55: =B55&F55 -> AugustTHIRIPURA SUNDARI.R | E55: =D55&$N$1 -> AugustTHIRIPURA SUNDARI.ROT Hours | F55: =IFERROR(VLOOKUP(C55,'Employees List'!$B$1:$I$999,4,0),"") -> THIRIPURA SUNDARI.R | G55: =S55-T55 -> 22201.585 | H55: =IFERROR(VLOOKUP(C55,'Employees List'!$B$2:$I$991,7,0),"") -> 8131010000016977 | I55: =IFERROR(VLOOKUP(F55,'Employees List'!$E$1:$AE$991,6,0),"") -> 21000 | J55: =I55*70% -> 14700 | K55: =I55*30% -> 6300 | L55: =IFERROR(VLOOKUP(B55,'Employees List'!$A$2:$K$991,11,0),"") -> 31 | M55: =IFERROR(VLOOKUP(D55,'Daily Attendance 25-26'!$A$4:BP999,5,0),"") -> 29 | N55: =IFERROR(VLOOKUP(E55,'Daily Attendance 25-26'!$A$1:$BO$1741,5,0),"") -> 12 | O55: 1200 | Q55: =I55/L55*M55 -> 19645.161 | R55: =I55/L55/8*1.5*N55 -> 1524.1935 | S55: =Q55+R55-P55+O55 -> 22369.355 | T55: =U55*0.75% -> 167.77016 | U55: =Q55+R55+O55 -> 22369.355
A56: CPIEMP055 | B56: August | C56: PR 02 | D56: =B56&F56 -> AugustGANESH | E56: =D56&$N$1 -> AugustGANESHOT Hours | F56: =IFERROR(VLOOKUP(C56,'Employees List'!$B$1:$I$999,4,0),"") -> GANESH | G56: =S56-T56 -> 20397.195 | H56: =IFERROR(VLOOKUP(C56,'Employees List'!$B$2:$I$991,7,0),"") -> 8811010012054879 | I56: =IFERROR(VLOOKUP(F56,'Employees List'!$E$1:$AE$991,6,0),"") -> 18500 | J56: =I56*70% -> 12950 | K56: =I56*30% -> 5550 | L56: =IFERROR(VLOOKUP(B56,'Employees List'!$A$2:$K$991,11,0),"") -> 31 | M56: =IFERROR(VLOOKUP(D56,'Daily Attendance 25-26'!$A$4:BP999,5,0),"") -> 29 | N56: =IFERROR(VLOOKUP(E56,'Daily Attendance 25-26'!$A$1:$BO$1741,5,0),"") -> 70 | O56: 450 | P56: 5000 | Q56: =I56/L56*M56 -> 17306.452 | R56: =I56/L56/8*1.5*N56 -> 7832.6613 | S56: =Q56+R56-P56+O56 -> 20589.113 | T56: =U56*0.75% -> 191.91835 | U56: =Q56+R56+O56 -> 25589.113
A57: CPIEMP056 | B57: August | C57: PR 01 | D57: =B57&F57 -> AugustVASANTHA.E | E57: =D57&$N$1 -> AugustVASANTHA.EOT Hours | F57: =IFERROR(VLOOKUP(C57,'Employees List'!$B$1:$I$999,4,0),"") -> VASANTHA.E | G57: =S57-T57 -> 19462.605 | H57: =IFERROR(VLOOKUP(C57,'Employees List'!$B$2:$I$991,7,0),"") -> 8131010000016959 | I57: =IFERROR(VLOOKUP(F57,'Employees List'!$E$1:$AE$991,6,0),"") -> 14500 | J57: =I57*70% -> 10150 | K57: =I57*30% -> 4350 | L57: =IFERROR(VLOOKUP(B57,'Employees List'!$A$2:$K$991,11,0),"") -> 31 | M57: =IFERROR(VLOOKUP(D57,'Daily Attendance 25-26'!$A$4:BP999,5,0),"") -> 31 | N57: =IFERROR(VLOOKUP(E57,'Daily Attendance 25-26'!$A$1:$BO$1741,5,0),"") -> 48 | O57: 900 | Q57: =I57/L57*M57 -> 14500 | R57: =I57/L57/8*1.5*N57 -> 4209.6774 | S57: =Q57+R57-P57+O57 -> 19609.677 | T57: =U57*0.75% -> 147.07258 | U57: =Q57+R57+O57 -> 19609.677
A58: CPIEMP057 | B58: August | C58: PR 03 | D58: =B58&F58 -> AugustADHIKARI BALIA.A | E58: =D58&$N$1 -> AugustADHIKARI BALIA.AOT Hours | F58: =IFERROR(VLOOKUP(C58,'Employees List'!$B$1:$I$999,4,0),"") -> ADHIKARI BALIA.A | G58: =S58-T58 -> 15843.908 | H58: =IFERROR(VLOOKUP(C58,'Employees List'!$B$2:$I$991,7,0),"") -> 8131010000018948 | I58: =IFERROR(VLOOKUP(F58,'Employees List'!$E$1:$AE$991,6,0),"") -> 13000 | J58: =I58*70% -> 9100 | K58: =I58*30% -> 3900 | L58: =IFERROR(VLOOKUP(B58,'Employees List'!$A$2:$K$991,11,0),"") -> 31 | M58: =IFERROR(VLOOKUP(D58,'Daily Attendance 25-26'!$A$4:BP999,5,0),"") -> 30 | N58: =IFERROR(VLOOKUP(E58,'Daily Attendance 25-26'!$A$1:$BO$1741,5,0),"") -> 127 | O58: 450 | P58: 7000 | Q58: =I58/L58*M58 -> 12580.645 | R58: =I58/L58/8*1.5*N58 -> 9985.8871 | S58: =Q58+R58-P58+O58 -> 16016.532 | T58: =U58*0.75% -> 172.62399 | U58: =Q58+R58+O58 -> 23016.532
A59: CPIEMP058 | B59: August | C59: PR 04 | D59: =B59&F59 -> AugustRUPESH KISAN | E59: =D59&$N$1 -> AugustRUPESH KISANOT Hours | F59: =IFERROR(VLOOKUP(C59,'Employees List'!$B$1:$I$999,4,0),"") -> RUPESH KISAN | G59: =S59-T59 -> 15687.83 | H59: =IFERROR(VLOOKUP(C59,'Employees List'!$B$2:$I$991,7,0),"") -> 411002010024591 | I59: =IFERROR(VLOOKUP(F59,'Employees List'!$E$1:$AE$991,6,0),"") -> 13000 | J59: =I59*70% -> 9100 | K59: =I59*30% -> 3900 | L59: =IFERROR(VLOOKUP(B59,'Employees List'!$A$2:$K$991,11,0),"") -> 31 | M59: =IFERROR(VLOOKUP(D59,'Daily Attendance 25-26'!$A$4:BP999,5,0),"") -> 30 | N59: =IFERROR(VLOOKUP(E59,'Daily Attendance 25-26'!$A$1:$BO$1741,5,0),"") -> 125 | O59: 450 | P59: 7000 | Q59: =I59/L59*M59 -> 12580.645 | R59: =I59/L59/8*1.5*N59 -> 9828.629 | S59: =Q59+R59-P59+O59 -> 15859.274 | T59: =U59*0.75% -> 171.44456 | U59: =Q59+R59+O59 -> 22859.274
A60: CPIEMP059 | B60: August | C60: PR 05 | D60: =B60&F60 -> AugustSANJAY BAGARTTI.K | E60: =D60&$N$1 -> AugustSANJAY BAGARTTI.KOT Hours | F60: =IFERROR(VLOOKUP(C60,'Employees List'!$B$1:$I$999,4,0),"") -> SANJAY BAGARTTI.K | G60: =S60-T60 -> 20736.847 | H60: =IFERROR(VLOOKUP(C60,'Employees List'!$B$2:$I$991,7,0),"") -> 8131010000021225 | I60: =IFERROR(VLOOKUP(F60,'Employees List'!$E$1:$AE$991,6,0),"") -> 13000 | J60: =I60*70% -> 9100 | K60: =I60*30% -> 3900 | L60: =IFERROR(VLOOKUP(B60,'Employees List'!$A$2:$K$991,11,0),"") -> 31 | M60: =IFERROR(VLOOKUP(D60,'Daily Attendance 25-26'!$A$4:BP999,5,0),"") -> 30 | N60: =IFERROR(VLOOKUP(E60,'Daily Attendance 25-26'!$A$1:$BO$1741,5,0),"") -> 100 | O60: 450 | Q60: =I60/L60*M60 -> 12580.645 | R60: =I60/L60/8*1.5*N60 -> 7862.9032 | S60: =Q60+R60-P60+O60 -> 20893.548 | T60: =U60*0.75% -> 156.70161 | U60: =Q60+R60+O60 -> 20893.548
A61: CPIEMP060 | B61: August | C61: PR 07 | D61: =B61&F61 -> AugustAMMU.S | E61: =D61&$N$1 -> AugustAMMU.SOT Hours | F61: =IFERROR(VLOOKUP(C61,'Employees List'!$B$1:$I$999,4,0),"") -> AMMU.S | G61: =S61-T61 -> 14276.992 | H61: =IFERROR(VLOOKUP(C61,'Employees List'!$B$2:$I$991,7,0),"") -> 65801000040238 | I61: =IFERROR(VLOOKUP(F61,'Employees List'!$E$1:$AE$991,6,0),"") -> 10500 | J61: =I61*70% -> 7350 | K61: =I61*30% -> 3150 | L61: =IFERROR(VLOOKUP(B61,'Employees List'!$A$2:$K$991,11,0),"") -> 31 | M61: =IFERROR(VLOOKUP(D61,'Daily Attendance 25-26'!$A$4:BP999,5,0),"") -> 31 | N61: =IFERROR(VLOOKUP(E61,'Daily Attendance 25-26'!$A$1:$BO$1741,5,0),"") -> 47 | O61: 900 | Q61: =I61/L61*M61 -> 10500 | R61: =I61/L61/8*1.5*N61 -> 2984.879 | S61: =Q61+R61-P61+O61 -> 14384.879 | T61: =U61*0.75% -> 107.88659 | U61: =Q61+R61+O61 -> 14384.879
A62: CPIEMP061 | B62: August | C62: PR 08 | D62: =B62&F62 -> AugustREVATHI.S | E62: =D62&$N$1 -> AugustREVATHI.SOT Hours | F62: =IFERROR(VLOOKUP(C62,'Employees List'!$B$1:$I$999,4,0),"") -> REVATHI.S | G62: =S62-T62 -> 9779.8382 | H62: =IFERROR(VLOOKUP(C62,'Employees List'!$B$2:$I$991,7,0),"") -> 8131010000016995 | I62: =IFERROR(VLOOKUP(F62,'Employees List'!$E$1:$AE$991,6,0),"") -> 10500 | J62: =I62*70% -> 7350 | K62: =I62*30% -> 3150 | L62: =IFERROR(VLOOKUP(B62,'Employees List'!$A$2:$K$991,11,0),"") -> 31 | M62: =IFERROR(VLOOKUP(D62,'Daily Attendance 25-26'!$A$4:BP999,5,0),"") -> 29 | N62: =IFERROR(VLOOKUP(E62,'Daily Attendance 25-26'!$A$1:$BO$1741,5,0),"") -> 41 | O62: 450 | P62: 3000 | Q62: =I62/L62*M62 -> 9822.5806 | R62: =I62/L62/8*1.5*N62 -> 2603.8306 | S62: =Q62+R62-P62+O62 -> 9876.4113 | T62: =U62*0.75% -> 96.573085 | U62: =Q62+R62+O62 -> 12876.411
A63: CPIEMP062 | B63: August | C63: AC 03 | D63: =B63&F63 -> AugustLEELAVATHI.M | E63: =D63&$N$1 -> AugustLEELAVATHI.MOT Hours | F63: =IFERROR(VLOOKUP(C63,'Employees List'!$B$1:$I$999,4,0),"") -> LEELAVATHI.M | G63: =S63-T63 -> 14313.611 | H63: =IFERROR(VLOOKUP(C63,'Employees List'!$B$2:$I$991,7,0),"") -> 8387010000017745 | I63: =IFERROR(VLOOKUP(F63,'Employees List'!$E$1:$AE$991,6,0),"") -> 14000 | J63: =I63*70% -> 9800 | K63: =I63*30% -> 4200 | L63: =IFERROR(VLOOKUP(B63,'Employees List'!$A$2:$K$991,11,0),"") -> 31 | M63: =IFERROR(VLOOKUP(D63,'Daily Attendance 25-26'!$A$4:BP999,5,0),"") -> 30 | N63: =IFERROR(VLOOKUP(E63,'Daily Attendance 25-26'!$A$1:$BO$1741,5,0),"") -> 5 | O63: 450 | Q63: =I63/L63*M63 -> 13548.387 | R63: =I63/L63/8*1.5*N63 -> 423.3871 | S63: =Q63+R63-P63+O63 -> 14421.774 | T63: =U63*0.75% -> 108.16331 | U63: =Q63+R63+O63 -> 14421.774
A64: CPIEMP063 | B64: August | C64: PR 21 | D64: =B64&F64 -> AugustLIPAN | E64: =D64&$N$1 -> AugustLIPANOT Hours | F64: =IFERROR(VLOOKUP(C64,'Employees List'!$B$1:$I$999,4,0),"") -> LIPAN | G64: =S64-T64 -> 16209.485 | H64: =IFERROR(VLOOKUP(C64,'Employees List'!$B$2:$I$991,7,0),"") -> 8131010000018957 | I64: =IFERROR(VLOOKUP(F64,'Employees List'!$E$1:$AE$991,6,0),"") -> 13000 | J64: =I64*70% -> 9100 | K64: =I64*30% -> 3900 | L64: =IFERROR(VLOOKUP(B64,'Employees List'!$A$2:$K$991,11,0),"") -> 31 | M64: =IFERROR(VLOOKUP(D64,'Daily Attendance 25-26'!$A$4:BP999,5,0),"") -> 31 | N64: =IFERROR(VLOOKUP(E64,'Daily Attendance 25-26'!$A$1:$BO$1741,5,0),"") -> 95 | O64: 900 | P64: 5000 | Q64: =I64/L64*M64 -> 13000 | R64: =I64/L64/8*1.5*N64 -> 7469.7581 | S64: =Q64+R64-P64+O64 -> 16369.758 | T64: =U64*0.75% -> 160.27319 | U64: =Q64+R64+O64 -> 21369.758
A65: CPIEMP064 | B65: August | C65: PR 27 | D65: =B65&F65 -> AugustPARSHU BAGH | E65: =D65&$N$1 -> AugustPARSHU BAGHOT Hours | F65: =IFERROR(VLOOKUP(C65,'Employees List'!$B$1:$I$999,4,0),"") -> PARSHU BAGH | G65: =S65-T65 -> 2965.494 | H65: =IFERROR(VLOOKUP(C65,'Employees List'!$B$2:$I$991,7,0),"") -> 40653547928 | I65: =IFERROR(VLOOKUP(F65,'Employees List'!$E$1:$AE$991,6,0),"") -> 13000 | J65: =I65*70% -> 9100 | K65: =I65*30% -> 3900 | L65: =IFERROR(VLOOKUP(B65,'Employees List'!$A$2:$K$991,11,0),"") -> 31 | M65: =IFERROR(VLOOKUP(D65,'Daily Attendance 25-26'!$A$4:BP999,5,0),"") -> 4.5 | N65: =IFERROR(VLOOKUP(E65,'Daily Attendance 25-26'!$A$1:$BO$1741,5,0),"") -> 14 | Q65: =I65/L65*M65 -> 1887.0968 | R65: =I65/L65/8*1.5*N65 -> 1100.8065 | S65: =Q65+R65-P65+O65 -> 2987.9032 | T65: =U65*0.75% -> 22.409274 | U65: =Q65+R65+O65 -> 2987.9032
A66: CPIEMP065 | B66: November | C66: AC 01 | D66: =B66&F66 -> NovemberBHUVANESHWARAN.V | E66: =D66&$N$1 -> NovemberBHUVANESHWARAN.VOT Hours | F66: =IFERROR(VLOOKUP(C66,'Employees List'!$B$1:$I$999,4,0),"") -> BHUVANESHWARAN.V | G66: =S66-T66 -> 66900 | H66: =IFERROR(VLOOKUP(C66,'Employees List'!$B$2:$I$991,7,0),"") -> 500101011548924 | I66: =IFERROR(VLOOKUP(F66,'Employees List'!$E$1:$AE$991,6,0),"") -> 66000 | J66: =I66*70% -> 46200 | K66: =I66*30% -> 19800 | L66: =IFERROR(VLOOKUP(B66,'Employees List'!$A$2:$K$991,11,0),"") -> 30 | M66: =IFERROR(VLOOKUP(D66,'Daily Attendance 25-26'!$A$4:BP999,5,0),"") -> 30 | N66: =IFERROR(VLOOKUP(E66,'Daily Attendance 25-26'!$A$1:$BO$1741,5,0),"") -> 0 | O66: 900 | Q66: =I66/L66*M66 -> 66000 | R66: =I66/L66/8*1.5*N66 -> 0 | S66: =Q66+R66-P66+O66 -> 66900 | T66: 0 | U66: =Q66+R66+O66 -> 66900
A67: CPIEMP066 | B67: November | C67: AC 02 | D67: =B67&F67 -> NovemberTHIRIPURA SUNDARI.R | E67: =D67&$N$1 -> NovemberTHIRIPURA SUNDARI.ROT Hours | F67: =IFERROR(VLOOKUP(C67,'Employees List'!$B$1:$I$999,4,0),"") -> THIRIPURA SUNDARI.R | G67: =S67-T67 -> 22684.828 | H67: =IFERROR(VLOOKUP(C67,'Employees List'!$B$2:$I$991,7,0),"") -> 8131010000016977 | I67: =IFERROR(VLOOKUP(F67,'Employees List'!$E$1:$AE$991,6,0),"") -> 21000 | J67: =I67*70% -> 14700 | K67: =I67*30% -> 6300 | L67: =IFERROR(VLOOKUP(B67,'Employees List'!$A$2:$K$991,11,0),"") -> 30 | M67: =IFERROR(VLOOKUP(D67,'Daily Attendance 25-26'!$A$4:BP999,5,0),"") -> 30 | N67: =IFERROR(VLOOKUP(E67,'Daily Attendance 25-26'!$A$1:$BO$1741,5,0),"") -> 5 | O67: 1200 | Q67: =I67/L67*M67 -> 21000 | R67: =I67/L67/8*1.5*N67 -> 656.25 | S67: =Q67+R67-P67+O67 -> 22856.25 | T67: =U67*0.75% -> 171.42188 | U67: =Q67+R67+O67 -> 22856.25
A68: CPIEMP067 | B68: November | C68: PR 02 | D68: =B68&F68 -> NovemberGANESH | E68: =D68&$N$1 -> NovemberGANESHOT Hours | F68: =IFERROR(VLOOKUP(C68,'Employees List'!$B$1:$I$999,4,0),"") -> GANESH | G68: =S68-T68 -> 21139.156 | H68: =IFERROR(VLOOKUP(C68,'Employees List'!$B$2:$I$991,7,0),"") -> 8811010012054879 | I68: =IFERROR(VLOOKUP(F68,'Employees List'!$E$1:$AE$991,6,0),"") -> 18500 | J68: =I68*70% -> 12950 | K68: =I68*30% -> 5550 | L68: =IFERROR(VLOOKUP(B68,'Employees List'!$A$2:$K$991,11,0),"") -> 30 | M68: =IFERROR(VLOOKUP(D68,'Daily Attendance 25-26'!$A$4:BP999,5,0),"") -> 24 | N68: =IFERROR(VLOOKUP(E68,'Daily Attendance 25-26'!$A$1:$BO$1741,5,0),"") -> 68 | O68: 450 | P68: 1800 | Q68: =I68/L68*M68 -> 14800 | R68: =I68/L68/8*1.5*N68 -> 7862.5 | S68: =Q68+R68-P68+O68 -> 21312.5 | T68: =U68*0.75% -> 173.34375 | U68: =Q68+R68+O68 -> 23112.5
A69: CPIEMP068 | B69: November | C69: PR 01 | D69: =B69&F69 -> NovemberVASANTHA.E | E69: =D69&$N$1 -> NovemberVASANTHA.EOT Hours | F69: =IFERROR(VLOOKUP(C69,'Employees List'!$B$1:$I$999,4,0),"") -> VASANTHA.E | G69: =S69-T69 -> 18585.596 | H69: =IFERROR(VLOOKUP(C69,'Employees List'!$B$2:$I$991,7,0),"") -> 8131010000016959 | I69: =IFERROR(VLOOKUP(F69,'Employees List'!$E$1:$AE$991,6,0),"") -> 14500 | J69: =I69*70% -> 10150 | K69: =I69*30% -> 4350 | L69: =IFERROR(VLOOKUP(B69,'Employees List'!$A$2:$K$991,11,0),"") -> 30 | M69: =IFERROR(VLOOKUP(D69,'Daily Attendance 25-26'!$A$4:BP999,5,0),"") -> 29 | N69: =IFERROR(VLOOKUP(E69,'Daily Attendance 25-26'!$A$1:$BO$1741,5,0),"") -> 47 | O69: 450 | Q69: =I69/L69*M69 -> 14016.667 | R69: =I69/L69/8*1.5*N69 -> 4259.375 | S69: =Q69+R69-P69+O69 -> 18726.042 | T69: =U69*0.75% -> 140.44531 | U69: =Q69+R69+O69 -> 18726.042
A70: CPIEMP069 | B70: November | C70: PR 05 | D70: =B70&F70 -> NovemberSANJAY BAGARTTI.K | E70: =D70&$N$1 -> NovemberSANJAY BAGARTTI.KOT Hours | F70: =IFERROR(VLOOKUP(C70,'Employees List'!$B$1:$I$999,4,0),"") -> SANJAY BAGARTTI.K | G70: =S70-T70 -> 21171.266 | H70: =IFERROR(VLOOKUP(C70,'Employees List'!$B$2:$I$991,7,0),"") -> 8131010000021225 | I70: =IFERROR(VLOOKUP(F70,'Employees List'!$E$1:$AE$991,6,0),"") -> 13000 | J70: =I70*70% -> 9100 | K70: =I70*30% -> 3900 | L70: =IFERROR(VLOOKUP(B70,'Employees List'!$A$2:$K$991,11,0),"") -> 30 | M70: =IFERROR(VLOOKUP(D70,'Daily Attendance 25-26'!$A$4:BP999,5,0),"") -> 30 | N70: =IFERROR(VLOOKUP(E70,'Daily Attendance 25-26'!$A$1:$BO$1741,5,0),"") -> 97 | O70: 450 | Q70: =I70/L70*M70 -> 13000 | R70: =I70/L70/8*1.5*N70 -> 7881.25 | S70: =Q70+R70-P70+O70 -> 21331.25 | T70: =U70*0.75% -> 159.98438 | U70: =Q70+R70+O70 -> 21331.25
A71: CPIEMP070 | B71: November | C71: PR 07 | D71: =B71&F71 -> NovemberAMMU.S | E71: =D71&$N$1 -> NovemberAMMU.SOT Hours | F71: =IFERROR(VLOOKUP(C71,'Employees List'!$B$1:$I$999,4,0),"") -> AMMU.S | G71: =S71-T71 -> 12778.438 | H71: =IFERROR(VLOOKUP(C71,'Employees List'!$B$2:$I$991,7,0),"") -> 65801000040238 | I71: =IFERROR(VLOOKUP(F71,'Employees List'!$E$1:$AE$991,6,0),"") -> 10500 | J71: =I71*70% -> 7350 | K71: =I71*30% -> 3150 | L71: =IFERROR(VLOOKUP(B71,'Employees List'!$A$2:$K$991,11,0),"") -> 30 | M71: =IFERROR(VLOOKUP(D71,'Daily Attendance 25-26'!$A$4:BP999,5,0),"") -> 28 | N71: =IFERROR(VLOOKUP(E71,'Daily Attendance 25-26'!$A$1:$BO$1741,5,0),"") -> 40 | O71: 450 | Q71: =I71/L71*M71 -> 9800 | R71: =I71/L71/8*1.5*N71 -> 2625 | S71: =Q71+R71-P71+O71 -> 12875 | T71: =U71*0.75% -> 96.5625 | U71: =Q71+R71+O71 -> 12875
A72: CPIEMP071 | B72: November | C72: PR 08 | D72: =B72&F72 -> NovemberREVATHI.S | E72: =D72&$N$1 -> NovemberREVATHI.SOT Hours | F72: =IFERROR(VLOOKUP(C72,'Employees List'!$B$1:$I$999,4,0),"") -> REVATHI.S | G72: =S72-T72 -> 11126.461 | H72: =IFERROR(VLOOKUP(C72,'Employees List'!$B$2:$I$991,7,0),"") -> 8131010000016995 | I72: =IFERROR(VLOOKUP(F72,'Employees List'!$E$1:$AE$991,6,0),"") -> 10500 | J72: =I72*70% -> 7350 | K72: =I72*30% -> 3150 | L72: =IFERROR(VLOOKUP(B72,'Employees List'!$A$2:$K$991,11,0),"") -> 30 | M72: =IFERROR(VLOOKUP(D72,'Daily Attendance 25-26'!$A$4:BP999,5,0),"") -> 27 | N72: =IFERROR(VLOOKUP(E72,'Daily Attendance 25-26'!$A$1:$BO$1741,5,0),"") -> 43 | O72: 450 | P72: 1500 | Q72: =I72/L72*M72 -> 9450 | R72: =I72/L72/8*1.5*N72 -> 2821.875 | S72: =Q72+R72-P72+O72 -> 11221.875 | T72: =U72*0.75% -> 95.414062 | U72: =Q72+R72+O72 -> 12721.875
A73: CPIEMP072 | B73: November | C73: AC 03 | D73: =B73&F73 -> NovemberLEELAVATHI.M | E73: =D73&$N$1 -> NovemberLEELAVATHI.MOT Hours | F73: =IFERROR(VLOOKUP(C73,'Employees List'!$B$1:$I$999,4,0),"") -> LEELAVATHI.M | G73: =S73-T73 -> 18299.219 | H73: =IFERROR(VLOOKUP(C73,'Employees List'!$B$2:$I$991,7,0),"") -> 8387010000017745 | I73: =IFERROR(VLOOKUP(F73,'Employees List'!$E$1:$AE$991,6,0),"") -> 14000 | J73: =I73*70% -> 9800 | K73: =I73*30% -> 4200 | L73: =IFERROR(VLOOKUP(B73,'Employees List'!$A$2:$K$991,11,0),"") -> 30 | M73: =IFERROR(VLOOKUP(D73,'Daily Attendance 25-26'!$A$4:BP999,5,0),"") -> 30 | N73: =IFERROR(VLOOKUP(E73,'Daily Attendance 25-26'!$A$1:$BO$1741,5,0),"") -> 29 | O73: =900+1000 -> 1900 | Q73: =I73/L73*M73 -> 14000 | R73: =I73/L73/8*1.5*N73 -> 2537.5 | S73: =Q73+R73-P73+O73 -> 18437.5 | T73: =U73*0.75% -> 138.28125 | U73: =Q73+R73+O73 -> 18437.5
A74: CPIEMP073 | B74: December | C74: AC 01 | D74: =B74&F74 -> DecemberBHUVANESHWARAN.V | E74: =D74&$N$1 -> DecemberBHUVANESHWARAN.VOT Hours | F74: =IFERROR(VLOOKUP(C74,'Employees List'!$B$1:$I$999,4,0),"") -> BHUVANESHWARAN.V | G74: =S74-T74 -> 66900 | H74: =IFERROR(VLOOKUP(C74,'Employees List'!$B$2:$I$991,7,0),"") -> 500101011548924 | I74: =IFERROR(VLOOKUP(F74,'Employees List'!$E$1:$AE$991,6,0),"") -> 66000 | J74: =I74*70% -> 46200 | K74: =I74*30% -> 19800 | L74: =IFERROR(VLOOKUP(B74,'Employees List'!$A$2:$K$991,11,0),"") -> 31 | M74: =IFERROR(VLOOKUP(D74,'Daily Attendance 25-26'!$A$4:BP999,5,0),"") -> 31 | N74: =IFERROR(VLOOKUP(E74,'Daily Attendance 25-26'!$A$1:$BO$1741,5,0),"") -> 0 | O74: 900 | Q74: =I74/L74*M74 -> 66000 | R74: =I74/L74/8*1.5*N74 -> 0 | S74: =Q74+R74-P74+O74 -> 66900 | T74: 0 | U74: =Q74+R74+O74 -> 66900
A75: CPIEMP074 | B75: December | C75: AC 02 | D75: =B75&F75 -> DecemberTHIRIPURA SUNDARI.R | E75: =D75&$N$1 -> DecemberTHIRIPURA SUNDARI.ROT Hours | F75: =IFERROR(VLOOKUP(C75,'Employees List'!$B$1:$I$999,4,0),"") -> THIRIPURA SUNDARI.R | G75: =S75-T75 -> 22033.5 | H75: =IFERROR(VLOOKUP(C75,'Employees List'!$B$2:$I$991,7,0),"") -> 8131010000016977 | I75: =IFERROR(VLOOKUP(F75,'Employees List'!$E$1:$AE$991,6,0),"") -> 21000 | J75: =I75*70% -> 14700 | K75: =I75*30% -> 6300 | L75: =IFERROR(VLOOKUP(B75,'Employees List'!$A$2:$K$991,11,0),"") -> 31 | M75: =IFERROR(VLOOKUP(D75,'Daily Attendance 25-26'!$A$4:BP999,5,0),"") -> 31 | N75: =IFERROR(VLOOKUP(E75,'Daily Attendance 25-26'!$A$1:$BO$1741,5,0),"") -> 0 | O75: 1200 | Q75: =I75/L75*M75 -> 21000 | R75: =I75/L75/8*1.5*N75 -> 0 | S75: =Q75+R75-P75+O75 -> 22200 | T75: =U75*0.75% -> 166.5 | U75: =Q75+R75+O75 -> 22200
A76: CPIEMP075 | B76: December | C76: PR 02 | D76: =B76&F76 -> DecemberGANESH | E76: =D76&$N$1 -> DecemberGANESHOT Hours | F76: =IFERROR(VLOOKUP(C76,'Employees List'!$B$1:$I$999,4,0),"") -> GANESH | G76: =S76-T76 -> 16122.782 | H76: =IFERROR(VLOOKUP(C76,'Employees List'!$B$2:$I$991,7,0),"") -> 8811010012054879 | I76: =IFERROR(VLOOKUP(F76,'Employees List'!$E$1:$AE$991,6,0),"") -> 18500 | J76: =I76*70% -> 12950 | K76: =I76*30% -> 5550 | L76: =IFERROR(VLOOKUP(B76,'Employees List'!$A$2:$K$991,11,0),"") -> 31 | M76: =IFERROR(VLOOKUP(D76,'Daily Attendance 25-26'!$A$4:BP999,5,0),"") -> 26 | N76: =IFERROR(VLOOKUP(E76,'Daily Attendance 25-26'!$A$1:$BO$1741,5,0),"") -> 25 | O76: 450 | P76: 2500 | Q76: =I76/L76*M76 -> 15516.129 | R76: =I76/L76/8*1.5*N76 -> 2797.379 | S76: =Q76+R76-P76+O76 -> 16263.508 | T76: =U76*0.75% -> 140.72631 | U76: =Q76+R76+O76 -> 18763.508
A77: CPIEMP076 | B77: December | C77: PR 01 | D77: =B77&F77 -> DecemberVASANTHA.E | E77: =D77&$N$1 -> DecemberVASANTHA.EOT Hours | F77: =IFERROR(VLOOKUP(C77,'Employees List'!$B$1:$I$999,4,0),"") -> VASANTHA.E | G77: =S77-T77 -> 17942.439 | H77: =IFERROR(VLOOKUP(C77,'Employees List'!$B$2:$I$991,7,0),"") -> 8131010000016959 | I77: =IFERROR(VLOOKUP(F77,'Employees List'!$E$1:$AE$991,6,0),"") -> 14500 | J77: =I77*70% -> 10150 | K77: =I77*30% -> 4350 | L77: =IFERROR(VLOOKUP(B77,'Employees List'!$A$2:$K$991,11,0),"") -> 31 | M77: =IFERROR(VLOOKUP(D77,'Daily Attendance 25-26'!$A$4:BP999,5,0),"") -> 30 | N77: =IFERROR(VLOOKUP(E77,'Daily Attendance 25-26'!$A$1:$BO$1741,5,0),"") -> 41 | O77: 450 | Q77: =I77/L77*M77 -> 14032.258 | R77: =I77/L77/8*1.5*N77 -> 3595.7661 | S77: =Q77+R77-P77+O77 -> 18078.024 | T77: =U77*0.75% -> 135.58518 | U77: =Q77+R77+O77 -> 18078.024
A78: CPIEMP077 | B78: December | C78: PR 05 | D78: =B78&F78 -> DecemberSANJAY BAGARTTI.K | E78: =D78&$N$1 -> DecemberSANJAY BAGARTTI.KOT Hours | F78: =IFERROR(VLOOKUP(C78,'Employees List'!$B$1:$I$999,4,0),"") -> SANJAY BAGARTTI.K | G78: =S78-T78 -> 5539.7097 | H78: =IFERROR(VLOOKUP(C78,'Employees List'!$B$2:$I$991,7,0),"") -> 8131010000021225 | I78: =IFERROR(VLOOKUP(F78,'Employees List'!$E$1:$AE$991,6,0),"") -> 13000 | J78: =I78*70% -> 9100 | K78: =I78*30% -> 3900 | L78: =IFERROR(VLOOKUP(B78,'Employees List'!$A$2:$K$991,11,0),"") -> 31 | M78: =IFERROR(VLOOKUP(D78,'Daily Attendance 25-26'!$A$4:BP999,5,0),"") -> 19 | N78: =IFERROR(VLOOKUP(E78,'Daily Attendance 25-26'!$A$1:$BO$1741,5,0),"") -> 28 | O78: 450 | P78: 5000 | Q78: =I78/L78*M78 -> 7967.7419 | R78: =I78/L78/8*1.5*N78 -> 2201.6129 | S78: =Q78+R78-P78+O78 -> 5619.3548 | T78: =U78*0.75% -> 79.645161 | U78: =Q78+R78+O78 -> 10619.355
A79: CPIEMP078 | B79: December | C79: PR 07 | D79: =B79&F79 -> DecemberAMMU.S | E79: =D79&$N$1 -> DecemberAMMU.SOT Hours | F79: =IFERROR(VLOOKUP(C79,'Employees List'!$B$1:$I$999,4,0),"") -> AMMU.S | G79: =S79-T79 -> 12023.457 | H79: =IFERROR(VLOOKUP(C79,'Employees List'!$B$2:$I$991,7,0),"") -> 65801000040238 | I79: =IFERROR(VLOOKUP(F79,'Employees List'!$E$1:$AE$991,6,0),"") -> 10500 | J79: =I79*70% -> 7350 | K79: =I79*30% -> 3150 | L79: =IFERROR(VLOOKUP(B79,'Employees List'!$A$2:$K$991,11,0),"") -> 31 | M79: =IFERROR(VLOOKUP(D79,'Daily Attendance 25-26'!$A$4:BP999,5,0),"") -> 29 | N79: =IFERROR(VLOOKUP(E79,'Daily Attendance 25-26'!$A$1:$BO$1741,5,0),"") -> 29 | O79: 450 | Q79: =I79/L79*M79 -> 9822.5806 | R79: =I79/L79/8*1.5*N79 -> 1841.7339 | S79: =Q79+R79-P79+O79 -> 12114.315 | T79: =U79*0.75% -> 90.857359 | U79: =Q79+R79+O79 -> 12114.315
A80: CPIEMP079 | B80: December | C80: PR 08 | D80: =B80&F80 -> DecemberREVATHI.S | E80: =D80&$N$1 -> DecemberREVATHI.SOT Hours | F80: =IFERROR(VLOOKUP(C80,'Employees List'!$B$1:$I$999,4,0),"") -> REVATHI.S | G80: =S80-T80 -> 11107.499 | H80: =IFERROR(VLOOKUP(C80,'Employees List'!$B$2:$I$991,7,0),"") -> 8131010000016995 | I80: =IFERROR(VLOOKUP(F80,'Employees List'!$E$1:$AE$991,6,0),"") -> 10500 | J80: =I80*70% -> 7350 | K80: =I80*30% -> 3150 | L80: =IFERROR(VLOOKUP(B80,'Employees List'!$A$2:$K$991,11,0),"") -> 31 | M80: =IFERROR(VLOOKUP(D80,'Daily Attendance 25-26'!$A$4:BP999,5,0),"") -> 30 | N80: =IFERROR(VLOOKUP(E80,'Daily Attendance 25-26'!$A$1:$BO$1741,5,0),"") -> 25 | O80: 450 | P80: 1000 | Q80: =I80/L80*M80 -> 10161.29 | R80: =I80/L80/8*1.5*N80 -> 1587.7016 | S80: =Q80+R80-P80+O80 -> 11198.992 | T80: =U80*0.75% -> 91.49244 | U80: =Q80+R80+O80 -> 12198.992
A81: CPIEMP080 | B81: December | C81: AC 03 | D81: =B81&F81 -> DecemberLEELAVATHI.M | E81: =D81&$N$1 -> DecemberLEELAVATHI.MOT Hours | F81: =IFERROR(VLOOKUP(C81,'Employees List'!$B$1:$I$999,4,0),"") -> LEELAVATHI.M | G81: =S81-T81 -> 17099.014 | H81: =IFERROR(VLOOKUP(C81,'Employees List'!$B$2:$I$991,7,0),"") -> 8387010000017745 | I81: =IFERROR(VLOOKUP(F81,'Employees List'!$E$1:$AE$991,6,0),"") -> 14000 | J81: =I81*70% -> 9800 | K81: =I81*30% -> 4200 | L81: =IFERROR(VLOOKUP(B81,'Employees List'!$A$2:$K$991,11,0),"") -> 31 | M81: =IFERROR(VLOOKUP(D81,'Daily Attendance 25-26'!$A$4:BP999,5,0),"") -> 31 | N81: =IFERROR(VLOOKUP(E81,'Daily Attendance 25-26'!$A$1:$BO$1741,5,0),"") -> 21 | O81: 1450 | Q81: =I81/L81*M81 -> 14000 | R81: =I81/L81/8*1.5*N81 -> 1778.2258 | S81: =Q81+R81-P83+O81 -> 17228.226 | T81: =U81*0.75% -> 129.21169 | U81: =Q81+R81+O81 -> 17228.226
A82: CPIEMP081 | B82: December | C82: PR 24 | D82: =B82&F82 -> DecemberNILAMANI KISAN.B | E82: =D82&$N$1 -> DecemberNILAMANI KISAN.BOT Hours | F82: =IFERROR(VLOOKUP(C82,'Employees List'!$B$1:$I$999,4,0),"") -> NILAMANI KISAN.B | G82: =S82-T82 -> 10934.427 | H82: =IFERROR(VLOOKUP(C82,'Employees List'!$B$2:$I$991,7,0),"") -> 38254473147 | I82: =IFERROR(VLOOKUP(F82,'Employees List'!$E$1:$AE$991,6,0),"") -> 12000 | J82: =I82*70% -> 8400 | K82: =I82*30% -> 3600 | L82: =IFERROR(VLOOKUP(B82,'Employees List'!$A$2:$K$991,11,0),"") -> 31 | M82: =IFERROR(VLOOKUP(D82,'Daily Attendance 25-26'!$A$4:BP999,5,0),"") -> 27 | N82: =IFERROR(VLOOKUP(E82,'Daily Attendance 25-26'!$A$1:$BO$1741,5,0),"") -> 71 | O82: 450 | P82: 5000 | Q82: =I82/L82*M82 -> 10451.613 | R82: =I82/L82/8*1.5*N82 -> 5153.2258 | S82: =Q82+R82-P82+O82 -> 11054.839 | T82: =U82*0.75% -> 120.41129 | U82: =Q82+R82+O82 -> 16054.839
A83: CPIEMP082 | B83: January | C83: AC 01 | D83: =B83&F83 -> JanuaryBHUVANESHWARAN.V | E83: =D83&$N$1 -> JanuaryBHUVANESHWARAN.VOT Hours | F83: =IFERROR(VLOOKUP(C83,'Employees List'!$B$1:$I$999,4,0),"") -> BHUVANESHWARAN.V | G83: =S83-T83 -> 66900 | H83: =IFERROR(VLOOKUP(C83,'Employees List'!$B$2:$I$991,7,0),"") -> 500101011548924 | I83: =IFERROR(VLOOKUP(F83,'Employees List'!$E$1:$AE$991,6,0),"") -> 66000 | J83: =I83*70% -> 46200 | K83: =I83*30% -> 19800 | L83: =IFERROR(VLOOKUP(B83,'Employees List'!$A$2:$K$991,11,0),"") -> 31 | M83: =IFERROR(VLOOKUP(D83,'Daily Attendance 25-26'!$A$4:BP999,5,0),"") -> 31 | N83: =IFERROR(VLOOKUP(E83,'Daily Attendance 25-26'!$A$1:$BO$1741,5,0),"") -> 0 | O83: 900 | Q83: =I83/L83*M83 -> 66000 | R83: =I83/L83/8*1.5*N83 -> 0 | S83: =Q83+R83-P83+O83 -> 66900 | T83: =0 -> 0 | U83: =Q83+R83+O83 -> 66900
A84: CPIEMP083 | B84: January | C84: AC 02 | D84: =B84&F84 -> JanuaryTHIRIPURA SUNDARI.R | E84: =D84&$N$1 -> JanuaryTHIRIPURA SUNDARI.ROT Hours | F84: =IFERROR(VLOOKUP(C84,'Employees List'!$B$1:$I$999,4,0),"") -> THIRIPURA SUNDARI.R | G84: =S84-T84 -> 22033.5 | H84: =IFERROR(VLOOKUP(C84,'Employees List'!$B$2:$I$991,7,0),"") -> 8131010000016977 | I84: =IFERROR(VLOOKUP(F84,'Employees List'!$E$1:$AE$991,6,0),"") -> 21000 | J84: =I84*70% -> 14700 | K84: =I84*30% -> 6300 | L84: =IFERROR(VLOOKUP(B84,'Employees List'!$A$2:$K$991,11,0),"") -> 31 | M84: =IFERROR(VLOOKUP(D84,'Daily Attendance 25-26'!$A$4:BP999,5,0),"") -> 31 | N84: =IFERROR(VLOOKUP(E84,'Daily Attendance 25-26'!$A$1:$BO$1741,5,0),"") -> 0 | O84: 1200 | Q84: =I84/L84*M84 -> 21000 | R84: =I84/L84/8*1.5*N84 -> 0 | S84: =Q84+R84-P84+O84 -> 22200 | T84: =U84*0.75% -> 166.5 | U84: =Q84+R84+O84 -> 22200
A85: CPIEMP084 | B85: January | C85: PR 02 | D85: =B85&F85 -> JanuaryGANESH | E85: =D85&$N$1 -> JanuaryGANESHOT Hours | F85: =IFERROR(VLOOKUP(C85,'Employees List'!$B$1:$I$999,4,0),"") -> GANESH | G85: =S85-T85 -> 5587.2525 | H85: =IFERROR(VLOOKUP(C85,'Employees List'!$B$2:$I$991,7,0),"") -> 8811010012054879 | I85: =IFERROR(VLOOKUP(F85,'Employees List'!$E$1:$AE$991,6,0),"") -> 18500 | J85: =I85*70% -> 12950 | K85: =I85*30% -> 5550 | L85: =IFERROR(VLOOKUP(B85,'Employees List'!$A$2:$K$991,11,0),"") -> 31 | M85: =IFERROR(VLOOKUP(D85,'Daily Attendance 25-26'!$A$4:BP999,5,0),"") -> 25 | N85: =IFERROR(VLOOKUP(E85,'Daily Attendance 25-26'!$A$1:$BO$1741,5,0),"") -> 3 | O85: 450 | P85: 10000 | Q85: =I85/L85*M85 -> 14919.355 | R85: =I85/L85/8*1.5*N85 -> 335.68548 | S85: =Q85+R85-P85+O85 -> 5705.0403 | T85: =U85*0.75% -> 117.7878 | U85: =Q85+R85+O85 -> 15705.04
A86: CPIEMP085 | B86: January | C86: PR 01 | D86: =B86&F86 -> JanuaryVASANTHA.E | E86: =D86&$N$1 -> JanuaryVASANTHA.EOT Hours | F86: =IFERROR(VLOOKUP(C86,'Employees List'!$B$1:$I$999,4,0),"") -> VASANTHA.E | G86: =S86-T86 -> 14721.817 | H86: =IFERROR(VLOOKUP(C86,'Employees List'!$B$2:$I$991,7,0),"") -> 8131010000016959 | I86: =IFERROR(VLOOKUP(F86,'Employees List'!$E$1:$AE$991,6,0),"") -> 14500 | J86: =I86*70% -> 10150 | K86: =I86*30% -> 4350 | L86: =IFERROR(VLOOKUP(B86,'Employees List'!$A$2:$K$991,11,0),"") -> 31 | M86: =IFERROR(VLOOKUP(D86,'Daily Attendance 25-26'!$A$4:BP999,5,0),"") -> 28.5 | N86: =IFERROR(VLOOKUP(E86,'Daily Attendance 25-26'!$A$1:$BO$1741,5,0),"") -> 12 | O86: 450 | Q86: =I86/L86*M86 -> 13330.645 | R86: =I86/L86/8*1.5*N86 -> 1052.4194 | S86: =Q86+R86-P86+O86 -> 14833.065 | T86: =U86*0.75% -> 111.24798 | U86: =Q86+R86+O86 -> 14833.065
A87: CPIEMP086 | B87: January | C87: PR 05 | D87: =B87&F87 -> JanuarySANJAY BAGARTTI.K | E87: =D87&$N$1 -> JanuarySANJAY BAGARTTI.KOT Hours | F87: =IFERROR(VLOOKUP(C87,'Employees List'!$B$1:$I$999,4,0),"") -> SANJAY BAGARTTI.K | G87: =S87-T87 -> 11814.352 | H87: =IFERROR(VLOOKUP(C87,'Employees List'!$B$2:$I$991,7,0),"") -> 8131010000021225 | I87: =IFERROR(VLOOKUP(F87,'Employees List'!$E$1:$AE$991,6,0),"") -> 13000 | J87: =I87*70% -> 9100 | K87: =I87*30% -> 3900 | L87: =IFERROR(VLOOKUP(B87,'Employees List'!$A$2:$K$991,11,0),"") -> 31 | M87: =IFERROR(VLOOKUP(D87,'Daily Attendance 25-26'!$A$4:BP999,5,0),"") -> 26 | N87: =IFERROR(VLOOKUP(E87,'Daily Attendance 25-26'!$A$1:$BO$1741,5,0),"") -> 7 | O87: 450 | Q87: =I87/L87*M87 -> 10903.226 | R87: =I87/L87/8*1.5*N87 -> 550.40323 | S87: =Q87+R87-P87+O87 -> 11903.629 | T87: =U87*0.75% -> 89.277218 | U87: =Q87+R87+O87 -> 11903.629
A88: CPIEMP087 | B88: January | C88: PR 07 | D88: =B88&F88 -> JanuaryAMMU.S | E88: =D88&$N$1 -> JanuaryAMMU.SOT Hours | F88: =IFERROR(VLOOKUP(C88,'Employees List'!$B$1:$I$999,4,0),"") -> AMMU.S | G88: =S88-T88 -> 10111.494 | H88: =IFERROR(VLOOKUP(C88,'Employees List'!$B$2:$I$991,7,0),"") -> 65801000040238 | I88: =IFERROR(VLOOKUP(F88,'Employees List'!$E$1:$AE$991,6,0),"") -> 10500 | J88: =I88*70% -> 7350 | K88: =I88*30% -> 3150 | L88: =IFERROR(VLOOKUP(B88,'Employees List'!$A$2:$K$991,11,0),"") -> 31 | M88: =IFERROR(VLOOKUP(D88,'Daily Attendance 25-26'!$A$4:BP999,5,0),"") -> 28 | N88: =IFERROR(VLOOKUP(E88,'Daily Attendance 25-26'!$A$1:$BO$1741,5,0),"") -> 4 | O88: 450 | Q88: =I88/L88*M88 -> 9483.871 | R88: =I88/L88/8*1.5*N88 -> 254.03226 | S88: =Q88+R88-P88+O88 -> 10187.903 | T88: =U88*0.75% -> 76.409274 | U88: =Q88+R88+O88 -> 10187.903
A89: CPIEMP088 | B89: January | C89: PR 08 | D89: =B89&F89 -> JanuaryREVATHI.S | E89: =D89&$N$1 -> JanuaryREVATHI.SOT Hours | F89: =IFERROR(VLOOKUP(C89,'Employees List'!$B$1:$I$999,4,0),"") -> REVATHI.S | G89: =S89-T89 -> 9250.06 | H89: =IFERROR(VLOOKUP(C89,'Employees List'!$B$2:$I$991,7,0),"") -> 8131010000016995 | I89: =IFERROR(VLOOKUP(F89,'Employees List'!$E$1:$AE$991,6,0),"") -> 10500 | J89: =I89*70% -> 7350 | K89: =I89*30% -> 3150 | L89: =IFERROR(VLOOKUP(B89,'Employees List'!$A$2:$K$991,11,0),"") -> 31 | M89: =IFERROR(VLOOKUP(D89,'Daily Attendance 25-26'!$A$4:BP999,5,0),"") -> 26 | N89: =IFERROR(VLOOKUP(E89,'Daily Attendance 25-26'!$A$1:$BO$1741,5,0),"") -> 1 | O89: 450 | Q89: =I89/L89*M89 -> 8806.4516 | R89: =I89/L89/8*1.5*N89 -> 63.508065 | S89: =Q89+R89-P89+O89 -> 9319.9597 | T89: =U89*0.75% -> 69.899698 | U89: =Q89+R89+O89 -> 9319.9597
A90: CPIEMP089 | B90: January | C90: AC 03 | D90: =B90&F90 -> JanuaryLEELAVATHI.M | E90: =D90&$N$1 -> JanuaryLEELAVATHI.MOT Hours | F90: =IFERROR(VLOOKUP(C90,'Employees List'!$B$1:$I$999,4,0),"") -> LEELAVATHI.M | G90: =S90-T90 -> 16032.877 | H90: =IFERROR(VLOOKUP(C90,'Employees List'!$B$2:$I$991,7,0),"") -> 8387010000017745 | I90: =IFERROR(VLOOKUP(F90,'Employees List'!$E$1:$AE$991,6,0),"") -> 14000 | J90: =I90*70% -> 9800 | K90: =I90*30% -> 4200 | L90: =IFERROR(VLOOKUP(B90,'Employees List'!$A$2:$K$991,11,0),"") -> 31 | M90: =IFERROR(VLOOKUP(D90,'Daily Attendance 25-26'!$A$4:BP999,5,0),"") -> 31 | N90: =IFERROR(VLOOKUP(E90,'Daily Attendance 25-26'!$A$1:$BO$1741,5,0),"") -> 3 | O90: 1900 | Q90: =I90/L90*M90 -> 14000 | R90: =I90/L90/8*1.5*N90 -> 254.03226 | S90: =Q90+R90-P90+O90 -> 16154.032 | T90: =U90*0.75% -> 121.15524 | U90: =Q90+R90+O90 -> 16154.032
A91: CPIEMP090 | B91: January | C91: PR 03 | D91: =B91&F91 -> JanuaryADHIKARI BALIA.A | E91: =D91&$N$1 -> JanuaryADHIKARI BALIA.AOT Hours | F91: =IFERROR(VLOOKUP(C91,'Employees List'!$B$1:$I$999,4,0),"") -> ADHIKARI BALIA.A | G91: =S91-T91 -> 6906.9022 | H91: =IFERROR(VLOOKUP(C91,'Employees List'!$B$2:$I$991,7,0),"") -> 8131010000018948 | I91: =IFERROR(VLOOKUP(F91,'Employees List'!$E$1:$AE$991,6,0),"") -> 13000 | J91: =I91*70% -> 9100 | K91: =I91*30% -> 3900 | L91: =IFERROR(VLOOKUP(B91,'Employees List'!$A$2:$K$991,11,0),"") -> 31 | M91: =IFERROR(VLOOKUP(D91,'Daily Attendance 25-26'!$A$4:BP999,5,0),"") -> 26 | N91: =IFERROR(VLOOKUP(E91,'Daily Attendance 25-26'!$A$1:$BO$1741,5,0),"") -> 21 | O91: 450 | P91: 6000 | Q91: =I91/L91*M91 -> 10903.226 | R91: =I91/L91/8*1.5*N91 -> 1651.2097 | S91: =Q91+R91-P91+O91 -> 7004.4355 | T91: =U91*0.75% -> 97.533266 | U91: =Q91+R91+O91 -> 13004.435
A92: CPIEMP091 | B92: January | C92: PR 27 | D92: =B92&F92 -> JanuaryPARSHU BAGH | E92: =D92&$N$1 -> JanuaryPARSHU BAGHOT Hours | F92: =IFERROR(VLOOKUP(C92,'Employees List'!$B$1:$I$999,4,0),"") -> PARSHU BAGH | G92: =S92-T92 -> 10204.548 | H92: =IFERROR(VLOOKUP(C92,'Employees List'!$B$2:$I$991,7,0),"") -> 40653547928 | I92: =IFERROR(VLOOKUP(F92,'Employees List'!$E$1:$AE$991,6,0),"") -> 13000 | J92: =I92*70% -> 9100 | K92: =I92*30% -> 3900 | L92: =IFERROR(VLOOKUP(B92,'Employees List'!$A$2:$K$991,11,0),"") -> 31 | M92: =IFERROR(VLOOKUP(D92,'Daily Attendance 25-26'!$A$4:BP999,5,0),"") -> 26 | N92: =IFERROR(VLOOKUP(E92,'Daily Attendance 25-26'!$A$1:$BO$1741,5,0),"") -> 12 | O92: 450 | P92: 2000 | Q92: =I92/L92*M92 -> 10903.226 | R92: =I92/L92/8*1.5*N92 -> 943.54839 | S92: =Q92+R92-P92+O92 -> 10296.774 | T92: =U92*0.75% -> 92.225806 | U92: =Q92+R92+O92 -> 12296.774
A93: CPIEMP092 | B93: January | C93: PR 24 | D93: =B93&F93 -> JanuaryNILAMANI KISAN.B | E93: =D93&$N$1 -> JanuaryNILAMANI KISAN.BOT Hours | F93: =IFERROR(VLOOKUP(C93,'Employees List'!$B$1:$I$999,4,0),"") -> NILAMANI KISAN.B | G93: =S93-T93 -> 4418.2258 | H93: =IFERROR(VLOOKUP(C93,'Employees List'!$B$2:$I$991,7,0),"") -> 38254473147 | I93: =IFERROR(VLOOKUP(F93,'Employees List'!$E$1:$AE$991,6,0),"") -> 12000 | J93: =I93*70% -> 8400 | K93: =I93*30% -> 3600 | L93: =IFERROR(VLOOKUP(B93,'Employees List'!$A$2:$K$991,11,0),"") -> 31 | M93: =IFERROR(VLOOKUP(D93,'Daily Attendance 25-26'!$A$4:BP999,5,0),"") -> 10 | N93: =IFERROR(VLOOKUP(E93,'Daily Attendance 25-26'!$A$1:$BO$1741,5,0),"") -> 8 | Q93: =I93/L93*M93 -> 3870.9677 | R93: =I93/L93/8*1.5*N93 -> 580.64516 | S93: =Q93+R93-P93+O93 -> 4451.6129 | T93: =U93*0.75% -> 33.387097 | U93: =Q93+R93+O93 -> 4451.6129
A94: CPIEMP093 | B94: February | C94: AC 01 | D94: =B94&F94 -> FebruaryBHUVANESHWARAN.V | E94: =D94&$N$1 -> FebruaryBHUVANESHWARAN.VOT Hours | F94: =IFERROR(VLOOKUP(C94,'Employees List'!$B$1:$I$999,4,0),"") -> BHUVANESHWARAN.V | G94: =S94-T94 -> 66900 | H94: =IFERROR(VLOOKUP(C94,'Employees List'!$B$2:$I$991,7,0),"") -> 500101011548924 | I94: =IFERROR(VLOOKUP(F94,'Employees List'!$E$1:$AE$991,6,0),"") -> 66000 | J94: =I94*70% -> 46200 | K94: =I94*30% -> 19800 | L94: =IFERROR(VLOOKUP(B94,'Employees List'!$A$2:$K$991,11,0),"") -> 28 | M94: =IFERROR(VLOOKUP(D94,'Daily Attendance 25-26'!$A$4:BP999,5,0),"") -> 28 | N94: =IFERROR(VLOOKUP(E94,'Daily Attendance 25-26'!$A$1:$BO$1741,5,0),"") -> 0 | O94: 900 | Q94: =I94/L94*M94 -> 66000 | R94: =I94/L94/8*1.5*N94 -> 0 | S94: =Q94+R94-P94+O94 -> 66900 | T94: 0 | U94: =Q94+R94+O94 -> 66900
A95: CPIEMP094 | B95: February | C95: AC 02 | D95: =B95&F95 -> FebruaryTHIRIPURA SUNDARI.R | E95: =D95&$N$1 -> FebruaryTHIRIPURA SUNDARI.ROT Hours | F95: =IFERROR(VLOOKUP(C95,'Employees List'!$B$1:$I$999,4,0),"") -> THIRIPURA SUNDARI.R | G95: =S95-T95 -> 22033.5 | H95: =IFERROR(VLOOKUP(C95,'Employees List'!$B$2:$I$991,7,0),"") -> 8131010000016977 | I95: =IFERROR(VLOOKUP(F95,'Employees List'!$E$1:$AE$991,6,0),"") -> 21000 | J95: =I95*70% -> 14700 | K95: =I95*30% -> 6300 | L95: =IFERROR(VLOOKUP(B95,'Employees List'!$A$2:$K$991,11,0),"") -> 28 | M95: =IFERROR(VLOOKUP(D95,'Daily Attendance 25-26'!$A$4:BP999,5,0),"") -> 28 | N95: =IFERROR(VLOOKUP(E95,'Daily Attendance 25-26'!$A$1:$BO$1741,5,0),"") -> 0 | O95: 1200 | Q95: =I95/L95*M95 -> 21000 | R95: =I95/L95/8*1.5*N95 -> 0 | S95: =Q95+R95-P95+O95 -> 22200 | T95: =U95*0.75% -> 166.5 | U95: =Q95+R95+O95 -> 22200
A96: CPIEMP095 | B96: February | C96: PR 02 | D96: =B96&F96 -> FebruaryGANESH | E96: =D96&$N$1 -> FebruaryGANESHOT Hours | F96: =IFERROR(VLOOKUP(C96,'Employees List'!$B$1:$I$999,4,0),"") -> GANESH | G96: =S96-T96 -> 14270.94 | H96: =IFERROR(VLOOKUP(C96,'Employees List'!$B$2:$I$991,7,0),"") -> 8811010012054879 | I96: =IFERROR(VLOOKUP(F96,'Employees List'!$E$1:$AE$991,6,0),"") -> 18500 | J96: =I96*70% -> 12950 | K96: =I96*30% -> 5550 | L96: =IFERROR(VLOOKUP(B96,'Employees List'!$A$2:$K$991,11,0),"") -> 28 | M96: =IFERROR(VLOOKUP(D96,'Daily Attendance 25-26'!$A$4:BP999,5,0),"") -> 25 | N96: =IFERROR(VLOOKUP(E96,'Daily Attendance 25-26'!$A$1:$BO$1741,5,0),"") -> 3.5 | O96: 450 | P96: 3000 | Q96: =I96/L96*M96 -> 16517.857 | R96: =I96/L96/8*1.5*N96 -> 433.59375 | S96: =Q96+R96-P96+O96 -> 14401.451 | T96: =U96*0.75% -> 130.51088 | U96: =Q96+R96+O96 -> 17401.451
A97: CPIEMP096 | B97: February | C97: PR 01 | D97: =B97&F97 -> FebruaryVASANTHA.E | E97: =D97&$N$1 -> FebruaryVASANTHA.EOT Hours | F97: =IFERROR(VLOOKUP(C97,'Employees List'!$B$1:$I$999,4,0),"") -> VASANTHA.E | G97: =S97-T97 -> 13312.017 | H97: =IFERROR(VLOOKUP(C97,'Employees List'!$B$2:$I$991,7,0),"") -> 8131010000016959 | I97: =IFERROR(VLOOKUP(F97,'Employees List'!$E$1:$AE$991,6,0),"") -> 14500 | J97: =I97*70% -> 10150 | K97: =I97*30% -> 4350 | L97: =IFERROR(VLOOKUP(B97,'Employees List'!$A$2:$K$991,11,0),"") -> 28 | M97: =IFERROR(VLOOKUP(D97,'Daily Attendance 25-26'!$A$4:BP999,5,0),"") -> 22.5 | N97: =IFERROR(VLOOKUP(E97,'Daily Attendance 25-26'!$A$1:$BO$1741,5,0),"") -> 13.5 | O97: 450 | Q97: =I97/L97*M97 -> 11651.786 | R97: =I97/L97/8*1.5*N97 -> 1310.8259 | S97: =Q97+R97-P97+O97 -> 13412.612 | T97: =U97*0.75% -> 100.59459 | U97: =Q97+R97+O97 -> 13412.612
A98: CPIEMP097 | B98: February | C98: PR 05 | D98: =B98&F98 -> FebruarySANJAY BAGARTTI.K | E98: =D98&$N$1 -> FebruarySANJAY BAGARTTI.KOT Hours | F98: =IFERROR(VLOOKUP(C98,'Employees List'!$B$1:$I$999,4,0),"") -> SANJAY BAGARTTI.K | G98: =S98-T98 -> 16258.169 | H98: =IFERROR(VLOOKUP(C98,'Employees List'!$B$2:$I$991,7,0),"") -> 8131010000021225 | I98: =IFERROR(VLOOKUP(F98,'Employees List'!$E$1:$AE$991,6,0),"") -> 13000 | J98: =I98*70% -> 9100 | K98: =I98*30% -> 3900 | L98: =IFERROR(VLOOKUP(B98,'Employees List'!$A$2:$K$991,11,0),"") -> 28 | M98: =IFERROR(VLOOKUP(D98,'Daily Attendance 25-26'!$A$4:BP999,5,0),"") -> 28 | N98: =IFERROR(VLOOKUP(E98,'Daily Attendance 25-26'!$A$1:$BO$1741,5,0),"") -> 28.5 | O98: 900 | Q98: =I98/L98*M98 -> 13000 | R98: =I98/L98/8*1.5*N98 -> 2481.0268 | S98: =Q98+R98-P98+O98 -> 16381.027 | T98: =U98*0.75% -> 122.8577 | U98: =Q98+R98+O98 -> 16381.027
A99: CPIEMP098 | B99: February | C99: PR 07 | D99: =B99&F99 -> FebruaryAMMU.S | E99: =D99&$N$1 -> FebruaryAMMU.SOT Hours | F99: =IFERROR(VLOOKUP(C99,'Employees List'!$B$1:$I$999,4,0),"") -> AMMU.S | G99: =S99-T99 -> 11454.07 | H99: =IFERROR(VLOOKUP(C99,'Employees List'!$B$2:$I$991,7,0),"") -> 65801000040238 | I99: =IFERROR(VLOOKUP(F99,'Employees List'!$E$1:$AE$991,6,0),"") -> 10500 | J99: =I99*70% -> 7350 | K99: =I99*30% -> 3150 | L99: =IFERROR(VLOOKUP(B99,'Employees List'!$A$2:$K$991,11,0),"") -> 28 | M99: =IFERROR(VLOOKUP(D99,'Daily Attendance 25-26'!$A$4:BP999,5,0),"") -> 28 | N99: =IFERROR(VLOOKUP(E99,'Daily Attendance 25-26'!$A$1:$BO$1741,5,0),"") -> 2 | O99: 900 | Q99: =I99/L99*M99 -> 10500 | R99: =I99/L99/8*1.5*N99 -> 140.625 | S99: =Q99+R99-P99+O99 -> 11540.625 | T99: =U99*0.75% -> 86.554688 | U99: =Q99+R99+O99 -> 11540.625
A100: CPIEMP099 | B100: February | C100: PR 08 | D100: =B100&F100 -> FebruaryREVATHI.S | E100: =D100&$N$1 -> FebruaryREVATHI.SOT Hours | F100: =IFERROR(VLOOKUP(C100,'Employees List'!$B$1:$I$999,4,0),"") -> REVATHI.S | G100: =S100-T100 -> 9590.8828 | H100: =IFERROR(VLOOKUP(C100,'Employees List'!$B$2:$I$991,7,0),"") -> 8131010000016995 | I100: =IFERROR(VLOOKUP(F100,'Employees List'!$E$1:$AE$991,6,0),"") -> 10500 | J100: =I100*70% -> 7350 | K100: =I100*30% -> 3150 | L100: =IFERROR(VLOOKUP(B100,'Employees List'!$A$2:$K$991,11,0),"") -> 28 | M100: =IFERROR(VLOOKUP(D100,'Daily Attendance 25-26'!$A$4:BP999,5,0),"") -> 25 | N100: =IFERROR(VLOOKUP(E100,'Daily Attendance 25-26'!$A$1:$BO$1741,5,0),"") -> 2 | O100: 450 | P100: 300 | Q100: =I100/L100*M100 -> 9375 | R100: =I100/L100/8*1.5*N100 -> 140.625 | S100: =Q100+R100-P100+O100 -> 9665.625 | T100: =U100*0.75% -> 74.742188 | U100: =Q100+R100+O100 -> 9965.625
...

Sheet Salary Transaction Details
A1: Salary Slip No | B1: Month | C1: Employee Code | D1: Name | E1: Account Number | F1: Bank Name | G1: NetPay | H1: Status | I1: Link
A2: CPIEMP001 | B2: =IFERROR(VLOOKUP(A2,'Salary Calculation'!A2:F999,2,0),"") -> April | C2: =IFERROR(VLOOKUP(A2,'Salary Calculation'!$A$2:$T$999,3,0),"") -> AC 01 | D2: =IFERROR(VLOOKUP(A2,'Salary Calculation'!$A$2:$T$999,6,0),"") -> BHUVANESHWARAN.V | E2: =IFERROR(VLOOKUP(A2,'Salary Calculation'!$A$2:$T$999,8,0),"") -> 500101011548924 | F2: =IFERROR(VLOOKUP(C2,'Employees List'!$B$2:H999,6,0),"") -> CUB | G2: =IFERROR(VLOOKUP(A2,'Salary Calculation'!$A$2:$T$999,7,0),"") -> 66900 | H2: PAID | I2: April
A3: CPIEMP002 | B3: =IFERROR(VLOOKUP(A3,'Salary Calculation'!A3:F1000,2,0),"") -> April | C3: =IFERROR(VLOOKUP(A3,'Salary Calculation'!$A$2:$T$999,3,0),"") -> AC 02 | D3: =IFERROR(VLOOKUP(A3,'Salary Calculation'!$A$2:$T$999,6,0),"") -> THIRIPURA SUNDARI.R | E3: =IFERROR(VLOOKUP(A3,'Salary Calculation'!$A$2:$T$999,8,0),"") -> 8131010000016977 | F3: =IFERROR(VLOOKUP(C3,'Employees List'!$B$2:H999,6,0),"") -> DBS | G3: =IFERROR(VLOOKUP(A3,'Salary Calculation'!$A$2:$T$999,7,0),"") -> 23075.625 | H3: PAID | I3: April
A4: CPIEMP003 | B4: =IFERROR(VLOOKUP(A4,'Salary Calculation'!A4:F1001,2,0),"") -> April | C4: =IFERROR(VLOOKUP(A4,'Salary Calculation'!$A$2:$T$999,3,0),"") -> PR 02 | D4: =IFERROR(VLOOKUP(A4,'Salary Calculation'!$A$2:$T$999,6,0),"") -> GANESH | E4: =IFERROR(VLOOKUP(A4,'Salary Calculation'!$A$2:$T$999,8,0),"") -> 8811010012054879 | F4: =IFERROR(VLOOKUP(C4,'Employees List'!$B$2:H999,6,0),"") -> DBS | G4: =IFERROR(VLOOKUP(A4,'Salary Calculation'!$A$2:$T$999,7,0),"") -> 13436.214 | H4: PAID | I4: April
A5: CPIEMP004 | B5: =IFERROR(VLOOKUP(A5,'Salary Calculation'!A5:F1002,2,0),"") -> April | C5: =IFERROR(VLOOKUP(A5,'Salary Calculation'!$A$2:$T$999,3,0),"") -> DR 01 | D5: =IFERROR(VLOOKUP(A5,'Salary Calculation'!$A$2:$T$999,6,0),"") -> ILAMATHIVANAN.S | E5: =IFERROR(VLOOKUP(A5,'Salary Calculation'!$A$2:$T$999,8,0),"") -> 8131010000016986 | F5: =IFERROR(VLOOKUP(C5,'Employees List'!$B$2:H999,6,0),"") -> DBS | G5: =IFERROR(VLOOKUP(A5,'Salary Calculation'!$A$2:$T$999,7,0),"") -> 16766.766 | H5: PAID | I5: April
A6: CPIEMP005 | B6: =IFERROR(VLOOKUP(A6,'Salary Calculation'!A6:F1003,2,0),"") -> April | C6: =IFERROR(VLOOKUP(A6,'Salary Calculation'!$A$2:$T$999,3,0),"") -> PR 07 | D6: =IFERROR(VLOOKUP(A6,'Salary Calculation'!$A$2:$T$999,6,0),"") -> AMMU.S | E6: =IFERROR(VLOOKUP(A6,'Salary Calculation'!$A$2:$T$999,8,0),"") -> 65801000040238 | F6: =IFERROR(VLOOKUP(C6,'Employees List'!$B$2:H999,6,0),"") -> IOB | G6: =IFERROR(VLOOKUP(A6,'Salary Calculation'!$A$2:$T$999,7,0),"") -> 12030.961 | H6: PAID | I6: April
A7: CPIEMP006 | B7: =IFERROR(VLOOKUP(A7,'Salary Calculation'!A7:F1004,2,0),"") -> April | C7: =IFERROR(VLOOKUP(A7,'Salary Calculation'!$A$2:$T$999,3,0),"") -> PR 08 | D7: =IFERROR(VLOOKUP(A7,'Salary Calculation'!$A$2:$T$999,6,0),"") -> REVATHI.S | E7: =IFERROR(VLOOKUP(A7,'Salary Calculation'!$A$2:$T$999,8,0),"") -> 8131010000016995 | F7: =IFERROR(VLOOKUP(C7,'Employees List'!$B$2:H999,6,0),"") -> DBS | G7: =IFERROR(VLOOKUP(A7,'Salary Calculation'!$A$2:$T$999,7,0),"") -> 9606.6953 | H7: PAID | I7: April
A8: CPIEMP007 | B8: =IFERROR(VLOOKUP(A8,'Salary Calculation'!A8:F1005,2,0),"") -> April | C8: =IFERROR(VLOOKUP(A8,'Salary Calculation'!$A$2:$T$999,3,0),"") -> AC 03 | D8: =IFERROR(VLOOKUP(A8,'Salary Calculation'!$A$2:$T$999,6,0),"") -> LEELAVATHI.M | E8: =IFERROR(VLOOKUP(A8,'Salary Calculation'!$A$2:$T$999,8,0),"") -> 8387010000017745 | F8: =IFERROR(VLOOKUP(C8,'Employees List'!$B$2:H999,6,0),"") -> DBS | G8: =IFERROR(VLOOKUP(A8,'Salary Calculation'!$A$2:$T$999,7,0),"") -> 15048.781 | H8: PAID | I8: April
A9: CPIEMP008 | B9: =IFERROR(VLOOKUP(A9,'Salary Calculation'!A9:F1006,2,0),"") -> April | C9: =IFERROR(VLOOKUP(A9,'Salary Calculation'!$A$2:$T$999,3,0),"") -> PR 27 | D9: =IFERROR(VLOOKUP(A9,'Salary Calculation'!$A$2:$T$999,6,0),"") -> PARSHU BAGH | E9: =IFERROR(VLOOKUP(A9,'Salary Calculation'!$A$2:$T$999,8,0),"") -> 40653547928 | F9: =IFERROR(VLOOKUP(C9,'Employees List'!$B$2:H999,6,0),"") -> SBI | G9: =IFERROR(VLOOKUP(A9,'Salary Calculation'!$A$2:$T$999,7,0),"") -> 4032.0312 | H9: ON HOLD
A10: CPIEMP009 | B10: =IFERROR(VLOOKUP(A10,'Salary Calculation'!A10:F1007,2,0),"") -> April | C10: =IFERROR(VLOOKUP(A10,'Salary Calculation'!$A$2:$T$999,3,0),"") -> PR 12 | D10: =IFERROR(VLOOKUP(A10,'Salary Calculation'!$A$2:$T$999,6,0),"") -> PINU | E10: =IFERROR(VLOOKUP(A10,'Salary Calculation'!$A$2:$T$999,8,0),"") -> 8131010000018814 | F10: =IFERROR(VLOOKUP(C10,'Employees List'!$B$2:H999,6,0),"") -> DBS | G10: =IFERROR(VLOOKUP(A10,'Salary Calculation'!$A$2:$T$999,7,0),"") -> 4298.7656 | H10: ON HOLD
A11: CPIEMP010 | B11: =IFERROR(VLOOKUP(A11,'Salary Calculation'!A11:F1008,2,0),"") -> April | C11: =IFERROR(VLOOKUP(A11,'Salary Calculation'!$A$2:$T$999,3,0),"") -> PR 05 | D11: =IFERROR(VLOOKUP(A11,'Salary Calculation'!$A$2:$T$999,6,0),"") -> SANJAY BAGARTTI.K | E11: =IFERROR(VLOOKUP(A11,'Salary Calculation'!$A$2:$T$999,8,0),"") -> 8131010000021225 | F11: =IFERROR(VLOOKUP(C11,'Employees List'!$B$2:H999,6,0),"") -> DBS | G11: =IFERROR(VLOOKUP(A11,'Salary Calculation'!$A$2:$T$999,7,0),"") -> 20811.484 | H11: PAID | I11: April
A12: CPIEMP011 | B12: =IFERROR(VLOOKUP(A12,'Salary Calculation'!A12:F1009,2,0),"") -> April | C12: =IFERROR(VLOOKUP(A12,'Salary Calculation'!$A$2:$T$999,3,0),"") -> PR 03 | D12: =IFERROR(VLOOKUP(A12,'Salary Calculation'!$A$2:$T$999,6,0),"") -> ADHIKARI BALIA.A | E12: =IFERROR(VLOOKUP(A12,'Salary Calculation'!$A$2:$T$999,8,0),"") -> 8131010000018948 | F12: =IFERROR(VLOOKUP(C12,'Employees List'!$B$2:H999,6,0),"") -> DBS | G12: =IFERROR(VLOOKUP(A12,'Salary Calculation'!$A$2:$T$999,7,0),"") -> 1542.6146 | H12: PAID | I12: April
A13: CPIEMP012 | B13: =IFERROR(VLOOKUP(A13,'Salary Calculation'!A13:F1010,2,0),"") -> April | C13: =IFERROR(VLOOKUP(A13,'Salary Calculation'!$A$2:$T$999,3,0),"") -> PR 04 | D13: =IFERROR(VLOOKUP(A13,'Salary Calculation'!$A$2:$T$999,6,0),"") -> RUPESH KISAN | E13: =IFERROR(VLOOKUP(A13,'Salary Calculation'!$A$2:$T$999,8,0),"") -> 411002010024591 | F13: =IFERROR(VLOOKUP(C13,'Employees List'!$B$2:H999,6,0),"") -> UBI | G13: =IFERROR(VLOOKUP(A13,'Salary Calculation'!$A$2:$T$999,7,0),"") -> 4236.2083 | H13: PAID | I13: April
A14: CPIEMP013 | B14: =IFERROR(VLOOKUP(A14,'Salary Calculation'!A14:F1011,2,0),"") -> April | C14: =IFERROR(VLOOKUP(A14,'Salary Calculation'!$A$2:$T$999,3,0),"") -> PR 21 | D14: =IFERROR(VLOOKUP(A14,'Salary Calculation'!$A$2:$T$999,6,0),"") -> LIPAN | E14: =IFERROR(VLOOKUP(A14,'Salary Calculation'!$A$2:$T$999,8,0),"") -> 8131010000018957 | F14: =IFERROR(VLOOKUP(C14,'Employees List'!$B$2:H999,6,0),"") -> DBS | G14: =IFERROR(VLOOKUP(A14,'Salary Calculation'!$A$2:$T$999,7,0),"") -> 365.17708 | H14: PAID
A15: CPIEMP014 | B15: =IFERROR(VLOOKUP(A15,'Salary Calculation'!A15:F1012,2,0),"") -> April | C15: =IFERROR(VLOOKUP(A15,'Salary Calculation'!$A$2:$T$999,3,0),"") -> PR 24 | D15: =IFERROR(VLOOKUP(A15,'Salary Calculation'!$A$2:$T$999,6,0),"") -> NILAMANI KISAN.B | E15: =IFERROR(VLOOKUP(A15,'Salary Calculation'!$A$2:$T$999,8,0),"") -> 38254473147 | F15: =IFERROR(VLOOKUP(C15,'Employees List'!$B$2:H999,6,0),"") -> SBI | G15: =IFERROR(VLOOKUP(A15,'Salary Calculation'!$A$2:$T$999,7,0),"") -> 14143.125 | H15: PAID | I15: April
A16: CPIEMP015 | B16: =IFERROR(VLOOKUP(A16,'Salary Calculation'!A16:F1013,2,0),"") -> May | C16: =IFERROR(VLOOKUP(A16,'Salary Calculation'!$A$2:$T$999,3,0),"") -> AC 01 | D16: =IFERROR(VLOOKUP(A16,'Salary Calculation'!$A$2:$T$999,6,0),"") -> BHUVANESHWARAN.V | E16: =IFERROR(VLOOKUP(A16,'Salary Calculation'!$A$2:$T$999,8,0),"") -> 500101011548924 | F16: =IFERROR(VLOOKUP(C16,'Employees List'!$B$2:H999,6,0),"") -> CUB | G16: =IFERROR(VLOOKUP(A16,'Salary Calculation'!$A$2:$T$999,7,0),"") -> 66900 | H16: PAID | I16: 45782
A17: CPIEMP016 | B17: =IFERROR(VLOOKUP(A17,'Salary Calculation'!A17:F1014,2,0),"") -> May | C17: =IFERROR(VLOOKUP(A17,'Salary Calculation'!$A$2:$T$999,3,0),"") -> AC 02 | D17: =IFERROR(VLOOKUP(A17,'Salary Calculation'!$A$2:$T$999,6,0),"") -> THIRIPURA SUNDARI.R | E17: =IFERROR(VLOOKUP(A17,'Salary Calculation'!$A$2:$T$999,8,0),"") -> 8131010000016977 | F17: =IFERROR(VLOOKUP(C17,'Employees List'!$B$2:H999,6,0),"") -> DBS | G17: =IFERROR(VLOOKUP(A17,'Salary Calculation'!$A$2:$T$999,7,0),"") -> 23294.135 | H17: PAID | I17: 45782
A18: CPIEMP017 | B18: =IFERROR(VLOOKUP(A18,'Salary Calculation'!A18:F1015,2,0),"") -> May | C18: =IFERROR(VLOOKUP(A18,'Salary Calculation'!$A$2:$T$999,3,0),"") -> PR 02 | D18: =IFERROR(VLOOKUP(A18,'Salary Calculation'!$A$2:$T$999,6,0),"") -> GANESH | E18: =IFERROR(VLOOKUP(A18,'Salary Calculation'!$A$2:$T$999,8,0),"") -> 8811010012054879 | F18: =IFERROR(VLOOKUP(C18,'Employees List'!$B$2:H999,6,0),"") -> DBS | G18: =IFERROR(VLOOKUP(A18,'Salary Calculation'!$A$2:$T$999,7,0),"") -> 19955.453 | H18: PAID | I18: 45782
A19: CPIEMP018 | B19: =IFERROR(VLOOKUP(A19,'Salary Calculation'!A19:F1016,2,0),"") -> May | C19: =IFERROR(VLOOKUP(A19,'Salary Calculation'!$A$2:$T$999,3,0),"") -> DR 01 | D19: =IFERROR(VLOOKUP(A19,'Salary Calculation'!$A$2:$T$999,6,0),"") -> ILAMATHIVANAN.S | E19: =IFERROR(VLOOKUP(A19,'Salary Calculation'!$A$2:$T$999,8,0),"") -> 8131010000016986 | F19: =IFERROR(VLOOKUP(C19,'Employees List'!$B$2:H999,6,0),"") -> DBS | G19: =IFERROR(VLOOKUP(A19,'Salary Calculation'!$A$2:$T$999,7,0),"") -> 29189.105 | H19: PAID | I19: 45782
A20: CPIEMP019 | B20: =IFERROR(VLOOKUP(A20,'Salary Calculation'!A20:F1017,2,0),"") -> May | C20: =IFERROR(VLOOKUP(A20,'Salary Calculation'!$A$2:$T$999,3,0),"") -> PR 03 | D20: =IFERROR(VLOOKUP(A20,'Salary Calculation'!$A$2:$T$999,6,0),"") -> ADHIKARI BALIA.A | E20: =IFERROR(VLOOKUP(A20,'Salary Calculation'!$A$2:$T$999,8,0),"") -> 8131010000018948 | F20: =IFERROR(VLOOKUP(C20,'Employees List'!$B$2:H999,6,0),"") -> DBS | G20: =IFERROR(VLOOKUP(A20,'Salary Calculation'!$A$2:$T$999,7,0),"") -> 19440.861 | H20: PAID | I20: 45782
A21: CPIEMP020 | B21: =IFERROR(VLOOKUP(A21,'Salary Calculation'!A21:F1018,2,0),"") -> May | C21: =IFERROR(VLOOKUP(A21,'Salary Calculation'!$A$2:$T$999,3,0),"") -> PR 04 | D21: =IFERROR(VLOOKUP(A21,'Salary Calculation'!$A$2:$T$999,6,0),"") -> RUPESH KISAN | E21: =IFERROR(VLOOKUP(A21,'Salary Calculation'!$A$2:$T$999,8,0),"") -> 411002010024591 | F21: =IFERROR(VLOOKUP(C21,'Employees List'!$B$2:H999,6,0),"") -> UBI | G21: =IFERROR(VLOOKUP(A21,'Salary Calculation'!$A$2:$T$999,7,0),"") -> 21018.9 | H21: PAID | I21: 45782 | J21: 45782
A22: CPIEMP021 | B22: =IFERROR(VLOOKUP(A22,'Salary Calculation'!A22:F1019,2,0),"") -> May | C22: =IFERROR(VLOOKUP(A22,'Salary Calculation'!$A$2:$T$999,3,0),"") -> PR 05 | D22: =IFERROR(VLOOKUP(A22,'Salary Calculation'!$A$2:$T$999,6,0),"") -> SANJAY BAGARTTI.K | E22: =IFERROR(VLOOKUP(A22,'Salary Calculation'!$A$2:$T$999,8,0),"") -> 8131010000021225 | F22: =IFERROR(VLOOKUP(C22,'Employees List'!$B$2:H999,6,0),"") -> DBS | G22: =IFERROR(VLOOKUP(A22,'Salary Calculation'!$A$2:$T$999,7,0),"") -> 25501.647 | H22: PAID | I22: 45782
A23: CPIEMP022 | B23: =IFERROR(VLOOKUP(A23,'Salary Calculation'!A23:F1020,2,0),"") -> May | C23: =IFERROR(VLOOKUP(A23,'Salary Calculation'!$A$2:$T$999,3,0),"") -> PR 21 | D23: =IFERROR(VLOOKUP(A23,'Salary Calculation'!$A$2:$T$999,6,0),"") -> LIPAN | E23: =IFERROR(VLOOKUP(A23,'Salary Calculation'!$A$2:$T$999,8,0),"") -> 8131010000018957 | F23: =IFERROR(VLOOKUP(C23,'Employees List'!$B$2:H999,6,0),"") -> DBS | G23: =IFERROR(VLOOKUP(A23,'Salary Calculation'!$A$2:$T$999,7,0),"") -> 20468.223 | H23: PAID | I23: 45782
A24: CPIEMP023 | B24: =IFERROR(VLOOKUP(A24,'Salary Calculation'!A24:F1021,2,0),"") -> May | C24: =IFERROR(VLOOKUP(A24,'Salary Calculation'!$A$2:$T$999,3,0),"") -> PR 07 | D24: =IFERROR(VLOOKUP(A24,'Salary Calculation'!$A$2:$T$999,6,0),"") -> AMMU.S | E24: =IFERROR(VLOOKUP(A24,'Salary Calculation'!$A$2:$T$999,8,0),"") -> 65801000040238 | F24: =IFERROR(VLOOKUP(C24,'Employees List'!$B$2:H999,6,0),"") -> IOB | G24: =IFERROR(VLOOKUP(A24,'Salary Calculation'!$A$2:$T$999,7,0),"") -> 11603.245 | H24: PAID | I24: 45782
A25: CPIEMP024 | B25: =IFERROR(VLOOKUP(A25,'Salary Calculation'!A25:F1022,2,0),"") -> May | C25: =IFERROR(VLOOKUP(A25,'Salary Calculation'!$A$2:$T$999,3,0),"") -> PR 08 | D25: =IFERROR(VLOOKUP(A25,'Salary Calculation'!$A$2:$T$999,6,0),"") -> REVATHI.S | E25: =IFERROR(VLOOKUP(A25,'Salary Calculation'!$A$2:$T$999,8,0),"") -> 8131010000016995 | F25: =IFERROR(VLOOKUP(C25,'Employees List'!$B$2:H999,6,0),"") -> DBS | G25: =IFERROR(VLOOKUP(A25,'Salary Calculation'!$A$2:$T$999,7,0),"") -> 11289.944 | H25: PAID | I25: 45782
A26: CPIEMP025 | B26: =IFERROR(VLOOKUP(A26,'Salary Calculation'!A26:F1023,2,0),"") -> May | C26: =IFERROR(VLOOKUP(A26,'Salary Calculation'!$A$2:$T$999,3,0),"") -> AC 03 | D26: =IFERROR(VLOOKUP(A26,'Salary Calculation'!$A$2:$T$999,6,0),"") -> LEELAVATHI.M | E26: =IFERROR(VLOOKUP(A26,'Salary Calculation'!$A$2:$T$999,8,0),"") -> 8387010000017745 | F26: =IFERROR(VLOOKUP(C26,'Employees List'!$B$2:H999,6,0),"") -> DBS | G26: =IFERROR(VLOOKUP(A26,'Salary Calculation'!$A$2:$T$999,7,0),"") -> 13865.385 | H26: PAID | I26: 45782
A27: CPIEMP026 | B27: =IFERROR(VLOOKUP(A27,'Salary Calculation'!A27:F1024,2,0),"") -> May | C27: =IFERROR(VLOOKUP(A27,'Salary Calculation'!$A$2:$T$999,3,0),"") -> PR 24 | D27: =IFERROR(VLOOKUP(A27,'Salary Calculation'!$A$2:$T$999,6,0),"") -> NILAMANI KISAN.B | E27: =IFERROR(VLOOKUP(A27,'Salary Calculation'!$A$2:$T$999,8,0),"") -> 38254473147 | F27: =IFERROR(VLOOKUP(C27,'Employees List'!$B$2:H999,6,0),"") -> SBI | G27: =IFERROR(VLOOKUP(A27,'Salary Calculation'!$A$2:$T$999,7,0),"") -> 18863.903 | H27: PAID | I27: 45782
A28: CPIEMP027 | B28: =IFERROR(VLOOKUP(A28,'Salary Calculation'!A28:F1025,2,0),"") -> June | C28: =IFERROR(VLOOKUP(A28,'Salary Calculation'!$A$2:$T$999,3,0),"") -> AC 01 | D28: =IFERROR(VLOOKUP(A28,'Salary Calculation'!$A$2:$T$999,6,0),"") -> BHUVANESHWARAN.V | E28: =IFERROR(VLOOKUP(A28,'Salary Calculation'!$A$2:$T$999,8,0),"") -> 500101011548924 | F28: =IFERROR(VLOOKUP(C28,'Employees List'!$B$2:H999,6,0),"") -> CUB | G28: =IFERROR(VLOOKUP(A28,'Salary Calculation'!$A$2:$T$999,7,0),"") -> 66900 | H28: PAID
A29: CPIEMP028 | B29: =IFERROR(VLOOKUP(A29,'Salary Calculation'!A29:F1026,2,0),"") -> June | C29: =IFERROR(VLOOKUP(A29,'Salary Calculation'!$A$2:$T$999,3,0),"") -> AC 02 | D29: =IFERROR(VLOOKUP(A29,'Salary Calculation'!$A$2:$T$999,6,0),"") -> THIRIPURA SUNDARI.R | E29: =IFERROR(VLOOKUP(A29,'Salary Calculation'!$A$2:$T$999,8,0),"") -> 8131010000016977 | F29: =IFERROR(VLOOKUP(C29,'Employees List'!$B$2:H999,6,0),"") -> DBS | G29: =IFERROR(VLOOKUP(A29,'Salary Calculation'!$A$2:$T$999,7,0),"") -> 22815.094 | H29: PAID
A30: CPIEMP029 | B30: =IFERROR(VLOOKUP(A30,'Salary Calculation'!A30:F1027,2,0),"") -> June | C30: =IFERROR(VLOOKUP(A30,'Salary Calculation'!$A$2:$T$999,3,0),"") -> PR 02 | D30: =IFERROR(VLOOKUP(A30,'Salary Calculation'!$A$2:$T$999,6,0),"") -> GANESH | E30: =IFERROR(VLOOKUP(A30,'Salary Calculation'!$A$2:$T$999,8,0),"") -> 8811010012054879 | F30: =IFERROR(VLOOKUP(C30,'Employees List'!$B$2:H999,6,0),"") -> DBS | G30: =IFERROR(VLOOKUP(A30,'Salary Calculation'!$A$2:$T$999,7,0),"") -> 16190.401 | H30: PAID
A31: CPIEMP030 | B31: =IFERROR(VLOOKUP(A31,'Salary Calculation'!A31:F1028,2,0),"") -> June | C31: =IFERROR(VLOOKUP(A31,'Salary Calculation'!$A$2:$T$999,3,0),"") -> PR 01 | D31: =IFERROR(VLOOKUP(A31,'Salary Calculation'!$A$2:$T$999,6,0),"") -> VASANTHA.E | E31: =IFERROR(VLOOKUP(A31,'Salary Calculation'!$A$2:$T$999,8,0),"") -> 8131010000016959 | F31: =IFERROR(VLOOKUP(C31,'Employees List'!$B$2:H999,6,0),"") -> DBS | G31: =IFERROR(VLOOKUP(A31,'Salary Calculation'!$A$2:$T$999,7,0),"") -> 18522.531 | H31: PAID
A32: CPIEMP031 | B32: =IFERROR(VLOOKUP(A32,'Salary Calculation'!A32:F1029,2,0),"") -> June | C32: =IFERROR(VLOOKUP(A32,'Salary Calculation'!$A$2:$T$999,3,0),"") -> DR 01 | D32: =IFERROR(VLOOKUP(A32,'Salary Calculation'!$A$2:$T$999,6,0),"") -> ILAMATHIVANAN.S | E32: =IFERROR(VLOOKUP(A32,'Salary Calculation'!$A$2:$T$999,8,0),"") -> 8131010000016986 | F32: =IFERROR(VLOOKUP(C32,'Employees List'!$B$2:H999,6,0),"") -> DBS | G32: =IFERROR(VLOOKUP(A32,'Salary Calculation'!$A$2:$T$999,7,0),"") -> 13550.953 | H32: PAID
A33: CPIEMP032 | B33: =IFERROR(VLOOKUP(A33,'Salary Calculation'!A33:F1030,2,0),"") -> June | C33: =IFERROR(VLOOKUP(A33,'Salary Calculation'!$A$2:$T$999,3,0),"") -> PR 03 | D33: =IFERROR(VLOOKUP(A33,'Salary Calculation'!$A$2:$T$999,6,0),"") -> ADHIKARI BALIA.A | E33: =IFERROR(VLOOKUP(A33,'Salary Calculation'!$A$2:$T$999,8,0),"") -> 8131010000018948 | F33: =IFERROR(VLOOKUP(C33,'Employees List'!$B$2:H999,6,0),"") -> DBS | G33: =IFERROR(VLOOKUP(A33,'Salary Calculation'!$A$2:$T$999,7,0),"") -> 19515.417 | H33: PAID
A34: CPIEMP033 | B34: =IFERROR(VLOOKUP(A34,'Salary Calculation'!A34:F1031,2,0),"") -> June | C34: =IFERROR(VLOOKUP(A34,'Salary Calculation'!$A$2:$T$999,3,0),"") -> PR 04 | D34: =IFERROR(VLOOKUP(A34,'Salary Calculation'!$A$2:$T$999,6,0),"") -> RUPESH KISAN | E34: =IFERROR(VLOOKUP(A34,'Salary Calculation'!$A$2:$T$999,8,0),"") -> 411002010024591 | F34: =IFERROR(VLOOKUP(C34,'Employees List'!$B$2:H999,6,0),"") -> UBI | G34: =IFERROR(VLOOKUP(A34,'Salary Calculation'!$A$2:$T$999,7,0),"") -> 19370.292 | H34: PAID
A35: CPIEMP034 | B35: =IFERROR(VLOOKUP(A35,'Salary Calculation'!A35:F1032,2,0),"") -> June | C35: =IFERROR(VLOOKUP(A35,'Salary Calculation'!$A$2:$T$999,3,0),"") -> PR 05 | D35: =IFERROR(VLOOKUP(A35,'Salary Calculation'!$A$2:$T$999,6,0),"") -> SANJAY BAGARTTI.K | E35: =IFERROR(VLOOKUP(A35,'Salary Calculation'!$A$2:$T$999,8,0),"") -> 8131010000021225 | F35: =IFERROR(VLOOKUP(C35,'Employees List'!$B$2:H999,6,0),"") -> DBS | G35: =IFERROR(VLOOKUP(A35,'Salary Calculation'!$A$2:$T$999,7,0),"") -> 20821.823 | H35: PAID
A36: CPIEMP035 | B36: =IFERROR(VLOOKUP(A36,'Salary Calculation'!A36:F1033,2,0),"") -> June | C36: =IFERROR(VLOOKUP(A36,'Salary Calculation'!$A$2:$T$999,3,0),"") -> PR 21 | D36: =IFERROR(VLOOKUP(A36,'Salary Calculation'!$A$2:$T$999,6,0),"") -> LIPAN | E36: =IFERROR(VLOOKUP(A36,'Salary Calculation'!$A$2:$T$999,8,0),"") -> 8131010000018957 | F36: =IFERROR(VLOOKUP(C36,'Employees List'!$B$2:H999,6,0),"") -> DBS | G36: =IFERROR(VLOOKUP(A36,'Salary Calculation'!$A$2:$T$999,7,0),"") -> 21456.609 | H36: PAID
A37: CPIEMP036 | B37: =IFERROR(VLOOKUP(A37,'Salary Calculation'!A37:F1034,2,0),"") -> June | C37: =IFERROR(VLOOKUP(A37,'Salary Calculation'!$A$2:$T$999,3,0),"") -> PR 24 | D37: =IFERROR(VLOOKUP(A37,'Salary Calculation'!$A$2:$T$999,6,0),"") -> NILAMANI KISAN.B | E37: =IFERROR(VLOOKUP(A37,'Salary Calculation'!$A$2:$T$999,8,0),"") -> 38254473147 | F37: =IFERROR(VLOOKUP(C37,'Employees List'!$B$2:H999,6,0),"") -> SBI | G37: =IFERROR(VLOOKUP(A37,'Salary Calculation'!$A$2:$T$999,7,0),"") -> 9528 | H37: PAID
A38: CPIEMP037 | B38: =IFERROR(VLOOKUP(A38,'Salary Calculation'!A38:F1035,2,0),"") -> June | C38: =IFERROR(VLOOKUP(A38,'Salary Calculation'!$A$2:$T$999,3,0),"") -> PR 07 | D38: =IFERROR(VLOOKUP(A38,'Salary Calculation'!$A$2:$T$999,6,0),"") -> AMMU.S | E38: =IFERROR(VLOOKUP(A38,'Salary Calculation'!$A$2:$T$999,8,0),"") -> 65801000040238 | F38: =IFERROR(VLOOKUP(C38,'Employees List'!$B$2:H999,6,0),"") -> IOB | G38: =IFERROR(VLOOKUP(A38,'Salary Calculation'!$A$2:$T$999,7,0),"") -> 12648.172 | H38: PAID
